[
  {
    "name": "zackrawrr",
    "game": "Just Chatting",
    "viewers": "49843"
  },
  {
    "name": "eliasn97",
    "game": "Minecraft",
    "viewers": "47490"
  },
  {
    "name": "n3on",
    "game": "Just Chatting",
    "viewers": "36753"
  },
  {
    "name": "shroud",
    "game": "Battlefield REDSEC",
    "viewers": "33160"
  },
  {
    "name": "papaplatte",
    "game": "Minecraft",
    "viewers": "31221"
  },
  {
    "name": "hasanabi",
    "game": "Just Chatting",
    "viewers": "28920"
  },
  {
    "name": "jynxzi",
    "game": "Clash Royale",
    "viewers": "26625"
  },
  {
    "name": "anyme023",
    "game": "EA Sports FC 26",
    "viewers": "26189"
  },
  {
    "name": "bastighg",
    "game": "Minecraft",
    "viewers": "23496"
  },
  {
    "name": "xqc",
    "game": "Just Chatting",
    "viewers": "21746"
  },
  {
    "name": "jasontheween",
    "game": "Clash Royale",
    "viewers": "20414"
  },
  {
    "name": "stableronaldo",
    "game": "Just Chatting",
    "viewers": "18231"
  },
  {
    "name": "lacy",
    "game": "Just Chatting",
    "viewers": "18089"
  },
  {
    "name": "ilrossopiubelloditwitch",
    "game": "Just Chatting",
    "viewers": "14699"
  },
  {
    "name": "cameliaaa92",
    "game": "Just Chatting",
    "viewers": "14083"
  },
  {
    "name": "alanzoka",
    "game": "DOCTOR VISCERA",
    "viewers": "13730"
  },
  {
    "name": "noway4u_sir",
    "game": "League of Legends",
    "viewers": "13158"
  },
  {
    "name": "yourragegaming",
    "game": "Just Chatting",
    "viewers": "11982"
  },
  {
    "name": "youladecadd",
    "game": "Grand Theft Auto V",
    "viewers": "10695"
  },
  {
    "name": "domingo",
    "game": "Crusader Kings III",
    "viewers": "10256"
  },
  {
    "name": "lord_kebun",
    "game": "Grand Theft Auto V",
    "viewers": "9718"
  },
  {
    "name": "valkyrae",
    "game": "Fortnite",
    "viewers": "9577"
  },
  {
    "name": "krokoboss",
    "game": "Minecraft",
    "viewers": "9213"
  },
  {
    "name": "smallant",
    "game": "Pokémon",
    "viewers": "9124"
  },
  {
    "name": "silvername",
    "game": "Megabonk",
    "viewers": "8893"
  },
  {
    "name": "angryginge13",
    "game": "RV There Yet?",
    "viewers": "8846"
  },
  {
    "name": "antoinedaniel",
    "game": "Crusader Kings III",
    "viewers": "8361"
  },
  {
    "name": "fontinnelerj",
    "game": "Just Chatting",
    "viewers": "8235"
  },
  {
    "name": "joe_bartolozzi",
    "game": "Clash Royale",
    "viewers": "8119"
  },
  {
    "name": "schradin",
    "game": "Minecraft",
    "viewers": "7217"
  },
  {
    "name": "summit1g",
    "game": "Battlefield REDSEC",
    "viewers": "6784"
  },
  {
    "name": "adapt",
    "game": "Just Chatting",
    "viewers": "6603"
  },
  {
    "name": "marcomerrino",
    "game": "Just Chatting",
    "viewers": "6572"
  },
  {
    "name": "xaryu",
    "game": "World of Warcraft",
    "viewers": "6319"
  },
  {
    "name": "therealmarzaa",
    "game": "Super Mario Party Jamboree",
    "viewers": "6134"
  },
  {
    "name": "controcalcio__",
    "game": "Sports",
    "viewers": "6091"
  },
  {
    "name": "elxokas",
    "game": "Escape from Duckov",
    "viewers": "5882"
  },
  {
    "name": "stray228",
    "game": "Dota 2",
    "viewers": "5659"
  },
  {
    "name": "leva2k",
    "game": "Just Chatting",
    "viewers": "5607"
  },
  {
    "name": "h2p_gucio",
    "game": "MISERY",
    "viewers": "5484"
  },
  {
    "name": "lydiaviolet",
    "game": "Just Chatting",
    "viewers": "5416"
  },
  {
    "name": "waolol1",
    "game": "League of Legends",
    "viewers": "5261"
  },
  {
    "name": "bonjwa",
    "game": "Super Fantasy Kingdom",
    "viewers": "5206"
  },
  {
    "name": "squeex",
    "game": "Plants vs. Zombies 2 Gardendless",
    "viewers": "5157"
  },
  {
    "name": "manuuxo",
    "game": "Olympic Games Tokyo 2020: The Official Video Game",
    "viewers": "5022"
  },
  {
    "name": "rachtaz",
    "game": "Hunt: Showdown 1896",
    "viewers": "4752"
  },
  {
    "name": "extraemily",
    "game": "Just Chatting",
    "viewers": "4580"
  },
  {
    "name": "justinbieber",
    "game": "Just Chatting",
    "viewers": "4551"
  },
  {
    "name": "s0mcs",
    "game": "Battlefield REDSEC",
    "viewers": "4539"
  },
  {
    "name": "locklear",
    "game": "Far Far West",
    "viewers": "4537"
  },
  {
    "name": "bisteconee",
    "game": "Just Chatting",
    "viewers": "4503"
  },
  {
    "name": "arrowcs",
    "game": "Counter-Strike",
    "viewers": "4366"
  },
  {
    "name": "oliviamonroe",
    "game": "Just Chatting",
    "viewers": "4197"
  },
  {
    "name": "forever",
    "game": "Minecraft",
    "viewers": "4193"
  },
  {
    "name": "mooda",
    "game": "VALORANT",
    "viewers": "3952"
  },
  {
    "name": "officermesser",
    "game": "Grand Theft Auto V",
    "viewers": "3936"
  },
  {
    "name": "marlon",
    "game": "Just Chatting",
    "viewers": "3807"
  },
  {
    "name": "imperialhal__",
    "game": "Apex Legends",
    "viewers": "3796"
  },
  {
    "name": "xop0",
    "game": "Dispatch",
    "viewers": "3697"
  },
  {
    "name": "enzzai",
    "game": "Pools, Hot Tubs, and Beaches",
    "viewers": "3682"
  },
  {
    "name": "kingwoolz",
    "game": "The Mortuary Assistant",
    "viewers": "3655"
  },
  {
    "name": "admiralbahroo",
    "game": "Escape from Duckov",
    "viewers": "3629"
  },
  {
    "name": "sonwabileovii",
    "game": "Just Chatting",
    "viewers": "3590"
  },
  {
    "name": "jeefhs",
    "game": "Hearthstone",
    "viewers": "3547"
  },
  {
    "name": "laranity",
    "game": "Guild Wars 2",
    "viewers": "3540"
  },
  {
    "name": "im_dontai",
    "game": "Just Chatting",
    "viewers": "3516"
  },
  {
    "name": "erobb221",
    "game": "Just Chatting",
    "viewers": "3515"
  },
  {
    "name": "fubgun",
    "game": "Path of Exile",
    "viewers": "3440"
  },
  {
    "name": "bonnie",
    "game": "Just Chatting",
    "viewers": "3432"
  },
  {
    "name": "robinsongz",
    "game": "Teamfight Tactics",
    "viewers": "3338"
  },
  {
    "name": "doublelift",
    "game": "League of Legends",
    "viewers": "3290"
  },
  {
    "name": "stonemountain64",
    "game": "Battlefield REDSEC",
    "viewers": "3247"
  },
  {
    "name": "chibidoki",
    "game": "Just Chatting",
    "viewers": "3244"
  },
  {
    "name": "gabepeixe",
    "game": "Just Chatting",
    "viewers": "3201"
  },
  {
    "name": "kaysan",
    "game": "Just Chatting",
    "viewers": "3189"
  },
  {
    "name": "ybicanoooobov",
    "game": "Dota 2",
    "viewers": "3159"
  },
  {
    "name": "gaechkatm",
    "game": "Dota 2",
    "viewers": "3157"
  },
  {
    "name": "nooreax",
    "game": "Minecraft",
    "viewers": "3100"
  },
  {
    "name": "grubby",
    "game": "Darkest Dungeon",
    "viewers": "3083"
  },
  {
    "name": "letshugotv",
    "game": "Minecraft",
    "viewers": "3080"
  },
  {
    "name": "ravusssss",
    "game": "Just Chatting",
    "viewers": "3034"
  },
  {
    "name": "sinder",
    "game": "Wolf Mate",
    "viewers": "3017"
  },
  {
    "name": "diyrachyo_2613",
    "game": "Dota 2",
    "viewers": "3015"
  },
  {
    "name": "stegi",
    "game": "Minecraft",
    "viewers": "3002"
  },
  {
    "name": "itachi_rl",
    "game": "VALORANT",
    "viewers": "2998"
  },
  {
    "name": "silky",
    "game": "Just Chatting",
    "viewers": "2939"
  },
  {
    "name": "etostark__",
    "game": "Just Chatting",
    "viewers": "2938"
  },
  {
    "name": "repaz",
    "game": "Minecraft",
    "viewers": "2923"
  },
  {
    "name": "goodtimeswithscar",
    "game": "Just Chatting",
    "viewers": "2894"
  },
  {
    "name": "dmf_kyochan",
    "game": "Dragon Quest I & II HD-2D Remake",
    "viewers": "2871"
  },
  {
    "name": "rubini",
    "game": "Tibia",
    "viewers": "2809"
  },
  {
    "name": "aspen",
    "game": "Overwatch 2",
    "viewers": "2757"
  },
  {
    "name": "kerrty",
    "game": "Hunt: Showdown 1896",
    "viewers": "2750"
  },
  {
    "name": "nissaxter",
    "game": "League of Legends",
    "viewers": "2742"
  },
  {
    "name": "penta",
    "game": "Just Chatting",
    "viewers": "2695"
  },
  {
    "name": "agraelus",
    "game": "Just Chatting",
    "viewers": "2695"
  },
  {
    "name": "tdvr_gaming",
    "game": "Ghosts of Tabor",
    "viewers": "2675"
  },
  {
    "name": "mightyteapot",
    "game": "Guild Wars 2",
    "viewers": "2624"
  },
  {
    "name": "skipnho",
    "game": "Just Chatting",
    "viewers": "2618"
  },
  {
    "name": "mrdzinold",
    "game": "RV There Yet?",
    "viewers": "2617"
  },
  {
    "name": "rivenzi",
    "game": "Crusader Kings III",
    "viewers": "2598"
  },
  {
    "name": "i_olga",
    "game": "I'm Only Sleeping",
    "viewers": "2587"
  },
  {
    "name": "gensyxa",
    "game": "Just Chatting",
    "viewers": "2530"
  },
  {
    "name": "esfandtv",
    "game": "Just Chatting",
    "viewers": "2520"
  },
  {
    "name": "jay3",
    "game": "Marvel Rivals",
    "viewers": "2502"
  },
  {
    "name": "morphilina",
    "game": "Just Chatting",
    "viewers": "2487"
  },
  {
    "name": "niekbeats",
    "game": "Minecraft",
    "viewers": "2443"
  },
  {
    "name": "rtgame",
    "game": "Cloverpit",
    "viewers": "2432"
  },
  {
    "name": "velja_lol",
    "game": "League of Legends",
    "viewers": "2429"
  },
  {
    "name": "baz1221",
    "game": "Counter-Strike",
    "viewers": "2413"
  },
  {
    "name": "swagg",
    "game": "Battlefield REDSEC",
    "viewers": "2406"
  },
  {
    "name": "aunkere",
    "game": "Counter-Strike",
    "viewers": "2364"
  },
  {
    "name": "w33haa",
    "game": "Dota 2",
    "viewers": "2335"
  },
  {
    "name": "sykkuno",
    "game": "Until Dawn",
    "viewers": "2335"
  },
  {
    "name": "ocwsport",
    "game": "Sports",
    "viewers": "2334"
  },
  {
    "name": "criken",
    "game": "DEVOUR",
    "viewers": "2332"
  },
  {
    "name": "deadlocknightshift",
    "game": "Deadlock",
    "viewers": "2278"
  },
  {
    "name": "faxuty",
    "game": "Just Chatting",
    "viewers": "2277"
  },
  {
    "name": "bawkbasoup",
    "game": "Resident Evil 2",
    "viewers": "2260"
  },
  {
    "name": "avoidingthepuddle",
    "game": "The Evil Within",
    "viewers": "2256"
  },
  {
    "name": "maudado",
    "game": "Minecraft",
    "viewers": "2212"
  },
  {
    "name": "sardaco",
    "game": "Old School RuneScape",
    "viewers": "2212"
  },
  {
    "name": "huskerrs",
    "game": "Battlefield REDSEC",
    "viewers": "2202"
  },
  {
    "name": "worldofwarships",
    "game": "World of Warships",
    "viewers": "2169"
  },
  {
    "name": "bigpuffer",
    "game": "Dispatch",
    "viewers": "2166"
  },
  {
    "name": "polispol1",
    "game": "Minecraft",
    "viewers": "2112"
  },
  {
    "name": "kurt0411",
    "game": "Football Manager 26",
    "viewers": "2105"
  },
  {
    "name": "skyrroztv",
    "game": "Battlefield REDSEC",
    "viewers": "2079"
  },
  {
    "name": "lobanjicaa",
    "game": "Just Chatting",
    "viewers": "2077"
  },
  {
    "name": "slotshub",
    "game": "Slots",
    "viewers": "2056"
  },
  {
    "name": "clym",
    "game": "Minecraft",
    "viewers": "2037"
  },
  {
    "name": "sloty45",
    "game": "Slots",
    "viewers": "2029"
  },
  {
    "name": "fallenshadow",
    "game": "Postal 2",
    "viewers": "1984"
  },
  {
    "name": "johnstone",
    "game": "Pokémon Legends: Z-A",
    "viewers": "1979"
  },
  {
    "name": "bagherajones",
    "game": "Crusader Kings III",
    "viewers": "1974"
  },
  {
    "name": "sidneyeweka",
    "game": "Minecraft",
    "viewers": "1973"
  },
  {
    "name": "aenot",
    "game": "Grand Theft Auto V",
    "viewers": "1965"
  },
  {
    "name": "boxbox",
    "game": "Teamfight Tactics",
    "viewers": "1960"
  },
  {
    "name": "vexoria_the_suneater",
    "game": "Special Events",
    "viewers": "1957"
  },
  {
    "name": "nicistemmler",
    "game": "Minecraft",
    "viewers": "1910"
  },
  {
    "name": "tobinatorlp",
    "game": "Just Chatting",
    "viewers": "1888"
  },
  {
    "name": "judah_xx",
    "game": "Just Chatting",
    "viewers": "1886"
  },
  {
    "name": "angledroit",
    "game": "ELDEN RING",
    "viewers": "1881"
  },
  {
    "name": "ray",
    "game": "The Legend of Zelda: Majora's Mask",
    "viewers": "1857"
  },
  {
    "name": "muriloso",
    "game": "Just Chatting",
    "viewers": "1852"
  },
  {
    "name": "ereklo_game",
    "game": "MapleStory",
    "viewers": "1834"
  },
  {
    "name": "pieface23",
    "game": "EA Sports FC 26",
    "viewers": "1819"
  },
  {
    "name": "honeypuu",
    "game": "Minecraft",
    "viewers": "1794"
  },
  {
    "name": "shisheyu",
    "game": "The Outer Worlds 2",
    "viewers": "1757"
  },
  {
    "name": "kerios",
    "game": "League of Legends",
    "viewers": "1751"
  },
  {
    "name": "bobross",
    "game": "Art",
    "viewers": "1743"
  },
  {
    "name": "kindalegoat",
    "game": "",
    "viewers": "1731"
  },
  {
    "name": "gamegladiatorgg",
    "game": "Slots",
    "viewers": "1723"
  },
  {
    "name": "renekreher",
    "game": "IRL",
    "viewers": "1719"
  },
  {
    "name": "zoomaa",
    "game": "Grand Theft Auto V",
    "viewers": "1714"
  },
  {
    "name": "ravshanbtw",
    "game": "Dota 2",
    "viewers": "1687"
  },
  {
    "name": "masondota2",
    "game": "Dota 2",
    "viewers": "1669"
  },
  {
    "name": "lilaggy",
    "game": "ELDEN RING",
    "viewers": "1661"
  },
  {
    "name": "diazbiffle",
    "game": "Battlefield REDSEC",
    "viewers": "1659"
  },
  {
    "name": "fuxelbau",
    "game": "Minecraft",
    "viewers": "1657"
  },
  {
    "name": "mohleking",
    "game": "EA Sports FC 26",
    "viewers": "1654"
  },
  {
    "name": "godmota",
    "game": "Slots",
    "viewers": "1649"
  },
  {
    "name": "sacy",
    "game": "Just Chatting",
    "viewers": "1638"
  },
  {
    "name": "strippin",
    "game": "DEVOUR",
    "viewers": "1632"
  },
  {
    "name": "chatterbox",
    "game": "Grand Theft Auto V",
    "viewers": "1632"
  },
  {
    "name": "hudsonamorm777",
    "game": "Virtual Casino",
    "viewers": "1618"
  },
  {
    "name": "getflakked",
    "game": "League of Legends",
    "viewers": "1610"
  },
  {
    "name": "itsspoit",
    "game": "Tom Clancy's Rainbow Six Siege X",
    "viewers": "1585"
  },
  {
    "name": "gaules",
    "game": "Human: Fall Flat",
    "viewers": "1575"
  },
  {
    "name": "onlyjson",
    "game": "Grand Theft Auto V",
    "viewers": "1570"
  },
  {
    "name": "zigueira",
    "game": "Battlefield REDSEC",
    "viewers": "1564"
  },
  {
    "name": "smzinho",
    "game": "Virtual Casino",
    "viewers": "1563"
  },
  {
    "name": "notquitelikedub",
    "game": "IRL",
    "viewers": "1562"
  },
  {
    "name": "dakillzor",
    "game": "World of Tanks",
    "viewers": "1552"
  },
  {
    "name": "mehdoche",
    "game": "Grand Theft Auto V",
    "viewers": "1551"
  },
  {
    "name": "axtlol",
    "game": "Battlefield REDSEC",
    "viewers": "1550"
  },
  {
    "name": "jabroni_mike",
    "game": "HELLMART",
    "viewers": "1548"
  },
  {
    "name": "fobm4ster",
    "game": "Wuthering Waves",
    "viewers": "1545"
  },
  {
    "name": "nikos",
    "game": "Grand Theft Auto V",
    "viewers": "1542"
  },
  {
    "name": "delaruetv",
    "game": "Just Chatting",
    "viewers": "1537"
  },
  {
    "name": "olhaogab",
    "game": "VALORANT",
    "viewers": "1534"
  },
  {
    "name": "sheviiioficial",
    "game": "Just Chatting",
    "viewers": "1519"
  },
  {
    "name": "haiset",
    "game": "Escape Simulator 2",
    "viewers": "1519"
  },
  {
    "name": "otzdarva",
    "game": "ELDEN RING NIGHTREIGN",
    "viewers": "1514"
  },
  {
    "name": "kiliratv",
    "game": "Escape the Backrooms",
    "viewers": "1500"
  },
  {
    "name": "slimeirl",
    "game": "League of Legends",
    "viewers": "1491"
  },
  {
    "name": "nohandsgamer",
    "game": "Hearthstone",
    "viewers": "1481"
  },
  {
    "name": "kaydop",
    "game": "Rocket League",
    "viewers": "1473"
  },
  {
    "name": "irissiri129",
    "game": "League of Legends",
    "viewers": "1472"
  },
  {
    "name": "quarterjade",
    "game": "Just Chatting",
    "viewers": "1468"
  },
  {
    "name": "lolitofdez",
    "game": "Rust",
    "viewers": "1456"
  },
  {
    "name": "zubarefff_slots_8618400",
    "game": "",
    "viewers": "1449"
  },
  {
    "name": "leutum",
    "game": "Just Chatting",
    "viewers": "1447"
  },
  {
    "name": "hakaiwrld",
    "game": "Garry's Mod",
    "viewers": "1443"
  },
  {
    "name": "foolish",
    "game": "Little Nightmares",
    "viewers": "1441"
  },
  {
    "name": "kkatamina",
    "game": "VALORANT",
    "viewers": "1436"
  },
  {
    "name": "lord_treputin__3626560",
    "game": "",
    "viewers": "1435"
  },
  {
    "name": "xqueeeee",
    "game": "STALCRAFT: X",
    "viewers": "1430"
  },
  {
    "name": "agentemaxo",
    "game": "Escape the Backrooms",
    "viewers": "1429"
  },
  {
    "name": "eeveelinh",
    "game": "Duet Night Abyss",
    "viewers": "1429"
  },
  {
    "name": "w0n23",
    "game": "Albion Online",
    "viewers": "1575"
  },
  {
    "name": "themrsark",
    "game": "Hunt: Showdown 1896",
    "viewers": "1418"
  },
  {
    "name": "seals311",
    "game": "Football Manager 26",
    "viewers": "1407"
  },
  {
    "name": "spookyloopz",
    "game": "Dead by Daylight",
    "viewers": "1394"
  },
  {
    "name": "giankoextreme",
    "game": "Super Mario Party Jamboree",
    "viewers": "1377"
  },
  {
    "name": "tarzaned",
    "game": "League of Legends",
    "viewers": "1366"
  },
  {
    "name": "sheefgg",
    "game": "Escape from Tarkov",
    "viewers": "1366"
  },
  {
    "name": "castro_1021",
    "game": "EA Sports FC 26",
    "viewers": "1365"
  },
  {
    "name": "baptistao",
    "game": "EA Sports FC 26",
    "viewers": "1345"
  },
  {
    "name": "iitifox",
    "game": "I'm Only Sleeping",
    "viewers": "1343"
  },
  {
    "name": "karmikkoala",
    "game": "Dota 2",
    "viewers": "1343"
  },
  {
    "name": "daruma_sn",
    "game": "Just Chatting",
    "viewers": "1330"
  },
  {
    "name": "pohx",
    "game": "Path of Exile",
    "viewers": "1326"
  },
  {
    "name": "elyihi",
    "game": "Sports",
    "viewers": "1318"
  },
  {
    "name": "barbarousking",
    "game": "Dead Space",
    "viewers": "1307"
  },
  {
    "name": "zerbs",
    "game": "Dead by Daylight",
    "viewers": "1306"
  },
  {
    "name": "baiano",
    "game": "League of Legends",
    "viewers": "1299"
  },
  {
    "name": "makatao",
    "game": "Battlefield REDSEC",
    "viewers": "1297"
  },
  {
    "name": "cohh",
    "game": "Always On",
    "viewers": "1281"
  },
  {
    "name": "stoopzz",
    "game": "Lost Ark",
    "viewers": "1280"
  },
  {
    "name": "smugalana",
    "game": "Megabonk",
    "viewers": "1277"
  },
  {
    "name": "ferolut",
    "game": "Counter-Strike",
    "viewers": "1274"
  },
  {
    "name": "ximycafak8",
    "game": "Virtual Casino",
    "viewers": "1265"
  },
  {
    "name": "leeandlie",
    "game": "Marvel Rivals",
    "viewers": "1261"
  },
  {
    "name": "bbreadman",
    "game": "Battlefield REDSEC",
    "viewers": "1257"
  },
  {
    "name": "mortenroyale",
    "game": "Clash Royale",
    "viewers": "1254"
  },
  {
    "name": "mym_alkapone",
    "game": "Just Chatting",
    "viewers": "1248"
  },
  {
    "name": "brino",
    "game": "Just Chatting",
    "viewers": "1246"
  },
  {
    "name": "swimy",
    "game": "EA Sports FC 26",
    "viewers": "1244"
  },
  {
    "name": "kumi",
    "game": "Just Chatting",
    "viewers": "1242"
  },
  {
    "name": "mrsal_59",
    "game": "Grand Theft Auto V",
    "viewers": "1230"
  },
  {
    "name": "mr_mammal",
    "game": "Old School RuneScape",
    "viewers": "1229"
  },
  {
    "name": "moauba",
    "game": "EA Sports FC 26",
    "viewers": "1225"
  },
  {
    "name": "scream",
    "game": "VALORANT",
    "viewers": "1224"
  },
  {
    "name": "raud",
    "game": "Just Chatting",
    "viewers": "1222"
  },
  {
    "name": "otplol_",
    "game": "League of Legends",
    "viewers": "1222"
  },
  {
    "name": "bandurka",
    "game": "Counter-Strike",
    "viewers": "1221"
  },
  {
    "name": "timthetatmanvods",
    "game": "Always On",
    "viewers": "1220"
  },
  {
    "name": "icemanisaac",
    "game": "Battlefield REDSEC",
    "viewers": "1216"
  },
  {
    "name": "gladd",
    "game": "Escape from Duckov",
    "viewers": "1211"
  },
  {
    "name": "pge4",
    "game": "Deadlock",
    "viewers": "1211"
  },
  {
    "name": "baalorlord",
    "game": "Slay the Spire",
    "viewers": "1208"
  },
  {
    "name": "kukuroneko",
    "game": "ASMR",
    "viewers": "1208"
  },
  {
    "name": "spockiller_tv",
    "game": "Grand Theft Auto V",
    "viewers": "1205"
  },
  {
    "name": "furo99",
    "game": "Just Chatting",
    "viewers": "1198"
  },
  {
    "name": "imaqtpie",
    "game": "FELLOWSHIP",
    "viewers": "1196"
  },
  {
    "name": "meranoh9",
    "game": "Virtual Casino",
    "viewers": "1182"
  },
  {
    "name": "winghaven",
    "game": "Battlefield REDSEC",
    "viewers": "1182"
  },
  {
    "name": "mount",
    "game": "Counter-Strike",
    "viewers": "1176"
  },
  {
    "name": "rosemondy",
    "game": "Minecraft",
    "viewers": "1176"
  },
  {
    "name": "aussieantics",
    "game": "Battlefield REDSEC",
    "viewers": "1173"
  },
  {
    "name": "sajam",
    "game": "2XKO",
    "viewers": "1166"
  },
  {
    "name": "bavepu66",
    "game": "Virtual Casino",
    "viewers": "1165"
  },
  {
    "name": "solaryhs",
    "game": "Hearthstone",
    "viewers": "1164"
  },
  {
    "name": "qttsix",
    "game": "Escape from Duckov",
    "viewers": "1160"
  },
  {
    "name": "phyzikk",
    "game": "Battlefield REDSEC",
    "viewers": "1157"
  },
  {
    "name": "khalamity",
    "game": "Hunt: Showdown 1896",
    "viewers": "1153"
  },
  {
    "name": "thimagroo",
    "game": "Just Chatting",
    "viewers": "1153"
  },
  {
    "name": "fyfeqi47",
    "game": "Virtual Casino",
    "viewers": "1150"
  },
  {
    "name": "gronkhtv",
    "game": "Borderlands 2",
    "viewers": "1150"
  },
  {
    "name": "saltydolphin",
    "game": "Pokémon FireRed/LeafGreen",
    "viewers": "1148"
  },
  {
    "name": "higgs",
    "game": "Fortnite",
    "viewers": "1141"
  },
  {
    "name": "coopertv",
    "game": "Counter-Strike",
    "viewers": "1141"
  },
  {
    "name": "jussef",
    "game": "Grand Theft Auto V",
    "viewers": "1141"
  },
  {
    "name": "snutzy",
    "game": "Slots",
    "viewers": "1140"
  },
  {
    "name": "zfg1",
    "game": "The Legend of Zelda: Ocarina of Time",
    "viewers": "1139"
  },
  {
    "name": "kayzahr",
    "game": "Battlefield REDSEC",
    "viewers": "1133"
  },
  {
    "name": "xizujite13",
    "game": "Virtual Casino",
    "viewers": "1131"
  },
  {
    "name": "hpduketv",
    "game": "Grand Theft Auto V",
    "viewers": "1128"
  },
  {
    "name": "captainlance9",
    "game": "Path of Exile",
    "viewers": "1121"
  },
  {
    "name": "aquwa",
    "game": "RV There Yet?",
    "viewers": "1119"
  },
  {
    "name": "caseoh247",
    "game": "Just Chatting",
    "viewers": "1114"
  },
  {
    "name": "aroyitt",
    "game": "Minecraft",
    "viewers": "1113"
  },
  {
    "name": "codemiko",
    "game": "Just Chatting",
    "viewers": "1097"
  },
  {
    "name": "tvander",
    "game": "Just Chatting",
    "viewers": "1096"
  },
  {
    "name": "abdu9974",
    "game": "Just Chatting",
    "viewers": "1095"
  },
  {
    "name": "ricci",
    "game": "Call of Duty: Warzone",
    "viewers": "1094"
  },
  {
    "name": "nightbarbie",
    "game": "Roblox Studio",
    "viewers": "1092"
  },
  {
    "name": "yuy_ix",
    "game": "RV There Yet?",
    "viewers": "1086"
  },
  {
    "name": "chiblee",
    "game": "Ultimate Theater Simulator",
    "viewers": "1084"
  },
  {
    "name": "ds_lily",
    "game": "Path of Exile",
    "viewers": "1081"
  },
  {
    "name": "mictia00",
    "game": "Minecraft",
    "viewers": "1077"
  },
  {
    "name": "abizaka",
    "game": "Just Chatting",
    "viewers": "1074"
  },
  {
    "name": "obormentv",
    "game": "Just Chatting",
    "viewers": "1072"
  },
  {
    "name": "bugha",
    "game": "Slots",
    "viewers": "1070"
  },
  {
    "name": "geega",
    "game": "The Séance of Blake Manor",
    "viewers": "1069"
  },
  {
    "name": "hamzakerdaloco",
    "game": "Grand Theft Auto V",
    "viewers": "1068"
  },
  {
    "name": "delaney",
    "game": "Hunt: Showdown 1896",
    "viewers": "1065"
  },
  {
    "name": "zanfas_cenegal",
    "game": "Virtual Casino",
    "viewers": "1061"
  },
  {
    "name": "mrtiboute",
    "game": "Phasmophobia",
    "viewers": "1059"
  },
  {
    "name": "low4n",
    "game": "Battlefield REDSEC",
    "viewers": "1059"
  },
  {
    "name": "guit88man",
    "game": "Mir Tankov",
    "viewers": "1058"
  },
  {
    "name": "arrowli",
    "game": "Guild Wars 2",
    "viewers": "1044"
  },
  {
    "name": "redpandash",
    "game": "Battlefield REDSEC",
    "viewers": "1037"
  },
  {
    "name": "chocotaco",
    "game": "Battlefield REDSEC",
    "viewers": "1030"
  },
  {
    "name": "ernesto",
    "game": "EA Sports FC 26",
    "viewers": "1029"
  },
  {
    "name": "oatsngoats",
    "game": "Super Metroid",
    "viewers": "1027"
  },
  {
    "name": "saintone",
    "game": "Duet Night Abyss",
    "viewers": "1027"
  },
  {
    "name": "mangekyou_14",
    "game": "Dota 2",
    "viewers": "1025"
  },
  {
    "name": "mirza_jahic",
    "game": "EA Sports FC 26",
    "viewers": "1020"
  },
  {
    "name": "canezerraa",
    "game": "VALORANT",
    "viewers": "1061"
  },
  {
    "name": "hungrybox",
    "game": "Super Smash Bros. Ultimate",
    "viewers": "1020"
  },
  {
    "name": "steelaaga",
    "game": "Just Chatting",
    "viewers": "1018"
  },
  {
    "name": "crelly",
    "game": "Just Chatting",
    "viewers": "1016"
  },
  {
    "name": "stormfall33",
    "game": "The Outer Worlds 2",
    "viewers": "1013"
  },
  {
    "name": "projektmelody",
    "game": "Dungeons & Dragons",
    "viewers": "1013"
  },
  {
    "name": "theburntpeanut_247",
    "game": "Always On",
    "viewers": "1009"
  },
  {
    "name": "sharkmacedo",
    "game": "EA Sports FC 26",
    "viewers": "1000"
  },
  {
    "name": "iitztimmy",
    "game": "Battlefield REDSEC",
    "viewers": "997"
  },
  {
    "name": "murdercrumpet",
    "game": "VRChat",
    "viewers": "994"
  },
  {
    "name": "whippy",
    "game": "Grand Theft Auto V",
    "viewers": "992"
  },
  {
    "name": "flyguncz",
    "game": "Escape Simulator 2",
    "viewers": "989"
  },
  {
    "name": "kotton",
    "game": "Battlefield REDSEC",
    "viewers": "987"
  },
  {
    "name": "uberhaxornova",
    "game": "MISERY",
    "viewers": "985"
  },
  {
    "name": "naitan",
    "game": "Just Chatting",
    "viewers": "985"
  },
  {
    "name": "qassimiento",
    "game": "Garry's Mod",
    "viewers": "982"
  },
  {
    "name": "xo_trixy",
    "game": "Dispatch",
    "viewers": "976"
  },
  {
    "name": "renrize",
    "game": "VALORANT",
    "viewers": "975"
  },
  {
    "name": "oguzzeira",
    "game": "Virtual Casino",
    "viewers": "972"
  },
  {
    "name": "mangel",
    "game": "Batman: Arkham City",
    "viewers": "972"
  },
  {
    "name": "thersguy",
    "game": "RuneScape",
    "viewers": "970"
  },
  {
    "name": "zeddy",
    "game": "Hearthstone",
    "viewers": "970"
  },
  {
    "name": "xarola_",
    "game": "VALORANT",
    "viewers": "967"
  },
  {
    "name": "ahmpy",
    "game": "World of Warcraft",
    "viewers": "963"
  },
  {
    "name": "calango",
    "game": "Counter-Strike",
    "viewers": "962"
  },
  {
    "name": "blitzstream",
    "game": "Chess",
    "viewers": "962"
  },
  {
    "name": "ndox_138",
    "game": "Path of Exile",
    "viewers": "961"
  },
  {
    "name": "deedge_live",
    "game": "RV There Yet?",
    "viewers": "959"
  },
  {
    "name": "dear_hellgirl",
    "game": "Dead by Daylight",
    "viewers": "958"
  },
  {
    "name": "luality",
    "game": "Escape from Duckov",
    "viewers": "948"
  },
  {
    "name": "jakeydavies",
    "game": "RV There Yet?",
    "viewers": "947"
  },
  {
    "name": "rogue",
    "game": "Battlefield REDSEC",
    "viewers": "945"
  },
  {
    "name": "chrisnxtdoor",
    "game": "Just Chatting",
    "viewers": "943"
  },
  {
    "name": "moman",
    "game": "Grand Theft Auto V",
    "viewers": "939"
  },
  {
    "name": "beterbabbit",
    "game": "Hearthstone",
    "viewers": "936"
  },
  {
    "name": "melhssn_",
    "game": "VALORANT",
    "viewers": "934"
  },
  {
    "name": "antedeguemonn",
    "game": "Tibia",
    "viewers": "933"
  },
  {
    "name": "crumbling1337",
    "game": "Dota 2",
    "viewers": "932"
  },
  {
    "name": "yodatv",
    "game": "FELLOWSHIP",
    "viewers": "932"
  },
  {
    "name": "tyrone",
    "game": "Grand Theft Auto V",
    "viewers": "932"
  },
  {
    "name": "narkuss_lol",
    "game": "League of Legends",
    "viewers": "932"
  },
  {
    "name": "ekkosuna",
    "game": "League of Legends",
    "viewers": "927"
  },
  {
    "name": "dirkneuenfels",
    "game": "DJs",
    "viewers": "926"
  },
  {
    "name": "derekkingonline",
    "game": "Just Chatting",
    "viewers": "926"
  },
  {
    "name": "elpelotasssss",
    "game": "Albion Online",
    "viewers": "926"
  },
  {
    "name": "fabo",
    "game": "Minecraft",
    "viewers": "926"
  },
  {
    "name": "proze",
    "game": "Battlefield REDSEC",
    "viewers": "921"
  },
  {
    "name": "derkc",
    "game": "EA Sports FC 26",
    "viewers": "920"
  },
  {
    "name": "fervonlaiho",
    "game": "Just Chatting",
    "viewers": "920"
  },
  {
    "name": "kapuzenwurm",
    "game": "Just Chatting",
    "viewers": "914"
  },
  {
    "name": "ravanha69",
    "game": "Virtual Casino",
    "viewers": "913"
  },
  {
    "name": "clutch_fii",
    "game": "Escape from Duckov",
    "viewers": "907"
  },
  {
    "name": "vegas",
    "game": "Deadlock",
    "viewers": "899"
  },
  {
    "name": "sanchovies",
    "game": "League of Legends",
    "viewers": "899"
  },
  {
    "name": "dekii",
    "game": "Battlefield REDSEC",
    "viewers": "889"
  },
  {
    "name": "dreads",
    "game": "Hearthstone",
    "viewers": "888"
  },
  {
    "name": "kenin",
    "game": "Virtual Casino",
    "viewers": "872"
  },
  {
    "name": "jaystayup",
    "game": "Grand Theft Auto V",
    "viewers": "868"
  },
  {
    "name": "slipix",
    "game": "League of Legends",
    "viewers": "866"
  },
  {
    "name": "shobek",
    "game": "Guild Wars 2",
    "viewers": "858"
  },
  {
    "name": "tolikthx",
    "game": "Just Chatting",
    "viewers": "854"
  },
  {
    "name": "celebi_cos",
    "game": "DRAGON QUEST XI S: Echoes of an Elusive Age",
    "viewers": "853"
  },
  {
    "name": "awizotv",
    "game": "Sejm The Game",
    "viewers": "852"
  },
  {
    "name": "acie",
    "game": "Just Chatting",
    "viewers": "847"
  },
  {
    "name": "neotblaze",
    "game": "Casino Simulator",
    "viewers": "839"
  },
  {
    "name": "moonkaselive",
    "game": "YAPYAP",
    "viewers": "836"
  },
  {
    "name": "gorilon",
    "game": "Pacify",
    "viewers": "835"
  },
  {
    "name": "leaksworld_",
    "game": "IRL",
    "viewers": "834"
  },
  {
    "name": "drdonutttttt",
    "game": "Minecraft",
    "viewers": "834"
  },
  {
    "name": "froggyloch",
    "game": "Silent Hill 2",
    "viewers": "834"
  },
  {
    "name": "zloy_artur_608115",
    "game": "",
    "viewers": "827"
  },
  {
    "name": "cricoccia3",
    "game": "EA Sports FC 26",
    "viewers": "824"
  },
  {
    "name": "puzanich_zanosi_2541478",
    "game": "Casino Simulator 2024",
    "viewers": "824"
  },
  {
    "name": "ibabyrainbow",
    "game": "Just Chatting",
    "viewers": "824"
  },
  {
    "name": "savyultras90",
    "game": "Battlefield REDSEC",
    "viewers": "823"
  },
  {
    "name": "papich_real_410125",
    "game": "",
    "viewers": "820"
  },
  {
    "name": "xchocobars",
    "game": "RV There Yet?",
    "viewers": "819"
  },
  {
    "name": "robbaz",
    "game": "Project Zomboid",
    "viewers": "817"
  },
  {
    "name": "buster_casino__120340",
    "game": "",
    "viewers": "816"
  },
  {
    "name": "casino_shadowkekw_9251662",
    "game": "Casino Simulator 2024",
    "viewers": "816"
  },
  {
    "name": "xrick75",
    "game": "Grand Theft Auto V",
    "viewers": "815"
  },
  {
    "name": "alveussanctuary",
    "game": "Animals, Aquariums, and Zoos",
    "viewers": "814"
  },
  {
    "name": "thedarkness",
    "game": "Battlefield REDSEC",
    "viewers": "812"
  },
  {
    "name": "juliakins",
    "game": "Just Chatting",
    "viewers": "811"
  },
  {
    "name": "7564671",
    "game": "",
    "viewers": "811"
  },
  {
    "name": "8355569",
    "game": "",
    "viewers": "810"
  },
  {
    "name": "bdsnuc",
    "game": "League of Legends",
    "viewers": "808"
  },
  {
    "name": "luxyrygirl___8519136",
    "game": "",
    "viewers": "807"
  },
  {
    "name": "cyyuvtuber",
    "game": "Lego & Brickbuilding",
    "viewers": "807"
  },
  {
    "name": "lilyaang",
    "game": "VALORANT",
    "viewers": "803"
  },
  {
    "name": "hamedloco",
    "game": "Just Chatting",
    "viewers": "802"
  },
  {
    "name": "frg_casino_3139267",
    "game": "Fortnite",
    "viewers": "800"
  },
  {
    "name": "tayoh_",
    "game": "Garry's Mod",
    "viewers": "800"
  },
  {
    "name": "speros",
    "game": "Battlefield REDSEC",
    "viewers": "798"
  },
  {
    "name": "souzasoul",
    "game": "Dead by Daylight",
    "viewers": "796"
  },
  {
    "name": "tikyjr",
    "game": "League of Legends",
    "viewers": "792"
  },
  {
    "name": "egorkreed_casino7759651",
    "game": "",
    "viewers": "789"
  },
  {
    "name": "twincytv",
    "game": "Grand Theft Auto V",
    "viewers": "786"
  },
  {
    "name": "buckefps",
    "game": "Fortnite",
    "viewers": "783"
  },
  {
    "name": "brohan",
    "game": "League of Legends",
    "viewers": "782"
  },
  {
    "name": "ezekiel_iii",
    "game": "Ire: A Prologue",
    "viewers": "780"
  },
  {
    "name": "kruzadar",
    "game": "Battlefield REDSEC",
    "viewers": "779"
  },
  {
    "name": "vitus_slots_4254338",
    "game": "",
    "viewers": "777"
  },
  {
    "name": "zir1gui",
    "game": "Virtual Casino",
    "viewers": "776"
  },
  {
    "name": "1uke337",
    "game": "Counter-Strike",
    "viewers": "774"
  },
  {
    "name": "leothecrack",
    "game": "Fortnite",
    "viewers": "771"
  },
  {
    "name": "zrush",
    "game": "Just Chatting",
    "viewers": "771"
  },
  {
    "name": "surugamonkey0113",
    "game": "VALORANT",
    "viewers": "771"
  },
  {
    "name": "ranellebrown",
    "game": "Just Chatting",
    "viewers": "765"
  },
  {
    "name": "rollinricher",
    "game": "Virtual Casino",
    "viewers": "765"
  },
  {
    "name": "claraatwork",
    "game": "Just Chatting",
    "viewers": "765"
  },
  {
    "name": "k13tv",
    "game": "Dota 2",
    "viewers": "764"
  },
  {
    "name": "dadxmad",
    "game": "League of Legends",
    "viewers": "762"
  },
  {
    "name": "jxliano",
    "game": "Trackmania",
    "viewers": "750"
  },
  {
    "name": "antilipsi",
    "game": "League of Legends",
    "viewers": "748"
  },
  {
    "name": "mukluk",
    "game": "Guild Wars 2",
    "viewers": "747"
  },
  {
    "name": "lucasalles69",
    "game": "Virtual Casino",
    "viewers": "746"
  },
  {
    "name": "sparkofphoenixtv",
    "game": "Minecraft",
    "viewers": "745"
  },
  {
    "name": "space",
    "game": "Marvel Rivals",
    "viewers": "745"
  },
  {
    "name": "skillspecs",
    "game": "Old School RuneScape",
    "viewers": "742"
  },
  {
    "name": "ghouly",
    "game": "Hunt: Showdown 1896",
    "viewers": "741"
  },
  {
    "name": "nefastone",
    "game": "Clash Royale",
    "viewers": "740"
  },
  {
    "name": "scarra",
    "game": "2XKO",
    "viewers": "739"
  },
  {
    "name": "agendafreetv",
    "game": "Just Chatting",
    "viewers": "738"
  },
  {
    "name": "drrilon",
    "game": "Just Chatting",
    "viewers": "736"
  },
  {
    "name": "usodah",
    "game": "Counter-Strike",
    "viewers": "736"
  },
  {
    "name": "stolenbr",
    "game": "Battlefield REDSEC",
    "viewers": "734"
  },
  {
    "name": "hutchmf_247",
    "game": "Always On",
    "viewers": "733"
  },
  {
    "name": "femimarss",
    "game": "Pokémon Legends: Z-A",
    "viewers": "729"
  },
  {
    "name": "xhocii",
    "game": "Counter-Strike",
    "viewers": "729"
  },
  {
    "name": "khalid_erk",
    "game": "Grand Theft Auto V",
    "viewers": "728"
  },
  {
    "name": "zherarrr",
    "game": "Heroes of Might and Magic III: The Restoration of Erathia",
    "viewers": "724"
  },
  {
    "name": "jocajoca27",
    "game": "",
    "viewers": "723"
  },
  {
    "name": "artosis",
    "game": "StarCraft",
    "viewers": "721"
  },
  {
    "name": "jericho",
    "game": "Battlefield REDSEC",
    "viewers": "717"
  },
  {
    "name": "lululuvely",
    "game": "Just Chatting",
    "viewers": "714"
  },
  {
    "name": "paache_",
    "game": "Inazuma Eleven Strikers",
    "viewers": "712"
  },
  {
    "name": "daniellippens",
    "game": "Just Chatting",
    "viewers": "710"
  },
  {
    "name": "matsuri_hs",
    "game": "Hearthstone",
    "viewers": "710"
  },
  {
    "name": "darthmicrotransaction",
    "game": "Path of Exile",
    "viewers": "709"
  },
  {
    "name": "dekkster",
    "game": "MARVEL SNAP",
    "viewers": "709"
  },
  {
    "name": "kestico",
    "game": "Racing Master",
    "viewers": "708"
  },
  {
    "name": "heystan",
    "game": "Just Chatting",
    "viewers": "707"
  },
  {
    "name": "yulla",
    "game": "VALORANT",
    "viewers": "706"
  },
  {
    "name": "mitchjones",
    "game": "Slots",
    "viewers": "706"
  },
  {
    "name": "chud_vr",
    "game": "VRChat",
    "viewers": "703"
  },
  {
    "name": "grandpoobear",
    "game": "Hades II",
    "viewers": "702"
  },
  {
    "name": "wichtiger",
    "game": "Minecraft",
    "viewers": "702"
  },
  {
    "name": "subroza",
    "game": "Battlefield REDSEC",
    "viewers": "701"
  },
  {
    "name": "direccioncorrecta1",
    "game": "Talk Shows & Podcasts",
    "viewers": "701"
  },
  {
    "name": "fluffozin",
    "game": "Virtual Casino",
    "viewers": "698"
  },
  {
    "name": "at0mium",
    "game": "Bloodborne",
    "viewers": "698"
  },
  {
    "name": "sheriffeli",
    "game": "Battlefield REDSEC",
    "viewers": "697"
  },
  {
    "name": "enkk",
    "game": "Just Chatting",
    "viewers": "697"
  },
  {
    "name": "eggsterr",
    "game": "VALORANT",
    "viewers": "695"
  },
  {
    "name": "mirreytv",
    "game": "Battlefield REDSEC",
    "viewers": "693"
  },
  {
    "name": "laxhawthorn007",
    "game": "DayZ",
    "viewers": "693"
  },
  {
    "name": "axialmatt",
    "game": "BALL x PIT",
    "viewers": "692"
  },
  {
    "name": "knight",
    "game": "Call of Duty: Warzone",
    "viewers": "692"
  },
  {
    "name": "warcraft",
    "game": "World of Warcraft",
    "viewers": "692"
  },
  {
    "name": "cartoonz",
    "game": "Battlefield REDSEC",
    "viewers": "689"
  },
  {
    "name": "ryux",
    "game": "Slots",
    "viewers": "686"
  },
  {
    "name": "nattank",
    "game": "Tibia",
    "viewers": "686"
  },
  {
    "name": "grimmi",
    "game": "Special Events",
    "viewers": "684"
  },
  {
    "name": "pow3r",
    "game": "Battlefield REDSEC",
    "viewers": "678"
  },
  {
    "name": "suncuster",
    "game": "Battlefield REDSEC",
    "viewers": "672"
  },
  {
    "name": "yukkkkiouo",
    "game": "League of Legends",
    "viewers": "667"
  },
  {
    "name": "tuadh",
    "game": "Path of Exile",
    "viewers": "665"
  },
  {
    "name": "earliboy",
    "game": "Minecraft",
    "viewers": "665"
  },
  {
    "name": "caligrafotv",
    "game": "Just Chatting",
    "viewers": "664"
  },
  {
    "name": "middleditch",
    "game": "Grand Theft Auto V",
    "viewers": "664"
  },
  {
    "name": "brunoocosta01",
    "game": "Grand Theft Auto V",
    "viewers": "663"
  },
  {
    "name": "kasumisen",
    "game": "Food & Drink",
    "viewers": "663"
  },
  {
    "name": "thesnootyfox",
    "game": "ASMR",
    "viewers": "661"
  },
  {
    "name": "xari",
    "game": "Crusader Kings III",
    "viewers": "660"
  },
  {
    "name": "drfeelgood",
    "game": "Pokémon Legends: Z-A",
    "viewers": "651"
  },
  {
    "name": "tonbocub",
    "game": "VALORANT",
    "viewers": "649"
  },
  {
    "name": "ikiimartin",
    "game": "EA Sports FC 26",
    "viewers": "648"
  },
  {
    "name": "ashlizzlle",
    "game": "Magic: The Gathering",
    "viewers": "647"
  },
  {
    "name": "talkto_megoose",
    "game": "World of Tanks",
    "viewers": "646"
  },
  {
    "name": "inoiizy",
    "game": "Minecraft",
    "viewers": "643"
  },
  {
    "name": "januslauvring",
    "game": "DJs",
    "viewers": "640"
  },
  {
    "name": "stormingh",
    "game": "Legend of Ymir",
    "viewers": "640"
  },
  {
    "name": "nuclearpastatom",
    "game": "ELDEN RING",
    "viewers": "637"
  },
  {
    "name": "sekiam",
    "game": "Just Chatting",
    "viewers": "634"
  },
  {
    "name": "moxsy",
    "game": "Borderlands 4",
    "viewers": "634"
  },
  {
    "name": "bobbypoffgaming",
    "game": "Battlefield REDSEC",
    "viewers": "633"
  },
  {
    "name": "shuteye_orange",
    "game": "Just Chatting",
    "viewers": "628"
  },
  {
    "name": "shahzam",
    "game": "VALORANT",
    "viewers": "627"
  },
  {
    "name": "lirik_247",
    "game": "Fright Fest",
    "viewers": "626"
  },
  {
    "name": "heyar",
    "game": "Software and Game Development",
    "viewers": "625"
  },
  {
    "name": "baxbeast",
    "game": "Arena Breakout: Infinite",
    "viewers": "625"
  },
  {
    "name": "narcisboza",
    "game": "Kings League",
    "viewers": "623"
  },
  {
    "name": "enkeo_",
    "game": "Call of Duty: Warzone",
    "viewers": "622"
  },
  {
    "name": "brigante_831",
    "game": "Just Chatting",
    "viewers": "622"
  },
  {
    "name": "itsryanhiga",
    "game": "VALORANT",
    "viewers": "622"
  },
  {
    "name": "ilumpe",
    "game": "Battlefield REDSEC",
    "viewers": "620"
  },
  {
    "name": "minos",
    "game": "Just Chatting",
    "viewers": "620"
  },
  {
    "name": "i_kagami_i",
    "game": "Grand Theft Auto V",
    "viewers": "618"
  },
  {
    "name": "fragas",
    "game": "Escape from Tarkov",
    "viewers": "595"
  },
  {
    "name": "anaaja",
    "game": "Battlefield REDSEC",
    "viewers": "663"
  },
  {
    "name": "shrcs",
    "game": "Counter-Strike",
    "viewers": "646"
  },
  {
    "name": "ranzratte",
    "game": "BATTLEFIELD 6",
    "viewers": "629"
  },
  {
    "name": "levideweerd",
    "game": "EA Sports FC 26",
    "viewers": "616"
  },
  {
    "name": "oddrey",
    "game": "Dead by Daylight",
    "viewers": "616"
  },
  {
    "name": "herdyn",
    "game": "JUMP KING QUEST",
    "viewers": "616"
  },
  {
    "name": "metaphor",
    "game": "Battlefield REDSEC",
    "viewers": "614"
  },
  {
    "name": "frttt",
    "game": "VALORANT",
    "viewers": "611"
  },
  {
    "name": "memberviper3",
    "game": "Slots",
    "viewers": "609"
  },
  {
    "name": "seucreysonreborn",
    "game": "Dota 2",
    "viewers": "606"
  },
  {
    "name": "colthavok",
    "game": "Call of Duty: Black Ops 6",
    "viewers": "603"
  },
  {
    "name": "hiimshankz",
    "game": "Grand Theft Auto V",
    "viewers": "603"
  },
  {
    "name": "etalyx",
    "game": "Crusader Kings III",
    "viewers": "603"
  },
  {
    "name": "exsl95",
    "game": "Minecraft",
    "viewers": "602"
  },
  {
    "name": "s7ormytv",
    "game": "Just Chatting",
    "viewers": "602"
  },
  {
    "name": "harryhesketh",
    "game": "EA Sports FC 26",
    "viewers": "600"
  },
  {
    "name": "gamesdonequick",
    "game": "Red Faction",
    "viewers": "595"
  },
  {
    "name": "chrismelberger",
    "game": "Dispatch",
    "viewers": "594"
  },
  {
    "name": "zorlakoka",
    "game": "Counter-Strike",
    "viewers": "594"
  },
  {
    "name": "thugfaast",
    "game": "PUBG: BATTLEGROUNDS",
    "viewers": "594"
  },
  {
    "name": "lemedtv",
    "game": "Just Chatting",
    "viewers": "592"
  },
  {
    "name": "beyaz",
    "game": "VALORANT",
    "viewers": "592"
  },
  {
    "name": "scottjund",
    "game": "Dead by Daylight",
    "viewers": "592"
  },
  {
    "name": "nagzz21",
    "game": "Just Chatting",
    "viewers": "592"
  },
  {
    "name": "imba__tv",
    "game": "Football Manager 26",
    "viewers": "591"
  },
  {
    "name": "corgicam",
    "game": "RV There Yet?",
    "viewers": "589"
  },
  {
    "name": "0pirikara0",
    "game": "Metaphor: ReFantazio",
    "viewers": "585"
  },
  {
    "name": "ootpdevelopments",
    "game": "Out of the Park Baseball 26",
    "viewers": "585"
  },
  {
    "name": "lake",
    "game": "Old School RuneScape",
    "viewers": "584"
  },
  {
    "name": "klupatwins",
    "game": "Just Chatting",
    "viewers": "583"
  },
  {
    "name": "basssultanhengzt45",
    "game": "Slots",
    "viewers": "582"
  },
  {
    "name": "roberttson",
    "game": "Just Chatting",
    "viewers": "579"
  },
  {
    "name": "leynainu",
    "game": "Just Chatting",
    "viewers": "578"
  },
  {
    "name": "officedrummer",
    "game": "Just Chatting",
    "viewers": "576"
  },
  {
    "name": "thatsanton",
    "game": "Just Chatting",
    "viewers": "576"
  },
  {
    "name": "elina",
    "game": "The Quarry",
    "viewers": "576"
  },
  {
    "name": "adler_blitz",
    "game": "Counter-Strike",
    "viewers": "575"
  },
  {
    "name": "krasififa_",
    "game": "EA Sports FC 26",
    "viewers": "573"
  },
  {
    "name": "leozintips",
    "game": "Just Chatting",
    "viewers": "571"
  },
  {
    "name": "mari",
    "game": "Dispatch",
    "viewers": "570"
  },
  {
    "name": "berrycrepe",
    "game": "Just Chatting",
    "viewers": "569"
  },
  {
    "name": "sonii",
    "game": "Guild Wars 2",
    "viewers": "568"
  },
  {
    "name": "ohtofu",
    "game": "Dead by Daylight",
    "viewers": "568"
  },
  {
    "name": "cobaltstreak",
    "game": "The Binding of Isaac: Repentance",
    "viewers": "567"
  },
  {
    "name": "crazyjapanese",
    "game": "Just Chatting",
    "viewers": "567"
  },
  {
    "name": "kertus",
    "game": "Grand Theft Auto V",
    "viewers": "566"
  },
  {
    "name": "blaize",
    "game": "EA Sports FC 26",
    "viewers": "566"
  },
  {
    "name": "aethelthryth",
    "game": "Minecraft",
    "viewers": "565"
  },
  {
    "name": "chris_gh0sty",
    "game": "Hunt: Showdown 1896",
    "viewers": "565"
  },
  {
    "name": "elnueveenvivo",
    "game": "",
    "viewers": "565"
  },
  {
    "name": "ttporky",
    "game": "Heroes of the Storm",
    "viewers": "564"
  },
  {
    "name": "angryjoeshow",
    "game": "BATTLEFIELD 6",
    "viewers": "564"
  },
  {
    "name": "luk_xoxo",
    "game": "VALORANT",
    "viewers": "562"
  },
  {
    "name": "bakagaijinlive",
    "game": "Just Chatting",
    "viewers": "560"
  },
  {
    "name": "onima_twitch",
    "game": "Grand Theft Auto V",
    "viewers": "559"
  },
  {
    "name": "luxthos",
    "game": "World of Warcraft",
    "viewers": "556"
  },
  {
    "name": "nitya_nil",
    "game": "Skinfreak",
    "viewers": "555"
  },
  {
    "name": "ajak0n",
    "game": "Just Chatting",
    "viewers": "555"
  },
  {
    "name": "n1kkifn2003",
    "game": "Fortnite",
    "viewers": "554"
  },
  {
    "name": "lagoda",
    "game": "Euro Truck Simulator 2",
    "viewers": "552"
  },
  {
    "name": "mahmoojen",
    "game": "Just Chatting",
    "viewers": "548"
  },
  {
    "name": "stereonline",
    "game": "Racing Master",
    "viewers": "548"
  },
  {
    "name": "africaalbion",
    "game": "Albion Online",
    "viewers": "547"
  },
  {
    "name": "daddydimmutv",
    "game": "Madden NFL 26",
    "viewers": "547"
  },
  {
    "name": "corky",
    "game": "PUBG: BATTLEGROUNDS",
    "viewers": "545"
  },
  {
    "name": "amslowtw",
    "game": "EA Sports FC 26",
    "viewers": "543"
  },
  {
    "name": "cicciotvv",
    "game": "Just Chatting",
    "viewers": "542"
  },
  {
    "name": "uzyduc",
    "game": "",
    "viewers": "542"
  },
  {
    "name": "drew_bills",
    "game": "Counter-Strike",
    "viewers": "538"
  },
  {
    "name": "joshog",
    "game": "Escape from Duckov",
    "viewers": "536"
  },
  {
    "name": "kick_freak",
    "game": "Heroes of Might and Magic III: The Restoration of Erathia",
    "viewers": "533"
  },
  {
    "name": "advocate_hs",
    "game": "Hearthstone",
    "viewers": "532"
  },
  {
    "name": "antoniomasmas",
    "game": "Just Chatting",
    "viewers": "531"
  },
  {
    "name": "theohs_",
    "game": "Hearthstone",
    "viewers": "531"
  },
  {
    "name": "lltrigger",
    "game": "League of Legends",
    "viewers": "527"
  },
  {
    "name": "policechasenetwork",
    "game": "Just Chatting",
    "viewers": "526"
  },
  {
    "name": "dcampion",
    "game": "Grand Theft Auto V",
    "viewers": "526"
  },
  {
    "name": "cpentagon",
    "game": "Battlefield REDSEC",
    "viewers": "524"
  },
  {
    "name": "mizitw",
    "game": "Battlefield REDSEC",
    "viewers": "524"
  },
  {
    "name": "marserracanta_",
    "game": "Just Chatting",
    "viewers": "523"
  },
  {
    "name": "niisa",
    "game": "Just Chatting",
    "viewers": "523"
  },
  {
    "name": "momoseventh",
    "game": "Dead by Daylight",
    "viewers": "520"
  },
  {
    "name": "capitanocima",
    "game": "Grand Theft Auto V",
    "viewers": "518"
  },
  {
    "name": "ronics2",
    "game": "Counter-Strike",
    "viewers": "518"
  },
  {
    "name": "kyr_sp33dy",
    "game": "BALL x PIT",
    "viewers": "517"
  },
  {
    "name": "fabriziocerrone",
    "game": "IRL",
    "viewers": "517"
  },
  {
    "name": "q_aretw",
    "game": "Just Chatting",
    "viewers": "516"
  },
  {
    "name": "suun",
    "game": "Dark and Darker",
    "viewers": "516"
  },
  {
    "name": "gassymexican",
    "game": "RV There Yet?",
    "viewers": "516"
  },
  {
    "name": "slwalekop",
    "game": "",
    "viewers": "515"
  },
  {
    "name": "xatufox",
    "game": "Phoenix Wright: Ace Attorney Trilogy",
    "viewers": "514"
  },
  {
    "name": "hyakujin",
    "game": "ELDEN RING",
    "viewers": "511"
  },
  {
    "name": "brutalmoose",
    "game": "Bad Ben",
    "viewers": "510"
  },
  {
    "name": "storkyyn",
    "game": "Grand Theft Auto V",
    "viewers": "509"
  },
  {
    "name": "redemption",
    "game": "Pokémon Emerald Version",
    "viewers": "508"
  },
  {
    "name": "llaviks",
    "game": "Just Chatting",
    "viewers": "508"
  },
  {
    "name": "carn_",
    "game": "Path of Exile",
    "viewers": "506"
  },
  {
    "name": "leckerboy21",
    "game": "EA Sports FC 26",
    "viewers": "506"
  },
  {
    "name": "bobbyraygray",
    "game": "Grand Theft Auto V",
    "viewers": "505"
  },
  {
    "name": "leopard",
    "game": "Destiny 2",
    "viewers": "505"
  },
  {
    "name": "ashmonsterftw",
    "game": "Dispatch",
    "viewers": "526"
  },
  {
    "name": "gamergirl",
    "game": "League of Legends",
    "viewers": "514"
  },
  {
    "name": "jankyrondo",
    "game": "Just Chatting",
    "viewers": "504"
  },
  {
    "name": "venofn",
    "game": "VALORANT",
    "viewers": "503"
  },
  {
    "name": "tedious_dave",
    "game": "Battlefield REDSEC",
    "viewers": "499"
  },
  {
    "name": "eslcs",
    "game": "Counter-Strike",
    "viewers": "499"
  },
  {
    "name": "zerobadass",
    "game": "Counter-Strike",
    "viewers": "499"
  },
  {
    "name": "yoyosavagemike",
    "game": "Fortnite",
    "viewers": "498"
  },
  {
    "name": "prolezwopia",
    "game": "Just Chatting",
    "viewers": "496"
  },
  {
    "name": "pokealexvgc",
    "game": "Just Chatting",
    "viewers": "496"
  },
  {
    "name": "brucegreene",
    "game": "RV There Yet?",
    "viewers": "491"
  },
  {
    "name": "uuraniummm",
    "game": "Just Chatting",
    "viewers": "490"
  },
  {
    "name": "divios",
    "game": "Black Desert",
    "viewers": "489"
  },
  {
    "name": "sura",
    "game": "Grand Theft Auto V",
    "viewers": "488"
  },
  {
    "name": "roxasorg13th",
    "game": "EA Sports FC 26",
    "viewers": "488"
  },
  {
    "name": "zeroyalviking",
    "game": "Pizza Deathlivery",
    "viewers": "488"
  },
  {
    "name": "lizabaktt",
    "game": "Just Chatting",
    "viewers": "487"
  },
  {
    "name": "demolition_d",
    "game": "Michigan: Report from Hell",
    "viewers": "485"
  },
  {
    "name": "patopapao",
    "game": "BALL x PIT",
    "viewers": "485"
  },
  {
    "name": "focusbf",
    "game": "Battlefield REDSEC",
    "viewers": "485"
  },
  {
    "name": "nekrolina",
    "game": "RV There Yet?",
    "viewers": "485"
  },
  {
    "name": "goldenjet_",
    "game": "Just Chatting",
    "viewers": "484"
  },
  {
    "name": "spartiatix",
    "game": "The Binding of Isaac: Repentance",
    "viewers": "484"
  },
  {
    "name": "passatigy",
    "game": "Battlefield REDSEC",
    "viewers": "482"
  },
  {
    "name": "mrxsmurf",
    "game": "Dota 2",
    "viewers": "479"
  },
  {
    "name": "ariasaki",
    "game": "Pokémon Legends: Z-A",
    "viewers": "479"
  },
  {
    "name": "veronikavolt",
    "game": "Just Chatting",
    "viewers": "478"
  },
  {
    "name": "mafuyumh1012",
    "game": "VALORANT",
    "viewers": "478"
  },
  {
    "name": "maciejay",
    "game": "Battlefield REDSEC",
    "viewers": "478"
  },
  {
    "name": "bokoen",
    "game": "RV There Yet?",
    "viewers": "478"
  },
  {
    "name": "jamside",
    "game": "BATTLEFIELD 6",
    "viewers": "476"
  },
  {
    "name": "sotchi_riot",
    "game": "Fright Fest",
    "viewers": "475"
  },
  {
    "name": "loge_tv",
    "game": "Star Citizen",
    "viewers": "473"
  },
  {
    "name": "tommypervan",
    "game": "Just Chatting",
    "viewers": "472"
  },
  {
    "name": "mariotq",
    "game": "IRL",
    "viewers": "472"
  },
  {
    "name": "andreynoiles",
    "game": "Just Chatting",
    "viewers": "471"
  },
  {
    "name": "arcus",
    "game": "Retro",
    "viewers": "470"
  },
  {
    "name": "akanemsko",
    "game": "Just Chatting",
    "viewers": "470"
  },
  {
    "name": "nerojeffhardy120",
    "game": "Counter-Strike",
    "viewers": "469"
  },
  {
    "name": "vinixiste",
    "game": "Just Chatting",
    "viewers": "467"
  },
  {
    "name": "porcelainmaid",
    "game": "Pokémon Legends: Z-A",
    "viewers": "466"
  },
  {
    "name": "ethanhzd",
    "game": "Just Chatting",
    "viewers": "465"
  },
  {
    "name": "youritalianwaifu",
    "game": "ASMR",
    "viewers": "464"
  },
  {
    "name": "ane4ka_megera",
    "game": "Caliber",
    "viewers": "463"
  },
  {
    "name": "yaboiwiilly",
    "game": "New World: Aeternum",
    "viewers": "463"
  },
  {
    "name": "kkubitzaa",
    "game": "Virtual Casino",
    "viewers": "460"
  },
  {
    "name": "spite",
    "game": "Dungeons & Dragons",
    "viewers": "460"
  },
  {
    "name": "uk2k75124",
    "game": "BATTLEFIELD 6",
    "viewers": "460"
  },
  {
    "name": "miikelmst",
    "game": "EA Sports FC 26",
    "viewers": "459"
  },
  {
    "name": "ferretsoftware",
    "game": "Animals, Aquariums, and Zoos",
    "viewers": "459"
  },
  {
    "name": "imanalidib",
    "game": "Just Chatting",
    "viewers": "457"
  },
  {
    "name": "snakeeyez",
    "game": "Street Fighter 6",
    "viewers": "457"
  },
  {
    "name": "poach",
    "game": "Delta Force",
    "viewers": "457"
  },
  {
    "name": "dealjb",
    "game": "Grand Theft Auto V",
    "viewers": "457"
  },
  {
    "name": "yesseniavo",
    "game": "GODDESS OF VICTORY: NIKKE",
    "viewers": "456"
  },
  {
    "name": "originangel",
    "game": "Pokémon Legends: Z-A",
    "viewers": "455"
  },
  {
    "name": "nugiyen",
    "game": "Path of Exile",
    "viewers": "455"
  },
  {
    "name": "overlordbou",
    "game": "World of Warships",
    "viewers": "455"
  },
  {
    "name": "moitaofc",
    "game": "Grand Theft Auto V",
    "viewers": "454"
  },
  {
    "name": "mickalow",
    "game": "Battlefield REDSEC",
    "viewers": "453"
  },
  {
    "name": "kumamonster",
    "game": "IRL",
    "viewers": "452"
  },
  {
    "name": "chiefbeef_rl",
    "game": "Rocket League",
    "viewers": "452"
  },
  {
    "name": "juventibus",
    "game": "Sports",
    "viewers": "450"
  },
  {
    "name": "eskay",
    "game": "2XKO",
    "viewers": "449"
  },
  {
    "name": "khadim",
    "game": "Grand Theft Auto V",
    "viewers": "449"
  },
  {
    "name": "ramez05",
    "game": "Masks of the Void",
    "viewers": "449"
  },
  {
    "name": "chawndo",
    "game": "Genshin Impact",
    "viewers": "449"
  },
  {
    "name": "cedduzzo",
    "game": "Grand Theft Auto V",
    "viewers": "447"
  },
  {
    "name": "kxrvinho",
    "game": "Virtual Casino",
    "viewers": "447"
  },
  {
    "name": "monkeys_forever",
    "game": "Dota 2",
    "viewers": "446"
  },
  {
    "name": "facuuparejas",
    "game": "Dead by Daylight",
    "viewers": "446"
  },
  {
    "name": "freakazoid",
    "game": "Counter-Strike",
    "viewers": "445"
  },
  {
    "name": "anthonycaliber",
    "game": "The Last of Us",
    "viewers": "444"
  },
  {
    "name": "skyjlv",
    "game": "GODDESS OF VICTORY: NIKKE",
    "viewers": "444"
  },
  {
    "name": "blukitsune9",
    "game": "Little Nightmares III",
    "viewers": "444"
  },
  {
    "name": "fgrav_",
    "game": "DON'T SCREAM",
    "viewers": "442"
  },
  {
    "name": "brozime",
    "game": "Duet Night Abyss",
    "viewers": "441"
  },
  {
    "name": "lucasrojo",
    "game": "Just Chatting",
    "viewers": "441"
  },
  {
    "name": "shiishak",
    "game": "Dota 2",
    "viewers": "441"
  },
  {
    "name": "jvkson",
    "game": "Grand Theft Auto V",
    "viewers": "441"
  },
  {
    "name": "timmac",
    "game": "Grand Theft Auto V",
    "viewers": "440"
  },
  {
    "name": "darkh1ts",
    "game": "Slots",
    "viewers": "437"
  },
  {
    "name": "vrauixo",
    "game": "Slots",
    "viewers": "436"
  },
  {
    "name": "gr1mreap1r",
    "game": "Ghosts of Tabor",
    "viewers": "434"
  },
  {
    "name": "thehamtv",
    "game": "Magic: The Gathering",
    "viewers": "433"
  },
  {
    "name": "arkanightlive",
    "game": "Just Chatting",
    "viewers": "433"
  },
  {
    "name": "badgecollectors",
    "game": "Fright Fest",
    "viewers": "432"
  },
  {
    "name": "clarkhellscream",
    "game": "Hearthstone",
    "viewers": "431"
  },
  {
    "name": "disnof",
    "game": "Escape from Duckov",
    "viewers": "431"
  },
  {
    "name": "carrypottergaming",
    "game": "Hearthstone",
    "viewers": "430"
  },
  {
    "name": "smokaloke",
    "game": "The Killing Antidote",
    "viewers": "430"
  },
  {
    "name": "apply",
    "game": "Overwatch 2",
    "viewers": "429"
  },
  {
    "name": "hollywoodbob",
    "game": "PUBG: BATTLEGROUNDS",
    "viewers": "427"
  },
  {
    "name": "pgod",
    "game": "Fortnite",
    "viewers": "427"
  },
  {
    "name": "squishymuffinz",
    "game": "Rocket League",
    "viewers": "425"
  },
  {
    "name": "granny",
    "game": "Waterpark Simulator",
    "viewers": "425"
  },
  {
    "name": "caresapo",
    "game": "League of Legends",
    "viewers": "425"
  },
  {
    "name": "igobygraven",
    "game": "Kingdom Hearts HD 1.5 + 2.5 ReMIX",
    "viewers": "421"
  },
  {
    "name": "ruflesscat",
    "game": "Fortnite",
    "viewers": "421"
  },
  {
    "name": "katie",
    "game": "Dark and Darker",
    "viewers": "360"
  },
  {
    "name": "ariasaki",
    "game": "Pokémon Legends: Z-A",
    "viewers": "479"
  },
  {
    "name": "ikoneec",
    "game": "DayZ",
    "viewers": "420"
  },
  {
    "name": "narang_421",
    "game": "Just Chatting",
    "viewers": "420"
  },
  {
    "name": "albyaround",
    "game": "Dead by Daylight",
    "viewers": "419"
  },
  {
    "name": "neogreg",
    "game": "Hearthstone",
    "viewers": "417"
  },
  {
    "name": "trimics2",
    "game": "Counter-Strike",
    "viewers": "416"
  },
  {
    "name": "witchblvde",
    "game": "Dota 2",
    "viewers": "416"
  },
  {
    "name": "gamescage",
    "game": "Sonic Racing: CrossWorlds",
    "viewers": "415"
  },
  {
    "name": "xpandorya",
    "game": "Grand Theft Auto V",
    "viewers": "413"
  },
  {
    "name": "pkdelastreinador",
    "game": "Just Chatting",
    "viewers": "413"
  },
  {
    "name": "reallifespartan",
    "game": "Halo: The Master Chief Collection",
    "viewers": "412"
  },
  {
    "name": "fraiki",
    "game": "DEVOUR",
    "viewers": "412"
  },
  {
    "name": "nakkida",
    "game": "Grand Theft Auto V",
    "viewers": "412"
  },
  {
    "name": "d3ad_plays",
    "game": "Dead by Daylight",
    "viewers": "410"
  },
  {
    "name": "waggle",
    "game": "Path of Exile",
    "viewers": "410"
  },
  {
    "name": "tftoddy",
    "game": "Chained Together",
    "viewers": "410"
  },
  {
    "name": "gsxrclyde",
    "game": "Destiny 2",
    "viewers": "409"
  },
  {
    "name": "nickyy",
    "game": "Just Chatting",
    "viewers": "409"
  },
  {
    "name": "choke7",
    "game": "YAPYAP",
    "viewers": "409"
  },
  {
    "name": "thomasrgn",
    "game": "Virtual Casino",
    "viewers": "409"
  },
  {
    "name": "esvandal",
    "game": "BALL x PIT",
    "viewers": "408"
  },
  {
    "name": "trivitv",
    "game": "Escape the Backrooms",
    "viewers": "407"
  },
  {
    "name": "b_komhate",
    "game": "Battlefield REDSEC",
    "viewers": "406"
  },
  {
    "name": "jhoolna",
    "game": "New World: Aeternum",
    "viewers": "406"
  },
  {
    "name": "kubon_",
    "game": "League of Legends",
    "viewers": "405"
  },
  {
    "name": "emerome",
    "game": "Games + Demos",
    "viewers": "405"
  },
  {
    "name": "cpcpcp",
    "game": "League of Legends",
    "viewers": "404"
  },
  {
    "name": "teamcaptain001",
    "game": "Marvel Rivals",
    "viewers": "402"
  },
  {
    "name": "nevsehirrrtr",
    "game": "",
    "viewers": "400"
  },
  {
    "name": "nickhots",
    "game": "Software and Game Development",
    "viewers": "400"
  },
  {
    "name": "skyytea",
    "game": "Fallout 4",
    "viewers": "400"
  },
  {
    "name": "beardlessbroski",
    "game": "STALCRAFT: X",
    "viewers": "399"
  },
  {
    "name": "faello1",
    "game": "Wuthering Waves",
    "viewers": "398"
  },
  {
    "name": "immarksman",
    "game": "BATTLEFIELD 6",
    "viewers": "397"
  },
  {
    "name": "emzy",
    "game": "Battlefield REDSEC",
    "viewers": "397"
  },
  {
    "name": "acr_pkr",
    "game": "Poker",
    "viewers": "396"
  },
  {
    "name": "vkingplays",
    "game": "The Outer Worlds 2",
    "viewers": "396"
  },
  {
    "name": "thehydrogen",
    "game": "League of Legends",
    "viewers": "394"
  },
  {
    "name": "rifftrax",
    "game": "Talk Shows & Podcasts",
    "viewers": "393"
  },
  {
    "name": "imh0nda",
    "game": "Counter-Strike",
    "viewers": "393"
  },
  {
    "name": "xenosysvex",
    "game": "Magic: The Gathering",
    "viewers": "391"
  },
  {
    "name": "kapesnik69",
    "game": "Balatro",
    "viewers": "390"
  },
  {
    "name": "der_skandal",
    "game": "Slots",
    "viewers": "390"
  },
  {
    "name": "gioee",
    "game": "Just Chatting",
    "viewers": "389"
  },
  {
    "name": "hcjustin",
    "game": "Phasmophobia",
    "viewers": "388"
  },
  {
    "name": "mbytes37",
    "game": "EA Sports FC 26",
    "viewers": "387"
  },
  {
    "name": "cash4kills_",
    "game": "Call of Duty: Warzone",
    "viewers": "386"
  },
  {
    "name": "papaschlumpf2019",
    "game": "EA Sports FC 26",
    "viewers": "386"
  },
  {
    "name": "mausabi",
    "game": "Grand Theft Auto V",
    "viewers": "386"
  },
  {
    "name": "alexcrasherss",
    "game": "Special Events",
    "viewers": "385"
  },
  {
    "name": "kyoinfinity",
    "game": "Legend of Ymir",
    "viewers": "385"
  },
  {
    "name": "reidboyy",
    "game": "Battlefield REDSEC",
    "viewers": "384"
  },
  {
    "name": "bozevstheworld",
    "game": "Just Chatting",
    "viewers": "384"
  },
  {
    "name": "deemonrider",
    "game": "Pokémon Community Game",
    "viewers": "384"
  },
  {
    "name": "mira",
    "game": "Just Chatting",
    "viewers": "384"
  },
  {
    "name": "yokasiri",
    "game": "Pizza Deathlivery",
    "viewers": "383"
  },
  {
    "name": "gennci",
    "game": "Counter-Strike",
    "viewers": "381"
  },
  {
    "name": "vertiigogaming",
    "game": "Project Zomboid",
    "viewers": "380"
  },
  {
    "name": "rodil",
    "game": "League of Legends",
    "viewers": "380"
  },
  {
    "name": "whisqey",
    "game": "Special Events",
    "viewers": "380"
  },
  {
    "name": "clararline",
    "game": "Just Chatting",
    "viewers": "378"
  },
  {
    "name": "suyummy",
    "game": "ASMR",
    "viewers": "378"
  },
  {
    "name": "ketchupgamer11",
    "game": "Call of Duty: Warzone",
    "viewers": "377"
  },
  {
    "name": "awesomeelina",
    "game": "Minecraft",
    "viewers": "375"
  },
  {
    "name": "sunshinevrc",
    "game": "ASMR",
    "viewers": "375"
  },
  {
    "name": "liquidhasuobs",
    "game": "Heroes of the Storm",
    "viewers": "375"
  },
  {
    "name": "possessivopk",
    "game": "Just Chatting",
    "viewers": "374"
  },
  {
    "name": "moumousx",
    "game": "Garry's Mod",
    "viewers": "373"
  },
  {
    "name": "egorushtv",
    "game": "Slots",
    "viewers": "373"
  },
  {
    "name": "lofigirl",
    "game": "Music",
    "viewers": "372"
  },
  {
    "name": "r3crutatv",
    "game": "Rust",
    "viewers": "372"
  },
  {
    "name": "playwithme",
    "game": "Deadlock",
    "viewers": "372"
  },
  {
    "name": "stanz",
    "game": "Fortnite",
    "viewers": "371"
  },
  {
    "name": "mollu",
    "game": "Super Mario Party Jamboree",
    "viewers": "370"
  },
  {
    "name": "streamerhouse",
    "game": "Tom Clancy's The Division 2",
    "viewers": "369"
  },
  {
    "name": "thenigelb",
    "game": "Just Chatting",
    "viewers": "368"
  },
  {
    "name": "zuyzyan",
    "game": "Dota 2",
    "viewers": "367"
  },
  {
    "name": "komanche",
    "game": "Minecraft",
    "viewers": "366"
  },
  {
    "name": "franciscoow",
    "game": "Shadowverse: Worlds Beyond",
    "viewers": "366"
  },
  {
    "name": "rclark98",
    "game": "Red Dead Redemption II",
    "viewers": "366"
  },
  {
    "name": "dariomartiz",
    "game": "EA Sports FC 26",
    "viewers": "364"
  },
  {
    "name": "blackhammerplay",
    "game": "Grand Theft Auto V",
    "viewers": "364"
  },
  {
    "name": "f0rsakenwow",
    "game": "Counter-Strike",
    "viewers": "363"
  },
  {
    "name": "joewo",
    "game": "Battlefield REDSEC",
    "viewers": "363"
  },
  {
    "name": "adamvseverything",
    "game": "STASIS: BONE TOTEM",
    "viewers": "363"
  },
  {
    "name": "iseedeadp3ople",
    "game": "Dota 2",
    "viewers": "362"
  },
  {
    "name": "desiheat",
    "game": "World of Warcraft",
    "viewers": "362"
  },
  {
    "name": "avacrown_",
    "game": "DJs",
    "viewers": "361"
  },
  {
    "name": "acoldone",
    "game": "Old School RuneScape",
    "viewers": "360"
  },
  {
    "name": "jupieverse",
    "game": "Palia",
    "viewers": "359"
  },
  {
    "name": "japaneseprintmaking",
    "game": "Makers & Crafting",
    "viewers": "359"
  },
  {
    "name": "fesicuro",
    "game": "Just Chatting",
    "viewers": "358"
  },
  {
    "name": "adria_asmr",
    "game": "ASMR",
    "viewers": "358"
  },
  {
    "name": "sesuko",
    "game": "Overwatch 2",
    "viewers": "357"
  },
  {
    "name": "dooomcr",
    "game": "Clash Royale",
    "viewers": "357"
  },
  {
    "name": "ortopilot",
    "game": "Music",
    "viewers": "356"
  },
  {
    "name": "coreano",
    "game": "Slime Rancher 2",
    "viewers": "356"
  },
  {
    "name": "repullze",
    "game": "Battlefield REDSEC",
    "viewers": "356"
  },
  {
    "name": "theguill84",
    "game": "Twitch Plays",
    "viewers": "356"
  },
  {
    "name": "peeguutv",
    "game": "Just Chatting",
    "viewers": "343"
  },
  {
    "name": "calizda7",
    "game": "Counter-Strike",
    "viewers": "622"
  },
  {
    "name": "heinzbaines_",
    "game": "RV There Yet?",
    "viewers": "355"
  },
  {
    "name": "bobqinxd",
    "game": "League of Legends",
    "viewers": "355"
  },
  {
    "name": "omendigotv",
    "game": "Slots",
    "viewers": "355"
  },
  {
    "name": "sneegsnag",
    "game": "Look Outside",
    "viewers": "353"
  },
  {
    "name": "abarone68",
    "game": "Poker",
    "viewers": "352"
  },
  {
    "name": "adef",
    "game": "Pokémon Platinum Version",
    "viewers": "352"
  },
  {
    "name": "sloppywalrusx",
    "game": "League of Legends",
    "viewers": "351"
  },
  {
    "name": "cheese",
    "game": "Super Mario 64",
    "viewers": "351"
  },
  {
    "name": "nassrll_",
    "game": "Rocket League",
    "viewers": "351"
  },
  {
    "name": "m3rkmus1c",
    "game": "Battlefield REDSEC",
    "viewers": "351"
  },
  {
    "name": "snkarma",
    "game": "League of Legends",
    "viewers": "349"
  },
  {
    "name": "lanje_live",
    "game": "World of Warcraft",
    "viewers": "349"
  },
  {
    "name": "goldeniums",
    "game": "Albion Online",
    "viewers": "348"
  },
  {
    "name": "knebel_de",
    "game": "Star Citizen",
    "viewers": "348"
  },
  {
    "name": "theblackhokage",
    "game": "Ghost of Yōtei",
    "viewers": "347"
  },
  {
    "name": "iamjustacrazy",
    "game": "Path of Exile",
    "viewers": "347"
  },
  {
    "name": "jdotb",
    "game": "World of Warcraft",
    "viewers": "347"
  },
  {
    "name": "lexitvz",
    "game": "Rusty Lake: Roots",
    "viewers": "346"
  },
  {
    "name": "vanessa_lopez_official",
    "game": "Just Chatting",
    "viewers": "346"
  },
  {
    "name": "cowsep",
    "game": "League of Legends",
    "viewers": "346"
  },
  {
    "name": "nokzsid",
    "game": "Grand Theft Auto V",
    "viewers": "346"
  },
  {
    "name": "norgannonhh",
    "game": "ARC Raiders",
    "viewers": "345"
  },
  {
    "name": "pantulive",
    "game": "Grand Theft Auto V",
    "viewers": "343"
  },
  {
    "name": "yamadamei_",
    "game": "ASMR",
    "viewers": "343"
  },
  {
    "name": "notoriousnaru",
    "game": "Guild Wars 2",
    "viewers": "342"
  },
  {
    "name": "mivtsy",
    "game": "Dune: Awakening",
    "viewers": "342"
  },
  {
    "name": "dansan_dayo",
    "game": "Just Chatting",
    "viewers": "342"
  },
  {
    "name": "papamutt",
    "game": "Dungeons & Dragons",
    "viewers": "341"
  },
  {
    "name": "j_alexander_hs",
    "game": "Hearthstone",
    "viewers": "341"
  },
  {
    "name": "yungdingo",
    "game": "Magic: The Gathering",
    "viewers": "341"
  },
  {
    "name": "iamfoosa",
    "game": "Gran Turismo 7",
    "viewers": "340"
  },
  {
    "name": "enzoo",
    "game": "NBA 2K26",
    "viewers": "340"
  },
  {
    "name": "miguelspencer2020",
    "game": "",
    "viewers": "340"
  },
  {
    "name": "ceremor",
    "game": "Dark and Darker",
    "viewers": "339"
  },
  {
    "name": "ayss",
    "game": "Just Chatting",
    "viewers": "339"
  },
  {
    "name": "mudynh0xd",
    "game": "Just Chatting",
    "viewers": "339"
  },
  {
    "name": "telemetropanama",
    "game": "Sports",
    "viewers": "339"
  },
  {
    "name": "fieldmouse",
    "game": "Hunt: Showdown 1896",
    "viewers": "338"
  },
  {
    "name": "jocat",
    "game": "Monster Hunter Wilds",
    "viewers": "336"
  },
  {
    "name": "geass_mlbb",
    "game": "Mobile Legends: Bang Bang",
    "viewers": "336"
  },
  {
    "name": "vortus43",
    "game": "Guild Wars 2",
    "viewers": "336"
  },
  {
    "name": "twobiers",
    "game": "Megabonk",
    "viewers": "335"
  },
  {
    "name": "mavro_jr",
    "game": "Just Chatting",
    "viewers": "335"
  },
  {
    "name": "ladytheladdy",
    "game": "Warframe",
    "viewers": "334"
  },
  {
    "name": "eternal_grudge",
    "game": "Don't Starve Together",
    "viewers": "334"
  },
  {
    "name": "douglassola",
    "game": "Just Chatting",
    "viewers": "333"
  },
  {
    "name": "uzya",
    "game": "Just Chatting",
    "viewers": "333"
  },
  {
    "name": "anth0xc0lab0y",
    "game": "Just Chatting",
    "viewers": "332"
  },
  {
    "name": "mistressmayhemmm",
    "game": "ASMR",
    "viewers": "332"
  },
  {
    "name": "captainsparklez",
    "game": "Megabonk",
    "viewers": "332"
  },
  {
    "name": "mikemateilive",
    "game": "Retro",
    "viewers": "331"
  },
  {
    "name": "ausrastenistmeinhobby",
    "game": "Grand Theft Auto V",
    "viewers": "330"
  },
  {
    "name": "rickth21",
    "game": "EA Sports FC 26",
    "viewers": "330"
  },
  {
    "name": "yukix100",
    "game": "Crypto",
    "viewers": "330"
  },
  {
    "name": "hastad",
    "game": "Virtual Casino",
    "viewers": "330"
  },
  {
    "name": "sharonqueen",
    "game": "ASMR",
    "viewers": "329"
  },
  {
    "name": "sui_dabz",
    "game": "Ghosts of Tabor",
    "viewers": "329"
  },
  {
    "name": "mularjuice",
    "game": "Just Chatting",
    "viewers": "329"
  },
  {
    "name": "saselandiadirectos",
    "game": "Just Chatting",
    "viewers": "328"
  },
  {
    "name": "oisakura",
    "game": "Just Chatting",
    "viewers": "328"
  },
  {
    "name": "apryze",
    "game": "Battlefield REDSEC",
    "viewers": "328"
  },
  {
    "name": "tr33_ow",
    "game": "Overwatch 2",
    "viewers": "328"
  },
  {
    "name": "kidshadoe",
    "game": "Resident Evil 4",
    "viewers": "327"
  },
  {
    "name": "m989876525",
    "game": "Hearthstone",
    "viewers": "327"
  },
  {
    "name": "potasticp",
    "game": "Baldur's Gate 3",
    "viewers": "326"
  },
  {
    "name": "thegeekentry",
    "game": "Pokémon Legends: Z-A",
    "viewers": "326"
  },
  {
    "name": "gavrilka",
    "game": "Just Chatting",
    "viewers": "325"
  },
  {
    "name": "blazx",
    "game": "Grand Theft Auto V",
    "viewers": "324"
  },
  {
    "name": "nicotheo_off",
    "game": "Grand Theft Auto V",
    "viewers": "324"
  },
  {
    "name": "thelorr",
    "game": "Dark and Darker",
    "viewers": "323"
  },
  {
    "name": "hotbeatstv",
    "game": "DJs",
    "viewers": "323"
  },
  {
    "name": "kodigogg",
    "game": "Clash Royale",
    "viewers": "322"
  },
  {
    "name": "tochnonemonker",
    "game": "STALCRAFT: X",
    "viewers": "321"
  },
  {
    "name": "nyunkoro",
    "game": "League of Legends",
    "viewers": "321"
  },
  {
    "name": "zoinkgd",
    "game": "Geometry Dash",
    "viewers": "321"
  },
  {
    "name": "felikah",
    "game": "Minecraft",
    "viewers": "320"
  },
  {
    "name": "ayoohenry",
    "game": "Ghosts of Tabor",
    "viewers": "320"
  },
  {
    "name": "mattivik",
    "game": "Pokémon FireRed/LeafGreen",
    "viewers": "320"
  },
  {
    "name": "ragevl_",
    "game": "Just Chatting",
    "viewers": "319"
  },
  {
    "name": "siormax",
    "game": "Hollywood Monsters",
    "viewers": "319"
  },
  {
    "name": "kelre0n",
    "game": "Red Dead Redemption II",
    "viewers": "318"
  },
  {
    "name": "vlouue",
    "game": "Fright Fest",
    "viewers": "317"
  },
  {
    "name": "tobiasfate",
    "game": "No, I'm Not A Human",
    "viewers": "317"
  },
  {
    "name": "ravenalternative",
    "game": "Just Chatting",
    "viewers": "317"
  },
  {
    "name": "zerocoolx",
    "game": "World of Warcraft",
    "viewers": "316"
  },
  {
    "name": "risshella",
    "game": "Pokémon Legends: Z-A",
    "viewers": "316"
  },
  {
    "name": "magnumofspades",
    "game": "Don't Starve Together",
    "viewers": "316"
  },
  {
    "name": "icythugger",
    "game": "Grand Theft Auto V",
    "viewers": "316"
  },
  {
    "name": "brajenirl",
    "game": "IRL",
    "viewers": "316"
  },
  {
    "name": "hankstergirl",
    "game": "Dinkum",
    "viewers": "316"
  },
  {
    "name": "ratoborrachudo",
    "game": "IRL",
    "viewers": "315"
  },
  {
    "name": "majski227",
    "game": "VALORANT",
    "viewers": "315"
  },
  {
    "name": "mitchflowerpower",
    "game": "Paper Mario: The Thousand-Year Door",
    "viewers": "315"
  },
  {
    "name": "marisnotokay",
    "game": "Just Chatting",
    "viewers": "315"
  },
  {
    "name": "whyandr3w",
    "game": "Marvel Rivals",
    "viewers": "315"
  },
  {
    "name": "karq",
    "game": "Overwatch 2",
    "viewers": "315"
  },
  {
    "name": "neet",
    "game": "VRChat",
    "viewers": "313"
  },
  {
    "name": "logo",
    "game": "Minecraft",
    "viewers": "301"
  },
  {
    "name": "kaileymae",
    "game": "Co-working & Studying",
    "viewers": "244"
  },
  {
    "name": "light_e7",
    "game": "Chaos Zero Nightmare",
    "viewers": "312"
  },
  {
    "name": "donfreez",
    "game": "VEIN",
    "viewers": "312"
  },
  {
    "name": "jacktorrance90",
    "game": "Magic: The Gathering",
    "viewers": "311"
  },
  {
    "name": "scope",
    "game": "Battlefield REDSEC",
    "viewers": "311"
  },
  {
    "name": "lewislefou",
    "game": "Silent Still",
    "viewers": "310"
  },
  {
    "name": "llyswi",
    "game": "Just Chatting",
    "viewers": "310"
  },
  {
    "name": "games4ndchill",
    "game": "Genshin Impact",
    "viewers": "310"
  },
  {
    "name": "reet",
    "game": "Fortnite",
    "viewers": "309"
  },
  {
    "name": "oruipinto",
    "game": "Counter-Strike",
    "viewers": "308"
  },
  {
    "name": "soydarmoo",
    "game": "Minecraft",
    "viewers": "308"
  },
  {
    "name": "asspizza730",
    "game": "Just Chatting",
    "viewers": "308"
  },
  {
    "name": "keeoh",
    "game": "VALORANT",
    "viewers": "308"
  },
  {
    "name": "sukidingels",
    "game": "BALL x PIT",
    "viewers": "307"
  },
  {
    "name": "sergeantheine",
    "game": "BATTLEFIELD 6",
    "viewers": "306"
  },
  {
    "name": "itsjstn",
    "game": "Rocket League",
    "viewers": "306"
  },
  {
    "name": "hucokagot",
    "game": "",
    "viewers": "305"
  },
  {
    "name": "paranga",
    "game": "Battlefield REDSEC",
    "viewers": "305"
  },
  {
    "name": "onepumpwillie",
    "game": "Dead by Daylight",
    "viewers": "304"
  },
  {
    "name": "client",
    "game": "Grand Theft Auto V",
    "viewers": "303"
  },
  {
    "name": "iriskpvp",
    "game": "Rust",
    "viewers": "303"
  },
  {
    "name": "maniika",
    "game": "EA Sports FC 26",
    "viewers": "303"
  },
  {
    "name": "stella",
    "game": "Old School RuneScape",
    "viewers": "302"
  },
  {
    "name": "prcs",
    "game": "Counter-Strike",
    "viewers": "302"
  },
  {
    "name": "alldaynyc",
    "game": "IRL",
    "viewers": "301"
  },
  {
    "name": "delux",
    "game": "Battlefield REDSEC",
    "viewers": "300"
  },
  {
    "name": "apenas1live",
    "game": "Just Chatting",
    "viewers": "299"
  },
  {
    "name": "geschriebene_geschichte",
    "game": "Writing & Reading",
    "viewers": "299"
  },
  {
    "name": "nadeshotvod",
    "game": "BATTLEFIELD 6",
    "viewers": "299"
  },
  {
    "name": "conducteir77",
    "game": "Dead by Daylight",
    "viewers": "298"
  },
  {
    "name": "j0j0c69",
    "game": "Slots",
    "viewers": "298"
  },
  {
    "name": "juakynen",
    "game": "Sports",
    "viewers": "298"
  },
  {
    "name": "nathansothershow",
    "game": "Baldur's Gate 3",
    "viewers": "298"
  },
  {
    "name": "scipionista",
    "game": "Sports",
    "viewers": "298"
  },
  {
    "name": "alvini98",
    "game": "Sports",
    "viewers": "297"
  },
  {
    "name": "andreadel1988",
    "game": "Among Us",
    "viewers": "296"
  },
  {
    "name": "manutegaming",
    "game": "Teamfight Tactics",
    "viewers": "296"
  },
  {
    "name": "phidx",
    "game": "2XKO",
    "viewers": "296"
  },
  {
    "name": "flokito_",
    "game": "Fortnite",
    "viewers": "295"
  },
  {
    "name": "kaysosa",
    "game": "Just Chatting",
    "viewers": "295"
  },
  {
    "name": "filiperaaamos",
    "game": "Dark Souls: Remastered",
    "viewers": "295"
  },
  {
    "name": "dub_ok_tv",
    "game": "Just Chatting",
    "viewers": "295"
  },
  {
    "name": "jermeeth",
    "game": "COMMUNITE",
    "viewers": "294"
  },
  {
    "name": "mbtyugioh",
    "game": "Just Chatting",
    "viewers": "294"
  },
  {
    "name": "tonytheduff",
    "game": "Dead by Daylight",
    "viewers": "294"
  },
  {
    "name": "bobbyzera",
    "game": "Virtual Casino",
    "viewers": "294"
  },
  {
    "name": "ivonyak",
    "game": "Battlefield REDSEC",
    "viewers": "294"
  },
  {
    "name": "anasse_kazib",
    "game": "Just Chatting",
    "viewers": "292"
  },
  {
    "name": "edennymph",
    "game": "Just Chatting",
    "viewers": "292"
  },
  {
    "name": "hydraoffi",
    "game": "Call of Duty: Warzone",
    "viewers": "292"
  },
  {
    "name": "chulo2funny",
    "game": "IRL",
    "viewers": "291"
  },
  {
    "name": "bobleexciv",
    "game": "Grand Theft Auto V",
    "viewers": "291"
  },
  {
    "name": "jmarianne",
    "game": "Co-working & Studying",
    "viewers": "290"
  },
  {
    "name": "erispheria",
    "game": "Metro 2033",
    "viewers": "290"
  },
  {
    "name": "momsyfnv2",
    "game": "Fortnite",
    "viewers": "290"
  },
  {
    "name": "tvabdou",
    "game": "Just Chatting",
    "viewers": "290"
  },
  {
    "name": "threedogg",
    "game": "Forbidden Siren 2",
    "viewers": "290"
  },
  {
    "name": "scott",
    "game": "Just Chatting",
    "viewers": "290"
  },
  {
    "name": "jeanfaymas",
    "game": "Just Chatting",
    "viewers": "290"
  },
  {
    "name": "ihw666",
    "game": "Just Chatting",
    "viewers": "289"
  },
  {
    "name": "nothingbutskillz",
    "game": "Tom Clancy's The Division 2",
    "viewers": "289"
  },
  {
    "name": "rockstarcr",
    "game": "Clash Royale",
    "viewers": "289"
  },
  {
    "name": "raimakgames",
    "game": "Dead by Daylight",
    "viewers": "289"
  },
  {
    "name": "imaginago_tv",
    "game": "Just Chatting",
    "viewers": "288"
  },
  {
    "name": "popsbarngrill",
    "game": "World of Warcraft",
    "viewers": "288"
  },
  {
    "name": "limbosauce",
    "game": "Genshin Impact",
    "viewers": "288"
  },
  {
    "name": "mogi",
    "game": "VALORANT",
    "viewers": "287"
  },
  {
    "name": "rouszztrash",
    "game": "Dota 2",
    "viewers": "287"
  },
  {
    "name": "spooknjukes",
    "game": "Dead by Daylight",
    "viewers": "287"
  },
  {
    "name": "lightbringer_dl",
    "game": "Deadlock",
    "viewers": "287"
  },
  {
    "name": "dvniel_play",
    "game": "Grand Theft Auto V",
    "viewers": "287"
  },
  {
    "name": "arlan360live",
    "game": "Just Chatting",
    "viewers": "286"
  },
  {
    "name": "fabiomtc_",
    "game": "EA Sports FC 26",
    "viewers": "286"
  },
  {
    "name": "zelalbade",
    "game": "Rise Online",
    "viewers": "285"
  },
  {
    "name": "sumono33",
    "game": "SUPER GHOULS'N GHOSTS",
    "viewers": "285"
  },
  {
    "name": "goodboy_tv",
    "game": "Path of Exile",
    "viewers": "285"
  },
  {
    "name": "caliebre",
    "game": "Skinfreak",
    "viewers": "284"
  },
  {
    "name": "kalathraslolweapon",
    "game": "Just Chatting",
    "viewers": "284"
  },
  {
    "name": "auteru",
    "game": "SILENT HILL ƒ",
    "viewers": "284"
  },
  {
    "name": "mc_douglax",
    "game": "Just Chatting",
    "viewers": "283"
  },
  {
    "name": "minikomew",
    "game": "Until Dawn",
    "viewers": "283"
  },
  {
    "name": "molgoatkirby",
    "game": "Old School RuneScape",
    "viewers": "283"
  },
  {
    "name": "rakattack",
    "game": "Overwatch 2",
    "viewers": "283"
  },
  {
    "name": "kseniya_soda",
    "game": "Just Chatting",
    "viewers": "283"
  },
  {
    "name": "maanigold",
    "game": "Guild Wars 2",
    "viewers": "282"
  },
  {
    "name": "milquetoast_claire",
    "game": "Project Zomboid",
    "viewers": "282"
  },
  {
    "name": "lege",
    "game": "Sid Meier's Civilization VI",
    "viewers": "282"
  },
  {
    "name": "bababartunek",
    "game": "Just Chatting",
    "viewers": "281"
  },
  {
    "name": "thabeast721",
    "game": "Retro",
    "viewers": "281"
  },
  {
    "name": "marbu_tv",
    "game": "EA Sports FC 26",
    "viewers": "279"
  },
  {
    "name": "gent",
    "game": "Apex Legends",
    "viewers": "278"
  },
  {
    "name": "myaustinwhite",
    "game": "Just Chatting",
    "viewers": "278"
  },
  {
    "name": "jakertonyt",
    "game": "Just Chatting",
    "viewers": "278"
  },
  {
    "name": "fred1uk",
    "game": "Counter-Strike",
    "viewers": "277"
  },
  {
    "name": "almighty9od",
    "game": "VALORANT",
    "viewers": "275"
  },
  {
    "name": "cahlaflour",
    "game": "RV There Yet?",
    "viewers": "275"
  },
  {
    "name": "kotzwurst",
    "game": "The Outlast Trials",
    "viewers": "275"
  },
  {
    "name": "cheatah_tv",
    "game": "Megabonk",
    "viewers": "275"
  },
  {
    "name": "stdantewhale",
    "game": "Albion Online",
    "viewers": "274"
  },
  {
    "name": "sennyk4",
    "game": "Just Chatting",
    "viewers": "272"
  },
  {
    "name": "ptownrocks",
    "game": "FINAL FANTASY VII",
    "viewers": "270"
  }
]