[
  {
    "name": "zackrawrr",
    "game": "Solo Leveling: ARISE OVERDRIVE",
    "viewers": "32828"
  },
  {
    "name": "hasanabi",
    "game": "Just Chatting",
    "viewers": "28762"
  },
  {
    "name": "jynxzi",
    "game": "Clash Royale",
    "viewers": "28754"
  },
  {
    "name": "tumblurr",
    "game": "Liar's Bar",
    "viewers": "28127"
  },
  {
    "name": "lvndmark",
    "game": "Escape from Tarkov",
    "viewers": "23351"
  },
  {
    "name": "jasontheween",
    "game": "Just Chatting",
    "viewers": "18085"
  },
  {
    "name": "aminematue",
    "game": "Just Chatting",
    "viewers": "17673"
  },
  {
    "name": "2xrakai",
    "game": "IRL",
    "viewers": "17584"
  },
  {
    "name": "jltomy",
    "game": "Grand Theft Auto V",
    "viewers": "16451"
  },
  {
    "name": "shroud",
    "game": "ARC Raiders",
    "viewers": "14357"
  },
  {
    "name": "lacy",
    "game": "Just Chatting",
    "viewers": "14258"
  },
  {
    "name": "elxokas",
    "game": "Minecraft",
    "viewers": "13890"
  },
  {
    "name": "alanzoka",
    "game": "MARVEL Cosmic Invasion",
    "viewers": "13751"
  },
  {
    "name": "loud_coringa",
    "game": "Just Chatting",
    "viewers": "11930"
  },
  {
    "name": "papaplatte",
    "game": "World of Warcraft",
    "viewers": "11288"
  },
  {
    "name": "wendolynortizz",
    "game": "IRL",
    "viewers": "11153"
  },
  {
    "name": "dona",
    "game": "Virtual Casino",
    "viewers": "11063"
  },
  {
    "name": "giggand",
    "game": "Grand Theft Auto V",
    "viewers": "10921"
  },
  {
    "name": "sodapoppin",
    "game": "World of Warcraft",
    "viewers": "10639"
  },
  {
    "name": "nrg_hamlinz",
    "game": "ARC Raiders",
    "viewers": "10599"
  },
  {
    "name": "jonvlogs",
    "game": "Just Chatting",
    "viewers": "10400"
  },
  {
    "name": "moonmoon",
    "game": "Mount & Blade II: Bannerlord",
    "viewers": "9889"
  },
  {
    "name": "summit1g",
    "game": "ARC Raiders",
    "viewers": "9317"
  },
  {
    "name": "kamet0",
    "game": "Grand Theft Auto V",
    "viewers": "8772"
  },
  {
    "name": "cinna",
    "game": "Just Chatting",
    "viewers": "8643"
  },
  {
    "name": "fps_shaka",
    "game": "Escape from Tarkov",
    "viewers": "8405"
  },
  {
    "name": "lord_kebun",
    "game": "Grand Theft Auto V",
    "viewers": "8398"
  },
  {
    "name": "domingo",
    "game": "League of Legends",
    "viewers": "8091"
  },
  {
    "name": "tigz",
    "game": "Escape from Tarkov",
    "viewers": "7642"
  },
  {
    "name": "joe_bartolozzi",
    "game": "Minecraft",
    "viewers": "7576"
  },
  {
    "name": "loltyler1",
    "game": "Minecraft",
    "viewers": "7278"
  },
  {
    "name": "filian",
    "game": "Just Chatting",
    "viewers": "7178"
  },
  {
    "name": "nico_la",
    "game": "Just Chatting",
    "viewers": "7016"
  },
  {
    "name": "baz1221",
    "game": "Counter-Strike",
    "viewers": "6818"
  },
  {
    "name": "folagorlives",
    "game": "Pokémon Platinum Version",
    "viewers": "6809"
  },
  {
    "name": "pauleta_twitch",
    "game": "Just Chatting",
    "viewers": "6629"
  },
  {
    "name": "quickybaby",
    "game": "World of Tanks",
    "viewers": "6353"
  },
  {
    "name": "happyhappygal",
    "game": "Fortnite",
    "viewers": "6294"
  },
  {
    "name": "ninja",
    "game": "ARC Raiders",
    "viewers": "6247"
  },
  {
    "name": "xaryu",
    "game": "World of Warcraft",
    "viewers": "5780"
  },
  {
    "name": "dougdoug",
    "game": "Donkey Kong Country 3: Dixie Kong's Double Trouble!",
    "viewers": "5562"
  },
  {
    "name": "erobb221",
    "game": "MLB The Show 25",
    "viewers": "5560"
  },
  {
    "name": "clix",
    "game": "Fortnite",
    "viewers": "5424"
  },
  {
    "name": "solo",
    "game": "Dota 2",
    "viewers": "5148"
  },
  {
    "name": "myth",
    "game": "ARC Raiders",
    "viewers": "5109"
  },
  {
    "name": "grubby",
    "game": "Warcraft III",
    "viewers": "5023"
  },
  {
    "name": "godmota",
    "game": "Special Events",
    "viewers": "4981"
  },
  {
    "name": "squeex",
    "game": "Super Mario 64",
    "viewers": "4928"
  },
  {
    "name": "bonjwachill",
    "game": "ARC Raiders",
    "viewers": "4614"
  },
  {
    "name": "cloakzy",
    "game": "ARC Raiders",
    "viewers": "4602"
  },
  {
    "name": "sheefgg",
    "game": "Escape from Tarkov",
    "viewers": "4597"
  },
  {
    "name": "scump",
    "game": "Call of Duty: Black Ops 7",
    "viewers": "4585"
  },
  {
    "name": "zentreya",
    "game": "Just Chatting",
    "viewers": "4500"
  },
  {
    "name": "knekro",
    "game": "Clair Obscur: Expedition 33",
    "viewers": "4476"
  },
  {
    "name": "krokoboss",
    "game": "League of Legends",
    "viewers": "4252"
  },
  {
    "name": "therealmarzaa",
    "game": "Liar's Bar",
    "viewers": "4212"
  },
  {
    "name": "realkatieb",
    "game": "Just Chatting",
    "viewers": "4031"
  },
  {
    "name": "ratirl",
    "game": "League of Legends",
    "viewers": "3997"
  },
  {
    "name": "baitybait",
    "game": "Shadow of the Colossus",
    "viewers": "3883"
  },
  {
    "name": "tarik",
    "game": "VALORANT",
    "viewers": "3856"
  },
  {
    "name": "formal",
    "game": "Call of Duty: Black Ops 7",
    "viewers": "3801"
  },
  {
    "name": "imperialhal__",
    "game": "Apex Legends",
    "viewers": "3783"
  },
  {
    "name": "voodoosh",
    "game": "Heroes of Might and Magic III: The Restoration of Erathia",
    "viewers": "3720"
  },
  {
    "name": "peereira7",
    "game": "Fortnite",
    "viewers": "3715"
  },
  {
    "name": "otzdarva",
    "game": "Dead by Daylight",
    "viewers": "3702"
  },
  {
    "name": "cohhcarnage",
    "game": "ARC Raiders",
    "viewers": "3695"
  },
  {
    "name": "sakurashymko",
    "game": "Just Chatting",
    "viewers": "3673"
  },
  {
    "name": "evelynomadera",
    "game": "IRL",
    "viewers": "3660"
  },
  {
    "name": "ratedepicz",
    "game": "Grand Theft Auto V",
    "viewers": "3653"
  },
  {
    "name": "elotrix",
    "game": "ARC Raiders",
    "viewers": "3590"
  },
  {
    "name": "rocky_",
    "game": "EA Sports FC 26",
    "viewers": "3566"
  },
  {
    "name": "a1000281",
    "game": "Just Chatting",
    "viewers": "3407"
  },
  {
    "name": "zoil",
    "game": "Just Chatting",
    "viewers": "3343"
  },
  {
    "name": "skipnho",
    "game": "Just Chatting",
    "viewers": "3302"
  },
  {
    "name": "chilledchaos",
    "game": "PlateUp!",
    "viewers": "3287"
  },
  {
    "name": "lilsimsie",
    "game": "Animal Crossing: New Horizons",
    "viewers": "3232"
  },
  {
    "name": "orslok",
    "game": "Fortnite",
    "viewers": "3203"
  },
  {
    "name": "dakillzor",
    "game": "World of Tanks",
    "viewers": "3121"
  },
  {
    "name": "polina__li",
    "game": "Just Chatting",
    "viewers": "3073"
  },
  {
    "name": "misoniq",
    "game": "Just Chatting",
    "viewers": "3034"
  },
  {
    "name": "justcooman",
    "game": "Dota 2",
    "viewers": "3010"
  },
  {
    "name": "drututt",
    "game": "League of Legends",
    "viewers": "3010"
  },
  {
    "name": "zwebackhd",
    "game": "EA Sports FC 26",
    "viewers": "2996"
  },
  {
    "name": "thesketchreal",
    "game": "Just Chatting",
    "viewers": "2978"
  },
  {
    "name": "henyathegenius",
    "game": "Just Chatting",
    "viewers": "2925"
  },
  {
    "name": "follentass",
    "game": "Just Chatting",
    "viewers": "2878"
  },
  {
    "name": "pobelter",
    "game": "League of Legends",
    "viewers": "2872"
  },
  {
    "name": "edizderbreite",
    "game": "Grand Theft Auto V",
    "viewers": "2866"
  },
  {
    "name": "theburntpeanut_247",
    "game": "Always On",
    "viewers": "2759"
  },
  {
    "name": "smallant",
    "game": "Super Mario Odyssey",
    "viewers": "2742"
  },
  {
    "name": "im_dontai",
    "game": "Just Chatting",
    "viewers": "2729"
  },
  {
    "name": "missmikkaa",
    "game": "The Walking Dead",
    "viewers": "2702"
  },
  {
    "name": "beterbabbit",
    "game": "Hearthstone",
    "viewers": "2664"
  },
  {
    "name": "dvm_medja",
    "game": "Grand Theft Auto V",
    "viewers": "2664"
  },
  {
    "name": "atrioc",
    "game": "Just Chatting",
    "viewers": "2637"
  },
  {
    "name": "nissaxter",
    "game": "League of Legends",
    "viewers": "2628"
  },
  {
    "name": "zibert1715_",
    "game": "Counter-Strike",
    "viewers": "2613"
  },
  {
    "name": "koskynho",
    "game": "Just Chatting",
    "viewers": "2574"
  },
  {
    "name": "foolish",
    "game": "VALORANT",
    "viewers": "2497"
  },
  {
    "name": "mrsal_59",
    "game": "Grand Theft Auto V",
    "viewers": "2490"
  },
  {
    "name": "ilame",
    "game": "ARC Raiders",
    "viewers": "2478"
  },
  {
    "name": "suetam1v4",
    "game": "Clash Royale",
    "viewers": "2477"
  },
  {
    "name": "russiamentop",
    "game": "PUBG: BATTLEGROUNDS",
    "viewers": "2460"
  },
  {
    "name": "jabroni_mike",
    "game": "Just Chatting",
    "viewers": "2443"
  },
  {
    "name": "axtlol",
    "game": "ARC Raiders",
    "viewers": "2393"
  },
  {
    "name": "nikos",
    "game": "Grand Theft Auto V",
    "viewers": "2377"
  },
  {
    "name": "shawdfxc",
    "game": "Counter-Strike",
    "viewers": "2360"
  },
  {
    "name": "lenag0lovach_572403",
    "game": "Dota 2",
    "viewers": "2341"
  },
  {
    "name": "w33haa",
    "game": "Dota 2",
    "viewers": "2332"
  },
  {
    "name": "sykkuno",
    "game": "Grand Theft Auto V",
    "viewers": "2324"
  },
  {
    "name": "treyjenk",
    "game": "Grand Theft Auto V",
    "viewers": "2283"
  },
  {
    "name": "kaydop",
    "game": "Rocket League",
    "viewers": "2279"
  },
  {
    "name": "camellia",
    "game": "Outer Wilds",
    "viewers": "2261"
  },
  {
    "name": "wavygocrazy_247",
    "game": "Call of Duty: Warzone",
    "viewers": "2239"
  },
  {
    "name": "sakoneko",
    "game": "Art",
    "viewers": "2230"
  },
  {
    "name": "baxbeast",
    "game": "Escape from Tarkov",
    "viewers": "2224"
  },
  {
    "name": "yurnboi",
    "game": "IRL",
    "viewers": "2206"
  },
  {
    "name": "judah_xx",
    "game": "Dota 2",
    "viewers": "2203"
  },
  {
    "name": "thomppssonn",
    "game": "Just Chatting",
    "viewers": "2195"
  },
  {
    "name": "officermesser",
    "game": "Grand Theft Auto V",
    "viewers": "2186"
  },
  {
    "name": "hexy",
    "game": "Games + Demos",
    "viewers": "2129"
  },
  {
    "name": "smugalana",
    "game": "Just Chatting",
    "viewers": "2129"
  },
  {
    "name": "sheviiioficial",
    "game": "Just Chatting",
    "viewers": "2124"
  },
  {
    "name": "swagg",
    "game": "Call of Duty: Black Ops 7",
    "viewers": "2111"
  },
  {
    "name": "nightkillakills",
    "game": "Just Chatting",
    "viewers": "2109"
  },
  {
    "name": "masondota2",
    "game": "Dota 2",
    "viewers": "2100"
  },
  {
    "name": "uuraniummm",
    "game": "Just Chatting",
    "viewers": "2092"
  },
  {
    "name": "yznsa",
    "game": "Marvel Rivals",
    "viewers": "2042"
  },
  {
    "name": "yanderegg",
    "game": "Special Events",
    "viewers": "2030"
  },
  {
    "name": "kingslots10",
    "game": "Virtual Casino",
    "viewers": "2010"
  },
  {
    "name": "antilipsi",
    "game": "League of Legends",
    "viewers": "2001"
  },
  {
    "name": "wasianiverson",
    "game": "Teamfight Tactics",
    "viewers": "1982"
  },
  {
    "name": "littlebigwhale",
    "game": "ARC Raiders",
    "viewers": "1974"
  },
  {
    "name": "mortenroyale",
    "game": "Clash Royale",
    "viewers": "1945"
  },
  {
    "name": "pieface23",
    "game": "EA Sports FC 26",
    "viewers": "1942"
  },
  {
    "name": "waolol1",
    "game": "League of Legends",
    "viewers": "1924"
  },
  {
    "name": "jamodo",
    "game": "EA Sports FC 26",
    "viewers": "1904"
  },
  {
    "name": "brawks",
    "game": "VALORANT",
    "viewers": "1856"
  },
  {
    "name": "surskity11",
    "game": "Just Chatting",
    "viewers": "1850"
  },
  {
    "name": "humzh",
    "game": "League of Legends",
    "viewers": "1834"
  },
  {
    "name": "kattpaccino",
    "game": "Just Chatting",
    "viewers": "1814"
  },
  {
    "name": "clownpiercenl",
    "game": "Minecraft",
    "viewers": "1813"
  },
  {
    "name": "teegrizzley",
    "game": "Bodycam",
    "viewers": "1776"
  },
  {
    "name": "nykchazza",
    "game": "Just Chatting",
    "viewers": "1773"
  },
  {
    "name": "conterstine",
    "game": "Minecraft",
    "viewers": "1763"
  },
  {
    "name": "frodan",
    "game": "Teamfight Tactics",
    "viewers": "1761"
  },
  {
    "name": "carola",
    "game": "HITMAN World of Assassination",
    "viewers": "1754"
  },
  {
    "name": "esfandtv",
    "game": "World of Warcraft",
    "viewers": "1674"
  },
  {
    "name": "ocwsport",
    "game": "Sports",
    "viewers": "1674"
  },
  {
    "name": "ismeiow",
    "game": "Just Chatting",
    "viewers": "1668"
  },
  {
    "name": "chatterbox",
    "game": "Grand Theft Auto V",
    "viewers": "1665"
  },
  {
    "name": "jay3",
    "game": "Overwatch 2",
    "viewers": "1661"
  },
  {
    "name": "onlyjson",
    "game": "Grand Theft Auto V",
    "viewers": "1652"
  },
  {
    "name": "rammdrian",
    "game": "Star Citizen",
    "viewers": "1614"
  },
  {
    "name": "barbarousking",
    "game": "Kingdom Hearts HD 1.5 + 2.5 ReMIX",
    "viewers": "1603"
  },
  {
    "name": "cineillojuan",
    "game": "Always On",
    "viewers": "1598"
  },
  {
    "name": "kukuroneko",
    "game": "ASMR",
    "viewers": "1578"
  },
  {
    "name": "sardaco",
    "game": "Old School RuneScape",
    "viewers": "1574"
  },
  {
    "name": "aussieantics",
    "game": "Fortnite",
    "viewers": "1569"
  },
  {
    "name": "gronkhtv",
    "game": "The Infected",
    "viewers": "1566"
  },
  {
    "name": "ekfqn75",
    "game": "Crypto",
    "viewers": "1554"
  },
  {
    "name": "mehdoche",
    "game": "Grand Theft Auto V",
    "viewers": "1545"
  },
  {
    "name": "pointcrow",
    "game": "Pokémon Platinum Version",
    "viewers": "1540"
  },
  {
    "name": "nyanners",
    "game": "Just Chatting",
    "viewers": "1536"
  },
  {
    "name": "celebi_cos",
    "game": "Just Chatting",
    "viewers": "1523"
  },
  {
    "name": "reudigruediger",
    "game": "Dead by Daylight",
    "viewers": "1516"
  },
  {
    "name": "brino",
    "game": "Just Chatting",
    "viewers": "1506"
  },
  {
    "name": "erbacce_cr",
    "game": "Clash Royale",
    "viewers": "1488"
  },
  {
    "name": "cozuvu99",
    "game": "Virtual Casino",
    "viewers": "1479"
  },
  {
    "name": "sypherpk",
    "game": "Fortnite",
    "viewers": "1476"
  },
  {
    "name": "hakaiwrld",
    "game": "Garry's Mod",
    "viewers": "1473"
  },
  {
    "name": "splinter",
    "game": "League of Legends",
    "viewers": "1473"
  },
  {
    "name": "k1anush",
    "game": "Just Chatting",
    "viewers": "1472"
  },
  {
    "name": "smzinho",
    "game": "Battlefield REDSEC",
    "viewers": "1468"
  },
  {
    "name": "circogg",
    "game": "Fortnite",
    "viewers": "1459"
  },
  {
    "name": "megalodonvt",
    "game": "Tattletail",
    "viewers": "1453"
  },
  {
    "name": "nooreax",
    "game": "Minecraft",
    "viewers": "1424"
  },
  {
    "name": "w0n23",
    "game": "Albion Online",
    "viewers": "1416"
  },
  {
    "name": "ds_lily",
    "game": "Diablo II",
    "viewers": "1414"
  },
  {
    "name": "tubbo",
    "game": "Minecraft",
    "viewers": "1406"
  },
  {
    "name": "polispol1",
    "game": "Minecraft",
    "viewers": "1392"
  },
  {
    "name": "couriway",
    "game": "Minecraft",
    "viewers": "1392"
  },
  {
    "name": "strippin",
    "game": "League of Legends",
    "viewers": "1380"
  },
  {
    "name": "imaqtpie",
    "game": "Teamfight Tactics",
    "viewers": "1379"
  },
  {
    "name": "kyr_sp33dy",
    "game": "PlateUp!",
    "viewers": "1377"
  },
  {
    "name": "renekreher",
    "game": "IRL",
    "viewers": "1375"
  },
  {
    "name": "miikelmst",
    "game": "EA Sports FC 26",
    "viewers": "1373"
  },
  {
    "name": "celestavt",
    "game": "Marvel Rivals",
    "viewers": "1371"
  },
  {
    "name": "ruetoo",
    "game": "Path of Exile",
    "viewers": "1368"
  },
  {
    "name": "vivalafazza",
    "game": "League of Legends",
    "viewers": "1366"
  },
  {
    "name": "theresnoee",
    "game": "IRL",
    "viewers": "1364"
  },
  {
    "name": "art_depo",
    "game": "Counter-Strike",
    "viewers": "1362"
  },
  {
    "name": "mathil1",
    "game": "Diablo II",
    "viewers": "1360"
  },
  {
    "name": "tekefiw80",
    "game": "Virtual Casino",
    "viewers": "1359"
  },
  {
    "name": "hollywood285",
    "game": "EA Sports FC 26",
    "viewers": "1357"
  },
  {
    "name": "repaz",
    "game": "A Way Out",
    "viewers": "1356"
  },
  {
    "name": "zerbs",
    "game": "Dead by Daylight",
    "viewers": "1354"
  },
  {
    "name": "barensz",
    "game": "Slots",
    "viewers": "1351"
  },
  {
    "name": "gaubera",
    "game": "Counter-Strike",
    "viewers": "1347"
  },
  {
    "name": "furl3x",
    "game": "Escape from Tarkov",
    "viewers": "1344"
  },
  {
    "name": "bagginstv",
    "game": "Where Winds Meet",
    "viewers": "1334"
  },
  {
    "name": "patuxd2c",
    "game": "Virtual Casino",
    "viewers": "1332"
  },
  {
    "name": "fanatixfire",
    "game": "Hearthstone",
    "viewers": "1329"
  },
  {
    "name": "streamnyc",
    "game": "",
    "viewers": "1316"
  },
  {
    "name": "desmondpilak",
    "game": "Escape from Tarkov",
    "viewers": "1316"
  },
  {
    "name": "elnueveenvivo",
    "game": "",
    "viewers": "1313"
  },
  {
    "name": "scarra",
    "game": "Teamfight Tactics",
    "viewers": "1312"
  },
  {
    "name": "calebhart42",
    "game": "FINAL FANTASY VII",
    "viewers": "1307"
  },
  {
    "name": "shadoune666",
    "game": "Minecraft",
    "viewers": "1306"
  },
  {
    "name": "eeveelinh",
    "game": "Street Fighter 6",
    "viewers": "1303"
  },
  {
    "name": "bustin",
    "game": "Dungeons & Dragons",
    "viewers": "1292"
  },
  {
    "name": "kiblester",
    "game": "Casino Simulator 2024",
    "viewers": "1289"
  },
  {
    "name": "yayahuz",
    "game": "Garena Free Fire",
    "viewers": "1275"
  },
  {
    "name": "juicy",
    "game": "Clash Royale",
    "viewers": "1271"
  },
  {
    "name": "oatsngoats",
    "game": "Metroid Prime 2: Echoes",
    "viewers": "1264"
  },
  {
    "name": "zerost_s",
    "game": "Shin Megami Tensei V: Vengeance",
    "viewers": "1252"
  },
  {
    "name": "solarbacca",
    "game": "League of Legends",
    "viewers": "1251"
  },
  {
    "name": "spraggy",
    "game": "Poker",
    "viewers": "1247"
  },
  {
    "name": "whylollycry",
    "game": "Just Chatting",
    "viewers": "1235"
  },
  {
    "name": "elpelotasssss",
    "game": "Albion Online",
    "viewers": "1230"
  },
  {
    "name": "croissantstriketv",
    "game": "Counter-Strike",
    "viewers": "1226"
  },
  {
    "name": "m0xyy",
    "game": "Marvel Rivals",
    "viewers": "1223"
  },
  {
    "name": "cerianmusic",
    "game": "Music",
    "viewers": "1222"
  },
  {
    "name": "datto",
    "game": "Destiny 2",
    "viewers": "1219"
  },
  {
    "name": "flyguncz",
    "game": "Geometry Dash",
    "viewers": "1218"
  },
  {
    "name": "mrtiboute",
    "game": "Phasmophobia",
    "viewers": "1216"
  },
  {
    "name": "phidx",
    "game": "TEKKEN 8",
    "viewers": "1212"
  },
  {
    "name": "la4awale",
    "game": "EA Sports FC 26",
    "viewers": "1204"
  },
  {
    "name": "ninadaddyisback",
    "game": "IRL",
    "viewers": "1189"
  },
  {
    "name": "moauba",
    "game": "EA Sports FC 26",
    "viewers": "1185"
  },
  {
    "name": "jakeydavies",
    "game": "Just Chatting",
    "viewers": "1183"
  },
  {
    "name": "stephenirl",
    "game": "Just Chatting",
    "viewers": "1181"
  },
  {
    "name": "lucajurman",
    "game": "Just Chatting",
    "viewers": "1179"
  },
  {
    "name": "caseoh247",
    "game": "Just Chatting",
    "viewers": "1177"
  },
  {
    "name": "captainlance9",
    "game": "Path of Exile",
    "viewers": "1164"
  },
  {
    "name": "lasqa",
    "game": "Yakuza Kiwami",
    "viewers": "1160"
  },
  {
    "name": "ginomachino",
    "game": "ELDEN RING",
    "viewers": "1151"
  },
  {
    "name": "tftoddy",
    "game": "Teamfight Tactics",
    "viewers": "1142"
  },
  {
    "name": "gaules",
    "game": "Counter-Strike",
    "viewers": "1139"
  },
  {
    "name": "fobm4ster",
    "game": "Arknights: Endfield",
    "viewers": "1138"
  },
  {
    "name": "chiblee",
    "game": "Violent Horror Stories 2",
    "viewers": "1136"
  },
  {
    "name": "pun1shers_tv",
    "game": "League of Legends",
    "viewers": "1132"
  },
  {
    "name": "aenot",
    "game": "Grand Theft Auto V",
    "viewers": "1130"
  },
  {
    "name": "filiperaaamos",
    "game": "Bloodborne",
    "viewers": "1129"
  },
  {
    "name": "themrsark",
    "game": "Darkwood",
    "viewers": "1120"
  },
  {
    "name": "theocacs",
    "game": "League of Legends",
    "viewers": "1112"
  },
  {
    "name": "snutzy",
    "game": "Slots",
    "viewers": "1108"
  },
  {
    "name": "honeypuu",
    "game": "Call of Duty: Black Ops 7",
    "viewers": "1103"
  },
  {
    "name": "burn",
    "game": "Grand Theft Auto V",
    "viewers": "1101"
  },
  {
    "name": "strawberrytabby",
    "game": "ARC Raiders",
    "viewers": "1099"
  },
  {
    "name": "leniniw",
    "game": "Counter-Strike",
    "viewers": "1098"
  },
  {
    "name": "royalistiq",
    "game": "Minecraft",
    "viewers": "1097"
  },
  {
    "name": "sheriffeli",
    "game": "Mount & Blade II: Bannerlord",
    "viewers": "1095"
  },
  {
    "name": "sydeon",
    "game": "Just Chatting",
    "viewers": "1079"
  },
  {
    "name": "ausrastenistmeinhobby",
    "game": "Grand Theft Auto V",
    "viewers": "1072"
  },
  {
    "name": "kanekolumi",
    "game": "Disco Elysium",
    "viewers": "1069"
  },
  {
    "name": "gladd",
    "game": "Planet Crafter",
    "viewers": "1065"
  },
  {
    "name": "alveussanctuary",
    "game": "Animals, Aquariums, and Zoos",
    "viewers": "1064"
  },
  {
    "name": "saltydolphin",
    "game": "Pokémon FireRed/LeafGreen",
    "viewers": "1061"
  },
  {
    "name": "kayzahr",
    "game": "ARC Raiders",
    "viewers": "1055"
  },
  {
    "name": "putrefy",
    "game": "Hogwarts Legacy",
    "viewers": "1053"
  },
  {
    "name": "uberhaxornova",
    "game": "Just Chatting",
    "viewers": "1051"
  },
  {
    "name": "nymphelia",
    "game": "ASMR",
    "viewers": "1047"
  },
  {
    "name": "roffle",
    "game": "Balatro",
    "viewers": "1037"
  },
  {
    "name": "blitzstream",
    "game": "Chess",
    "viewers": "1022"
  },
  {
    "name": "forzorezor",
    "game": "Counter-Strike",
    "viewers": "1013"
  },
  {
    "name": "rainbow6",
    "game": "Tom Clancy's Rainbow Six Siege X",
    "viewers": "1012"
  },
  {
    "name": "bbreadman",
    "game": "Battlefield REDSEC",
    "viewers": "1011"
  },
  {
    "name": "daltoosh",
    "game": "ARC Raiders",
    "viewers": "1011"
  },
  {
    "name": "djmissshelton",
    "game": "DJs",
    "viewers": "1010"
  },
  {
    "name": "zubaref_casino_6417008",
    "game": "",
    "viewers": "1009"
  },
  {
    "name": "viper",
    "game": "League of Legends",
    "viewers": "1005"
  },
  {
    "name": "juniperactias",
    "game": "Hollow Knight: Silksong",
    "viewers": "1003"
  },
  {
    "name": "simply",
    "game": "Tetris",
    "viewers": "1001"
  },
  {
    "name": "kastaclysm",
    "game": "The Spirit and the Mouse",
    "viewers": "996"
  },
  {
    "name": "coopertv",
    "game": "Counter-Strike",
    "viewers": "994"
  },
  {
    "name": "benjyfishy",
    "game": "League of Legends",
    "viewers": "992"
  },
  {
    "name": "treputin__lord_6606867",
    "game": "",
    "viewers": "992"
  },
  {
    "name": "vip07770",
    "game": "Just Chatting",
    "viewers": "990"
  },
  {
    "name": "miasova",
    "game": "ASMR",
    "viewers": "990"
  },
  {
    "name": "couragejd",
    "game": "Fortnite",
    "viewers": "989"
  },
  {
    "name": "burgaofps",
    "game": "Arena Breakout: Infinite",
    "viewers": "989"
  },
  {
    "name": "leothecrack",
    "game": "Fortnite",
    "viewers": "982"
  },
  {
    "name": "furo99",
    "game": "Grand Theft Auto V",
    "viewers": "976"
  },
  {
    "name": "derkc",
    "game": "EA Sports FC 26",
    "viewers": "975"
  },
  {
    "name": "tyrone",
    "game": "Grand Theft Auto V",
    "viewers": "975"
  },
  {
    "name": "sacy",
    "game": "ARC Raiders",
    "viewers": "971"
  },
  {
    "name": "berks",
    "game": "Star Citizen",
    "viewers": "963"
  },
  {
    "name": "captain_domo",
    "game": "ELDEN RING",
    "viewers": "960"
  },
  {
    "name": "redpandash",
    "game": "Delta Force",
    "viewers": "959"
  },
  {
    "name": "guit88man",
    "game": "Mir Tankov",
    "viewers": "959"
  },
  {
    "name": "dantes",
    "game": "League of Legends",
    "viewers": "958"
  },
  {
    "name": "aliciaxlife",
    "game": "Just Chatting",
    "viewers": "952"
  },
  {
    "name": "hanner",
    "game": "Just Chatting",
    "viewers": "945"
  },
  {
    "name": "sajam",
    "game": "2XKO",
    "viewers": "943"
  },
  {
    "name": "deedge_live",
    "game": "SIDE EFFECTS",
    "viewers": "939"
  },
  {
    "name": "robbaz",
    "game": "Mount & Blade II: Bannerlord",
    "viewers": "938"
  },
  {
    "name": "murdercrumpet",
    "game": "VRChat",
    "viewers": "935"
  },
  {
    "name": "ashlizzlle",
    "game": "Magic: The Gathering",
    "viewers": "933"
  },
  {
    "name": "zemie",
    "game": "Fortnite",
    "viewers": "932"
  },
  {
    "name": "tamatthi",
    "game": "Escape from Tarkov",
    "viewers": "932"
  },
  {
    "name": "stoopzz",
    "game": "Where Winds Meet",
    "viewers": "929"
  },
  {
    "name": "gordaons1",
    "game": "Grand Theft Auto V",
    "viewers": "926"
  },
  {
    "name": "roberttson",
    "game": "Just Chatting",
    "viewers": "922"
  },
  {
    "name": "beaulo",
    "game": "Tom Clancy's Rainbow Six Siege X",
    "viewers": "920"
  },
  {
    "name": "ster",
    "game": "Solo Leveling: ARISE OVERDRIVE",
    "viewers": "920"
  },
  {
    "name": "savix",
    "game": "World of Warcraft",
    "viewers": "919"
  },
  {
    "name": "alkaizerx",
    "game": "Diablo II",
    "viewers": "916"
  },
  {
    "name": "arielle",
    "game": "Just Chatting",
    "viewers": "913"
  },
  {
    "name": "nohandsgamer",
    "game": "Hearthstone",
    "viewers": "913"
  },
  {
    "name": "iateyourpie",
    "game": "Yu-Gi-Oh! Forbidden Memories",
    "viewers": "903"
  },
  {
    "name": "k1m6a",
    "game": "Crypto",
    "viewers": "901"
  },
  {
    "name": "tolkin",
    "game": "PUBG: BATTLEGROUNDS",
    "viewers": "899"
  },
  {
    "name": "trilluxe",
    "game": "Just Chatting",
    "viewers": "898"
  },
  {
    "name": "matta",
    "game": "Just Chatting",
    "viewers": "893"
  },
  {
    "name": "mikami_kon",
    "game": "ARC Raiders",
    "viewers": "892"
  },
  {
    "name": "mohleking",
    "game": "EA Sports FC 26",
    "viewers": "891"
  },
  {
    "name": "jelty",
    "game": "Fortnite",
    "viewers": "884"
  },
  {
    "name": "mirza_jahic",
    "game": "EA Sports FC 26",
    "viewers": "880"
  },
  {
    "name": "lobosjr",
    "game": "ELDEN RING",
    "viewers": "879"
  },
  {
    "name": "elquaria",
    "game": "A Way Out",
    "viewers": "866"
  },
  {
    "name": "bren_tm2",
    "game": "Trackmania",
    "viewers": "864"
  },
  {
    "name": "shahzam",
    "game": "VALORANT",
    "viewers": "862"
  },
  {
    "name": "uwoslab",
    "game": "Science & Technology",
    "viewers": "860"
  },
  {
    "name": "djjoaoraridade",
    "game": "DJs",
    "viewers": "859"
  },
  {
    "name": "papamutt",
    "game": "MARVEL Cosmic Invasion",
    "viewers": "857"
  },
  {
    "name": "sommerset",
    "game": "Fortnite",
    "viewers": "856"
  },
  {
    "name": "hadi_ow",
    "game": "Overwatch 2",
    "viewers": "854"
  },
  {
    "name": "drew_bills",
    "game": "Counter-Strike",
    "viewers": "852"
  },
  {
    "name": "mbtyugioh",
    "game": "Just Chatting",
    "viewers": "850"
  },
  {
    "name": "surefour",
    "game": "Fallout: New Vegas",
    "viewers": "848"
  },
  {
    "name": "itmejp",
    "game": "League of Legends",
    "viewers": "848"
  },
  {
    "name": "batalhadaaldeia",
    "game": "Music",
    "viewers": "847"
  },
  {
    "name": "zanfas_cenegal",
    "game": "Battlefield REDSEC",
    "viewers": "846"
  },
  {
    "name": "marex",
    "game": "",
    "viewers": "841"
  },
  {
    "name": "acie",
    "game": "Just Chatting",
    "viewers": "839"
  },
  {
    "name": "ricci",
    "game": "Call of Duty: Black Ops 7",
    "viewers": "838"
  },
  {
    "name": "call911_nowtv",
    "game": "World of Tanks",
    "viewers": "831"
  },
  {
    "name": "youngdabo",
    "game": "IRL",
    "viewers": "823"
  },
  {
    "name": "ranellebrown",
    "game": "Just Chatting",
    "viewers": "821"
  },
  {
    "name": "itsryanhiga",
    "game": "VALORANT",
    "viewers": "821"
  },
  {
    "name": "jankyrondo",
    "game": "Just Chatting",
    "viewers": "816"
  },
  {
    "name": "xchocobars",
    "game": "Teamfight Tactics",
    "viewers": "814"
  },
  {
    "name": "divios",
    "game": "Black Desert",
    "viewers": "813"
  },
  {
    "name": "buckefps",
    "game": "Fortnite",
    "viewers": "810"
  },
  {
    "name": "kong",
    "game": "Pools, Hot Tubs, and Beaches",
    "viewers": "806"
  },
  {
    "name": "porcelainmaid",
    "game": "Just Chatting",
    "viewers": "805"
  },
  {
    "name": "tikyjr",
    "game": "League of Legends",
    "viewers": "799"
  },
  {
    "name": "biggogamin",
    "game": "NBA 2K26",
    "viewers": "797"
  },
  {
    "name": "awsonair",
    "game": "Talk Shows & Podcasts",
    "viewers": "795"
  },
  {
    "name": "lizabaktt",
    "game": "Just Chatting",
    "viewers": "794"
  },
  {
    "name": "norafawn",
    "game": "Fortnite",
    "viewers": "791"
  },
  {
    "name": "iicka_dayo",
    "game": "Just Chatting",
    "viewers": "790"
  },
  {
    "name": "mickalow",
    "game": "ARC Raiders",
    "viewers": "789"
  },
  {
    "name": "purpled",
    "game": "Minecraft",
    "viewers": "789"
  },
  {
    "name": "llaviks",
    "game": "Just Chatting",
    "viewers": "788"
  },
  {
    "name": "elojoninja",
    "game": "League of Legends",
    "viewers": "787"
  },
  {
    "name": "blackmatrixishere",
    "game": "Battlefield 6",
    "viewers": "786"
  },
  {
    "name": "zbra",
    "game": "Overwatch 2",
    "viewers": "784"
  },
  {
    "name": "zherarrr",
    "game": "Heroes of Might and Magic III: The Restoration of Erathia",
    "viewers": "783"
  },
  {
    "name": "lethalfrag",
    "game": "Spelunky 2",
    "viewers": "782"
  },
  {
    "name": "botkz",
    "game": "Minecraft",
    "viewers": "774"
  },
  {
    "name": "roadhouse",
    "game": "Might and Magic VII: For Blood and Honor",
    "viewers": "774"
  },
  {
    "name": "mr_mammal",
    "game": "Old School RuneScape",
    "viewers": "773"
  },
  {
    "name": "zorlakoka",
    "game": "Counter-Strike",
    "viewers": "773"
  },
  {
    "name": "gzk_fps",
    "game": "Virtual Casino",
    "viewers": "771"
  },
  {
    "name": "bentopot",
    "game": "Just Chatting",
    "viewers": "771"
  },
  {
    "name": "dorki",
    "game": "World of Warcraft",
    "viewers": "769"
  },
  {
    "name": "fildrong",
    "game": "Pokémon Legends: Z-A",
    "viewers": "758"
  },
  {
    "name": "desperatenasus",
    "game": "League of Legends",
    "viewers": "755"
  },
  {
    "name": "lululuvely",
    "game": "Battlefield REDSEC",
    "viewers": "753"
  },
  {
    "name": "opat04",
    "game": "League of Legends",
    "viewers": "752"
  },
  {
    "name": "skillspecs",
    "game": "Old School RuneScape",
    "viewers": "749"
  },
  {
    "name": "proze",
    "game": "Call of Duty: Black Ops 7",
    "viewers": "748"
  },
  {
    "name": "stereonline",
    "game": "Just Chatting",
    "viewers": "744"
  },
  {
    "name": "giooomz",
    "game": "VALORANT",
    "viewers": "743"
  },
  {
    "name": "felikah",
    "game": "Minecraft",
    "viewers": "742"
  },
  {
    "name": "loyd",
    "game": "Grand Theft Auto V",
    "viewers": "742"
  },
  {
    "name": "army_guy_e8",
    "game": "World of Tanks",
    "viewers": "740"
  },
  {
    "name": "blaize",
    "game": "Just Chatting",
    "viewers": "737"
  },
  {
    "name": "coscu_casino_5450647",
    "game": "",
    "viewers": "735"
  },
  {
    "name": "yu_song",
    "game": "Mahjong Soul",
    "viewers": "734"
  },
  {
    "name": "casino_shadowkekw_2797841",
    "game": "Casino Simulator 2024",
    "viewers": "731"
  },
  {
    "name": "timmy2cans",
    "game": "ARC Raiders",
    "viewers": "731"
  },
  {
    "name": "kabhaal",
    "game": "HELLDIVERS 2",
    "viewers": "730"
  },
  {
    "name": "deadblossomjesse",
    "game": "Just Chatting",
    "viewers": "730"
  },
  {
    "name": "buster_slots_9848190",
    "game": "",
    "viewers": "725"
  },
  {
    "name": "wudijo",
    "game": "Diablo III",
    "viewers": "723"
  },
  {
    "name": "calango",
    "game": "Just Chatting",
    "viewers": "722"
  },
  {
    "name": "tamae_",
    "game": "Resident Evil 2",
    "viewers": "722"
  },
  {
    "name": "miguelspencer2020",
    "game": "",
    "viewers": "722"
  },
  {
    "name": "sharkie_tv",
    "game": "Counter-Strike",
    "viewers": "720"
  },
  {
    "name": "artur_zloy_9157877",
    "game": "",
    "viewers": "720"
  },
  {
    "name": "seucreysonreborn",
    "game": "Dota 2",
    "viewers": "719"
  },
  {
    "name": "raylene",
    "game": "Marvel Rivals",
    "viewers": "716"
  },
  {
    "name": "tolikthx",
    "game": "Just Chatting",
    "viewers": "715"
  },
  {
    "name": "tleyds",
    "game": "Teamfight Tactics",
    "viewers": "714"
  },
  {
    "name": "6746860",
    "game": "",
    "viewers": "710"
  },
  {
    "name": "meteos",
    "game": "League of Legends",
    "viewers": "709"
  },
  {
    "name": "casino_egorkreed_5070647",
    "game": "",
    "viewers": "709"
  },
  {
    "name": "mariosturniolo",
    "game": "Just Chatting",
    "viewers": "708"
  },
  {
    "name": "j0j0c69",
    "game": "League of Legends",
    "viewers": "708"
  },
  {
    "name": "carmen",
    "game": "Grand Theft Auto V",
    "viewers": "708"
  },
  {
    "name": "frg_casino_9514322",
    "game": "Fortnite",
    "viewers": "707"
  },
  {
    "name": "nagzz21",
    "game": "Super Mario 64",
    "viewers": "706"
  },
  {
    "name": "adamcrook",
    "game": "DayZ",
    "viewers": "705"
  },
  {
    "name": "splitsie",
    "game": "Space Engineers 2",
    "viewers": "704"
  },
  {
    "name": "xrick75",
    "game": "Grand Theft Auto V",
    "viewers": "703"
  },
  {
    "name": "thedarkraimola",
    "game": "Just Chatting",
    "viewers": "698"
  },
  {
    "name": "ziriguidum777",
    "game": "Virtual Casino",
    "viewers": "697"
  },
  {
    "name": "hpduketv",
    "game": "Bodycam",
    "viewers": "697"
  },
  {
    "name": "bgg02",
    "game": "FINAL FANTASY",
    "viewers": "696"
  },
  {
    "name": "maxon_zanos_5458903",
    "game": "Dota 2",
    "viewers": "694"
  },
  {
    "name": "3853639",
    "game": "",
    "viewers": "694"
  },
  {
    "name": "reemknocks",
    "game": "IRL",
    "viewers": "693"
  },
  {
    "name": "slipix",
    "game": "League of Legends",
    "viewers": "692"
  },
  {
    "name": "fesicuro",
    "game": "Just Chatting",
    "viewers": "683"
  },
  {
    "name": "puzanich_lots_2860362",
    "game": "Casino Simulator 2024",
    "viewers": "683"
  },
  {
    "name": "dooomcr",
    "game": "Clash Royale",
    "viewers": "682"
  },
  {
    "name": "sharkmacedo",
    "game": "EA Sports FC 26",
    "viewers": "682"
  },
  {
    "name": "snkarma",
    "game": "League of Legends",
    "viewers": "681"
  },
  {
    "name": "luxyry__girl_7570968",
    "game": "",
    "viewers": "681"
  },
  {
    "name": "fathersongaming",
    "game": "Spyro the Dragon",
    "viewers": "681"
  },
  {
    "name": "bonniealt",
    "game": "Just Chatting",
    "viewers": "680"
  },
  {
    "name": "timthetatmanvods",
    "game": "Always On",
    "viewers": "679"
  },
  {
    "name": "averse",
    "game": "Where Winds Meet",
    "viewers": "678"
  },
  {
    "name": "kimistreamt",
    "game": "Just Chatting",
    "viewers": "678"
  },
  {
    "name": "gocchanmikey",
    "game": "ARC Raiders",
    "viewers": "676"
  },
  {
    "name": "drdonutttttt",
    "game": "Minecraft",
    "viewers": "675"
  },
  {
    "name": "vegas",
    "game": "Deadlock",
    "viewers": "674"
  },
  {
    "name": "benzaie",
    "game": "MARVEL Cosmic Invasion",
    "viewers": "672"
  },
  {
    "name": "spartiatix",
    "game": "DARK SOULS III",
    "viewers": "671"
  },
  {
    "name": "herdyn",
    "game": "Just Chatting",
    "viewers": "670"
  },
  {
    "name": "ravanha69",
    "game": "Virtual Casino",
    "viewers": "668"
  },
  {
    "name": "cyyuvtuber",
    "game": "Just Chatting",
    "viewers": "666"
  },
  {
    "name": "sruser11",
    "game": "Virtual Casino",
    "viewers": "666"
  },
  {
    "name": "kanonxo",
    "game": "Where Winds Meet",
    "viewers": "662"
  },
  {
    "name": "dashretro",
    "game": "FINAL FANTASY VII",
    "viewers": "656"
  },
  {
    "name": "cantdie",
    "game": "Escape from Tarkov",
    "viewers": "654"
  },
  {
    "name": "mahmoojen",
    "game": "Just Chatting",
    "viewers": "654"
  },
  {
    "name": "narkuss_lol",
    "game": "League of Legends",
    "viewers": "653"
  },
  {
    "name": "camak",
    "game": "Grand Theft Auto V",
    "viewers": "652"
  },
  {
    "name": "dreads",
    "game": "Hearthstone",
    "viewers": "651"
  },
  {
    "name": "muts",
    "game": "Old School RuneScape",
    "viewers": "649"
  },
  {
    "name": "firedancer",
    "game": "Just Chatting",
    "viewers": "649"
  },
  {
    "name": "ernesto",
    "game": "EA Sports FC 26",
    "viewers": "648"
  },
  {
    "name": "csgoplayernoob1",
    "game": "Virtual Casino",
    "viewers": "648"
  },
  {
    "name": "sypeh",
    "game": "Marvel Rivals",
    "viewers": "647"
  },
  {
    "name": "inoiizy",
    "game": "ARC Raiders",
    "viewers": "647"
  },
  {
    "name": "lagoda",
    "game": "Euro Truck Simulator 2",
    "viewers": "644"
  },
  {
    "name": "knight",
    "game": "Call of Duty: Warzone",
    "viewers": "644"
  },
  {
    "name": "k13tv",
    "game": "Dota 2",
    "viewers": "643"
  },
  {
    "name": "drummondgx",
    "game": "Counter-Strike",
    "viewers": "643"
  },
  {
    "name": "leckerboy21",
    "game": "EA Sports FC 26",
    "viewers": "642"
  },
  {
    "name": "6bodya66",
    "game": "Counter-Strike",
    "viewers": "641"
  },
  {
    "name": "ferretsoftware",
    "game": "Animals, Aquariums, and Zoos",
    "viewers": "641"
  },
  {
    "name": "th3antonio",
    "game": "Escape from Tarkov",
    "viewers": "639"
  },
  {
    "name": "twincytv",
    "game": "Grand Theft Auto V",
    "viewers": "639"
  },
  {
    "name": "delux",
    "game": "ARC Raiders",
    "viewers": "639"
  },
  {
    "name": "kamicakes1",
    "game": "ASMR",
    "viewers": "638"
  },
  {
    "name": "isiinggunz",
    "game": "MapleStory",
    "viewers": "638"
  },
  {
    "name": "corgicam",
    "game": "Marbles on Stream",
    "viewers": "637"
  },
  {
    "name": "kalei",
    "game": "ARC Raiders",
    "viewers": "635"
  },
  {
    "name": "webhallen",
    "game": "Sonic Racing: CrossWorlds",
    "viewers": "635"
  },
  {
    "name": "reeze",
    "game": "World of Warcraft",
    "viewers": "635"
  },
  {
    "name": "guiixd1",
    "game": "EA Sports FC 26",
    "viewers": "634"
  },
  {
    "name": "noodlewolfvt",
    "game": "ASMR",
    "viewers": "634"
  },
  {
    "name": "chocotaco",
    "game": "Escape from Tarkov",
    "viewers": "633"
  },
  {
    "name": "kalle",
    "game": "Escape from Tarkov",
    "viewers": "626"
  },
  {
    "name": "savyultras90",
    "game": "Call of Duty: Warzone",
    "viewers": "626"
  },
  {
    "name": "mizitw",
    "game": "Call of Duty: Warzone",
    "viewers": "625"
  },
  {
    "name": "keeoh",
    "game": "VALORANT",
    "viewers": "624"
  },
  {
    "name": "moman",
    "game": "Grand Theft Auto V",
    "viewers": "623"
  },
  {
    "name": "lagmasterpiece",
    "game": "Just Chatting",
    "viewers": "622"
  },
  {
    "name": "wintergaming",
    "game": "They Are Billions",
    "viewers": "620"
  },
  {
    "name": "glepizs",
    "game": "Slots",
    "viewers": "619"
  },
  {
    "name": "yogscast",
    "game": "Just Chatting",
    "viewers": "616"
  },
  {
    "name": "yttalk2menice",
    "game": "Just Chatting",
    "viewers": "616"
  },
  {
    "name": "xthefarmerx",
    "game": "Path of Exile",
    "viewers": "614"
  },
  {
    "name": "carljrtm",
    "game": "Trackmania",
    "viewers": "614"
  },
  {
    "name": "knut",
    "game": "Just Chatting",
    "viewers": "613"
  },
  {
    "name": "replays",
    "game": "Fortnite",
    "viewers": "613"
  },
  {
    "name": "mushamaru_",
    "game": "Escape from Tarkov",
    "viewers": "609"
  },
  {
    "name": "p4perback",
    "game": "Lethal Company",
    "viewers": "607"
  },
  {
    "name": "sput",
    "game": "Vintage Story",
    "viewers": "602"
  },
  {
    "name": "joshog",
    "game": "Green Hell",
    "viewers": "602"
  },
  {
    "name": "ness",
    "game": "Hearthstone",
    "viewers": "601"
  },
  {
    "name": "mandymess",
    "game": "Dead by Daylight",
    "viewers": "598"
  },
  {
    "name": "geschriebene_geschichte",
    "game": "Writing & Reading",
    "viewers": "598"
  },
  {
    "name": "sandyjackson",
    "game": "Just Chatting",
    "viewers": "598"
  },
  {
    "name": "notgeega",
    "game": "ARC Raiders",
    "viewers": "597"
  },
  {
    "name": "anabancr",
    "game": "Clash Royale",
    "viewers": "597"
  },
  {
    "name": "nakkida",
    "game": "Grand Theft Auto V",
    "viewers": "596"
  },
  {
    "name": "lilyaang",
    "game": "VALORANT",
    "viewers": "596"
  },
  {
    "name": "heyar",
    "game": "ARC Raiders",
    "viewers": "594"
  },
  {
    "name": "cricoccia3",
    "game": "EA Sports FC 26",
    "viewers": "594"
  },
  {
    "name": "hamzapvris",
    "game": "EA Sports FC 26",
    "viewers": "592"
  },
  {
    "name": "poka",
    "game": "DARK SOULS III",
    "viewers": "591"
  },
  {
    "name": "icemanisaac",
    "game": "Battlefield REDSEC",
    "viewers": "588"
  },
  {
    "name": "passatigy",
    "game": "Of Ash and Steel",
    "viewers": "584"
  },
  {
    "name": "ap_r0se",
    "game": "Grand Theft Auto V",
    "viewers": "582"
  },
  {
    "name": "bobbyraygray",
    "game": "Grand Theft Auto V",
    "viewers": "582"
  },
  {
    "name": "jericho",
    "game": "Escape from Tarkov",
    "viewers": "580"
  },
  {
    "name": "katevolved",
    "game": "League of Legends",
    "viewers": "578"
  },
  {
    "name": "xari",
    "game": "Where Winds Meet",
    "viewers": "578"
  },
  {
    "name": "qassimiento",
    "game": "Grand Theft Auto V",
    "viewers": "577"
  },
  {
    "name": "alle",
    "game": "Escape from Tarkov",
    "viewers": "576"
  },
  {
    "name": "adef",
    "game": "ELDEN RING",
    "viewers": "575"
  },
  {
    "name": "ahlaundoh",
    "game": "World of Warcraft",
    "viewers": "573"
  },
  {
    "name": "kajzoo",
    "game": "World of Tanks",
    "viewers": "573"
  },
  {
    "name": "rugifobev",
    "game": "",
    "viewers": "571"
  },
  {
    "name": "vixella",
    "game": "Papa's Freezeria Deluxe",
    "viewers": "570"
  },
  {
    "name": "sunnysplosion",
    "game": "Clair Obscur: Expedition 33",
    "viewers": "569"
  },
  {
    "name": "kertus",
    "game": "Grand Theft Auto V",
    "viewers": "568"
  },
  {
    "name": "razah",
    "game": "Tom Clancy's Rainbow Six Siege X",
    "viewers": "567"
  },
  {
    "name": "jpkrez",
    "game": "Call of Duty: Black Ops 7",
    "viewers": "564"
  },
  {
    "name": "antedeguemonn",
    "game": "Tibia",
    "viewers": "564"
  },
  {
    "name": "calebdmtg",
    "game": "Magic: The Gathering",
    "viewers": "564"
  },
  {
    "name": "honeyxxo",
    "game": "Escape from Tarkov",
    "viewers": "563"
  },
  {
    "name": "hector",
    "game": "Grand Theft Auto V",
    "viewers": "561"
  },
  {
    "name": "rogue",
    "game": "Battlefield REDSEC",
    "viewers": "560"
  },
  {
    "name": "helenalive",
    "game": "Dota 2",
    "viewers": "555"
  },
  {
    "name": "xenosysvex",
    "game": "Dispatch",
    "viewers": "550"
  },
  {
    "name": "syanne",
    "game": "Just Chatting",
    "viewers": "550"
  },
  {
    "name": "stepz2",
    "game": "League of Legends",
    "viewers": "550"
  },
  {
    "name": "dahmien7",
    "game": "Escape from Tarkov",
    "viewers": "549"
  },
  {
    "name": "krytous_cs",
    "game": "Counter-Strike",
    "viewers": "549"
  },
  {
    "name": "overlordbou",
    "game": "World of Warships",
    "viewers": "548"
  },
  {
    "name": "whatifjulia",
    "game": "Animal Crossing: New Horizons",
    "viewers": "546"
  },
  {
    "name": "cepreu_inq",
    "game": "Aion 2",
    "viewers": "544"
  },
  {
    "name": "gewinnergamesbonuslot",
    "game": "Slots",
    "viewers": "542"
  },
  {
    "name": "0uahleouff",
    "game": "Fortnite",
    "viewers": "542"
  },
  {
    "name": "feliciaday",
    "game": "Cabernet",
    "viewers": "542"
  },
  {
    "name": "seoi1016",
    "game": "Just Chatting",
    "viewers": "541"
  },
  {
    "name": "gamedebookofrabonuslot",
    "game": "Slots",
    "viewers": "541"
  },
  {
    "name": "captainmyko",
    "game": "Rust",
    "viewers": "540"
  },
  {
    "name": "gamescage",
    "game": "MARVEL Cosmic Invasion",
    "viewers": "538"
  },
  {
    "name": "yokasiri",
    "game": "Minecraft",
    "viewers": "536"
  },
  {
    "name": "minos",
    "game": "Just Chatting",
    "viewers": "536"
  },
  {
    "name": "dcampion",
    "game": "Grand Theft Auto V",
    "viewers": "535"
  },
  {
    "name": "defakator_officiel",
    "game": "Just Chatting",
    "viewers": "535"
  },
  {
    "name": "livegametester24slots",
    "game": "Slots",
    "viewers": "534"
  },
  {
    "name": "forsa",
    "game": "ELDEN RING",
    "viewers": "534"
  },
  {
    "name": "d3ad_plays",
    "game": "Dead by Daylight",
    "viewers": "532"
  },
  {
    "name": "africaalbion",
    "game": "Albion Online",
    "viewers": "530"
  },
  {
    "name": "albyaround",
    "game": "Dead by Daylight",
    "viewers": "530"
  },
  {
    "name": "flishard",
    "game": "Virtual Casino",
    "viewers": "528"
  },
  {
    "name": "montegamebonuslot",
    "game": "Slots",
    "viewers": "528"
  },
  {
    "name": "faello1",
    "game": "Wuthering Waves",
    "viewers": "528"
  },
  {
    "name": "shrcs",
    "game": "Counter-Strike",
    "viewers": "526"
  },
  {
    "name": "sneegsnag",
    "game": "Minecraft",
    "viewers": "526"
  },
  {
    "name": "mobuckets",
    "game": "NBA 2K26",
    "viewers": "523"
  },
  {
    "name": "lollipop21k",
    "game": "Counter-Strike",
    "viewers": "522"
  },
  {
    "name": "bobbypoffgaming",
    "game": "Call of Duty: Warzone",
    "viewers": "520"
  },
  {
    "name": "a1dan8992",
    "game": "Rust",
    "viewers": "519"
  },
  {
    "name": "waitimcheating",
    "game": "Escape from Tarkov",
    "viewers": "519"
  },
  {
    "name": "djquethemixologist",
    "game": "DJs",
    "viewers": "519"
  },
  {
    "name": "hak1ramay",
    "game": "Counter-Strike",
    "viewers": "519"
  },
  {
    "name": "roozworld",
    "game": "Just Chatting",
    "viewers": "516"
  },
  {
    "name": "jojosaysbreee",
    "game": "Phasmophobia",
    "viewers": "516"
  },
  {
    "name": "cirno_tv",
    "game": "Castlevania: Dawn of Sorrow",
    "viewers": "516"
  },
  {
    "name": "mrxsmurf",
    "game": "Dota 2",
    "viewers": "515"
  },
  {
    "name": "renegade",
    "game": "Call of Duty: Black Ops 7",
    "viewers": "514"
  },
  {
    "name": "mblaoc",
    "game": "Age of Empires II",
    "viewers": "514"
  },
  {
    "name": "fabriziocerrone",
    "game": "IRL",
    "viewers": "514"
  },
  {
    "name": "norgamebonuslots",
    "game": "Slots",
    "viewers": "513"
  },
  {
    "name": "chrismelberger",
    "game": "Just Chatting",
    "viewers": "513"
  },
  {
    "name": "johnpal",
    "game": "Lost Ark",
    "viewers": "513"
  },
  {
    "name": "averageharry_",
    "game": "Just Chatting",
    "viewers": "512"
  },
  {
    "name": "artosis",
    "game": "StarCraft",
    "viewers": "510"
  },
  {
    "name": "fragas",
    "game": "Escape from Tarkov",
    "viewers": "510"
  },
  {
    "name": "ekkosuna",
    "game": "League of Legends",
    "viewers": "510"
  },
  {
    "name": "muriloso",
    "game": "Just Chatting",
    "viewers": "510"
  },
  {
    "name": "thiseguysessions",
    "game": "DJs",
    "viewers": "509"
  },
  {
    "name": "azulgg",
    "game": "Pokémon Trading Card Game Live",
    "viewers": "509"
  },
  {
    "name": "isko",
    "game": "Slots",
    "viewers": "509"
  },
  {
    "name": "jvzin7",
    "game": "Counter-Strike",
    "viewers": "508"
  },
  {
    "name": "rysiek",
    "game": "World of Tanks",
    "viewers": "507"
  },
  {
    "name": "qucee",
    "game": "Fall Guys",
    "viewers": "507"
  },
  {
    "name": "chrisudalla",
    "game": "Pokémon Infinite Fusion",
    "viewers": "506"
  },
  {
    "name": "linkzzey",
    "game": "Minecraft",
    "viewers": "506"
  },
  {
    "name": "zelalbade",
    "game": "Rise Online",
    "viewers": "505"
  },
  {
    "name": "binas",
    "game": "Escape from Tarkov",
    "viewers": "504"
  },
  {
    "name": "threedogg",
    "game": "HITMAN World of Assassination",
    "viewers": "504"
  },
  {
    "name": "danielslump",
    "game": "Call of Duty: Black Ops 7",
    "viewers": "503"
  },
  {
    "name": "aimbotcalvin",
    "game": "Deadlock",
    "viewers": "503"
  },
  {
    "name": "mainduc",
    "game": "Slots",
    "viewers": "501"
  },
  {
    "name": "hudsonamorm77",
    "game": "Virtual Casino",
    "viewers": "501"
  },
  {
    "name": "diegoruzzarin",
    "game": "Talk Shows & Podcasts",
    "viewers": "500"
  },
  {
    "name": "justandy89",
    "game": "ARC Raiders",
    "viewers": "499"
  },
  {
    "name": "mogsy",
    "game": "A.I.L.A",
    "viewers": "498"
  },
  {
    "name": "pantulive",
    "game": "Grand Theft Auto V",
    "viewers": "493"
  },
  {
    "name": "gluhammer",
    "game": "Heroes of Might and Magic III: The Restoration of Erathia",
    "viewers": "493"
  },
  {
    "name": "kutcherlol",
    "game": "World of Warcraft",
    "viewers": "492"
  },
  {
    "name": "nikomfps",
    "game": "Counter-Strike",
    "viewers": "491"
  },
  {
    "name": "claraatwork",
    "game": "Minecraft",
    "viewers": "490"
  },
  {
    "name": "ashmonsterftw",
    "game": "Five Hearts Under One Roof 2",
    "viewers": "489"
  },
  {
    "name": "aethelthryth",
    "game": "Just Chatting",
    "viewers": "489"
  },
  {
    "name": "scope",
    "game": "Call of Duty: Black Ops 7",
    "viewers": "489"
  },
  {
    "name": "ddooyaa",
    "game": "Just Chatting",
    "viewers": "488"
  },
  {
    "name": "weronest",
    "game": "Heroes of Might and Magic III: The Restoration of Erathia",
    "viewers": "488"
  },
  {
    "name": "tingting57",
    "game": "ASMR",
    "viewers": "486"
  },
  {
    "name": "enders",
    "game": "Battlefield REDSEC",
    "viewers": "486"
  },
  {
    "name": "moxsy",
    "game": "Path of Exile 2",
    "viewers": "486"
  },
  {
    "name": "basssultanhengzt45",
    "game": "Slots",
    "viewers": "486"
  },
  {
    "name": "raffale_",
    "game": "Just Chatting",
    "viewers": "485"
  },
  {
    "name": "abbramovich",
    "game": "Grand Theft Auto V",
    "viewers": "485"
  },
  {
    "name": "kant",
    "game": "Just Chatting",
    "viewers": "484"
  },
  {
    "name": "rodil",
    "game": "League of Legends",
    "viewers": "484"
  },
  {
    "name": "krabick",
    "game": "Rollerdrome",
    "viewers": "483"
  },
  {
    "name": "mezzogiorno",
    "game": "Grand Theft Auto V",
    "viewers": "483"
  },
  {
    "name": "gordiender",
    "game": "Virtual Casino",
    "viewers": "481"
  },
  {
    "name": "vladboyz",
    "game": "Just Chatting",
    "viewers": "481"
  },
  {
    "name": "voxy",
    "game": "Magic: The Gathering",
    "viewers": "481"
  },
  {
    "name": "stefaniejoosten",
    "game": "ARC Raiders",
    "viewers": "481"
  },
  {
    "name": "luxthos",
    "game": "World of Warcraft",
    "viewers": "480"
  },
  {
    "name": "nocriesof",
    "game": "Counter-Strike",
    "viewers": "479"
  },
  {
    "name": "zigofps",
    "game": "Grand Theft Auto V",
    "viewers": "479"
  },
  {
    "name": "makatao",
    "game": "ARC Raiders",
    "viewers": "479"
  },
  {
    "name": "sacriel",
    "game": "Fights in Tight Spaces",
    "viewers": "479"
  },
  {
    "name": "molodooyq",
    "game": "Dota 2",
    "viewers": "476"
  },
  {
    "name": "ikiimartin",
    "game": "EA Sports FC 26",
    "viewers": "475"
  },
  {
    "name": "etalyx",
    "game": "Mount & Blade II: Bannerlord",
    "viewers": "474"
  },
  {
    "name": "arrowcs",
    "game": "Counter-Strike",
    "viewers": "473"
  },
  {
    "name": "kaemii",
    "game": "VALORANT",
    "viewers": "472"
  },
  {
    "name": "synderen",
    "game": "Dota 2",
    "viewers": "472"
  },
  {
    "name": "uniquee",
    "game": "Dota 2",
    "viewers": "471"
  },
  {
    "name": "focusbf",
    "game": "Battlefield 6",
    "viewers": "471"
  },
  {
    "name": "albislol",
    "game": "FINAL FANTASY XIV ONLINE",
    "viewers": "470"
  },
  {
    "name": "iseedeadp3ople",
    "game": "Dota 2",
    "viewers": "470"
  },
  {
    "name": "low4n",
    "game": "ARC Raiders",
    "viewers": "470"
  },
  {
    "name": "fir_",
    "game": "Super Mario Odyssey",
    "viewers": "468"
  },
  {
    "name": "flapiix",
    "game": "Call of Duty: Black Ops 7",
    "viewers": "467"
  },
  {
    "name": "danoc0",
    "game": "Counter-Strike",
    "viewers": "466"
  },
  {
    "name": "winghaven",
    "game": "ARC Raiders",
    "viewers": "465"
  },
  {
    "name": "marzzzzy",
    "game": "Just Chatting",
    "viewers": "464"
  },
  {
    "name": "neet",
    "game": "VRChat",
    "viewers": "463"
  },
  {
    "name": "reet",
    "game": "Fortnite",
    "viewers": "463"
  },
  {
    "name": "ej_sa",
    "game": "Science & Technology",
    "viewers": "462"
  },
  {
    "name": "miyunie__",
    "game": "ASMR",
    "viewers": "457"
  },
  {
    "name": "adamvseverything",
    "game": "Baldur's Gate 3",
    "viewers": "456"
  },
  {
    "name": "tteuw",
    "game": "Just Chatting",
    "viewers": "455"
  },
  {
    "name": "gbln420",
    "game": "Detroit: Become Human",
    "viewers": "453"
  },
  {
    "name": "jeanfaymas",
    "game": "System Shock",
    "viewers": "452"
  },
  {
    "name": "timmy_poker",
    "game": "Poker",
    "viewers": "452"
  },
  {
    "name": "pesh",
    "game": "Liar's Bar",
    "viewers": "452"
  },
  {
    "name": "carolbalds",
    "game": "Just Chatting",
    "viewers": "452"
  },
  {
    "name": "capitanocima",
    "game": "Grand Theft Auto V",
    "viewers": "451"
  },
  {
    "name": "feeckz",
    "game": "Albion Online",
    "viewers": "450"
  },
  {
    "name": "scrubnoob",
    "game": "League of Legends",
    "viewers": "449"
  },
  {
    "name": "nickyy",
    "game": "Just Chatting",
    "viewers": "449"
  },
  {
    "name": "ghostiexuwu",
    "game": "ASMR",
    "viewers": "448"
  },
  {
    "name": "cash4kills_",
    "game": "Call of Duty: Warzone",
    "viewers": "447"
  },
  {
    "name": "thehamtv",
    "game": "Magic: The Gathering",
    "viewers": "447"
  },
  {
    "name": "blazx",
    "game": "Grand Theft Auto V",
    "viewers": "446"
  },
  {
    "name": "yugioh_official",
    "game": "Yu-Gi-Oh! Master Duel",
    "viewers": "445"
  },
  {
    "name": "shuteye_orange",
    "game": "Just Chatting",
    "viewers": "444"
  },
  {
    "name": "nicklink",
    "game": "League of Legends",
    "viewers": "444"
  },
  {
    "name": "hankstergirl",
    "game": "Tavern Manager Simulator",
    "viewers": "443"
  },
  {
    "name": "shivfps",
    "game": "Apex Legends",
    "viewers": "442"
  },
  {
    "name": "delt4forc3",
    "game": "IRL",
    "viewers": "441"
  },
  {
    "name": "sorrisodozorlak",
    "game": "Grand Theft Auto V",
    "viewers": "439"
  },
  {
    "name": "the8bitdrummer",
    "game": "Music",
    "viewers": "439"
  },
  {
    "name": "rifftrax",
    "game": "Always On",
    "viewers": "439"
  },
  {
    "name": "omendigotv",
    "game": "Slots",
    "viewers": "437"
  },
  {
    "name": "luckzin",
    "game": "Virtual Casino",
    "viewers": "437"
  },
  {
    "name": "bushszn",
    "game": "Fortnite",
    "viewers": "436"
  },
  {
    "name": "generatorfrajdy",
    "game": "DrainSim",
    "viewers": "436"
  },
  {
    "name": "poach",
    "game": "Delta Force",
    "viewers": "436"
  },
  {
    "name": "policechasenetwork",
    "game": "Just Chatting",
    "viewers": "435"
  },
  {
    "name": "drjayfisto",
    "game": "FELLOWSHIP",
    "viewers": "434"
  },
  {
    "name": "potasticp",
    "game": "Baldur's Gate 3",
    "viewers": "433"
  },
  {
    "name": "martiinezsa",
    "game": "Counter-Strike",
    "viewers": "433"
  },
  {
    "name": "woojungx4",
    "game": "Just Chatting",
    "viewers": "433"
  },
  {
    "name": "imgritside",
    "game": "Just Chatting",
    "viewers": "433"
  },
  {
    "name": "noahlunsi",
    "game": "Just Chatting",
    "viewers": "432"
  },
  {
    "name": "averagejonas",
    "game": "Deadlock",
    "viewers": "432"
  },
  {
    "name": "gioee",
    "game": "Just Chatting",
    "viewers": "431"
  },
  {
    "name": "mariotq",
    "game": "IRL",
    "viewers": "431"
  },
  {
    "name": "ruflesscat",
    "game": "Fortnite",
    "viewers": "431"
  },
  {
    "name": "fixlol1",
    "game": "League of Legends",
    "viewers": "430"
  },
  {
    "name": "zchum",
    "game": "Escape from Tarkov",
    "viewers": "430"
  },
  {
    "name": "isaacelera",
    "game": "EA Sports FC 26",
    "viewers": "430"
  },
  {
    "name": "joewo",
    "game": "Call of Duty: Warzone",
    "viewers": "429"
  },
  {
    "name": "daku",
    "game": "Once Human",
    "viewers": "429"
  },
  {
    "name": "alfie",
    "game": "Old School RuneScape",
    "viewers": "428"
  },
  {
    "name": "brutalmoose",
    "game": "Retro",
    "viewers": "428"
  },
  {
    "name": "chocokokko_",
    "game": "Just Chatting",
    "viewers": "427"
  },
  {
    "name": "rdcwaitingroom_",
    "game": "Just Chatting",
    "viewers": "427"
  },
  {
    "name": "jmdeck",
    "game": "Call of Duty: Warzone",
    "viewers": "426"
  },
  {
    "name": "steelmixok",
    "game": "DJs",
    "viewers": "426"
  },
  {
    "name": "itsmoshimadden",
    "game": "Madden NFL 26",
    "viewers": "426"
  },
  {
    "name": "hotbeatstv",
    "game": "DJs",
    "viewers": "426"
  },
  {
    "name": "thugfaast",
    "game": "Virtual Casino",
    "viewers": "423"
  },
  {
    "name": "sabrinoca",
    "game": "Fortnite",
    "viewers": "423"
  },
  {
    "name": "reidboyy",
    "game": "Call of Duty: Black Ops 7",
    "viewers": "422"
  },
  {
    "name": "joltzdude139",
    "game": "Borderlands 2",
    "viewers": "422"
  },
  {
    "name": "jakeey",
    "game": "ARC Raiders",
    "viewers": "422"
  },
  {
    "name": "todurooficial",
    "game": "Grand Theft Auto V",
    "viewers": "420"
  },
  {
    "name": "elvisayomastercard",
    "game": "Grand Theft Auto V",
    "viewers": "417"
  },
  {
    "name": "scottjund",
    "game": "Dark Souls: Remastered",
    "viewers": "416"
  },
  {
    "name": "grimmmz",
    "game": "ARC Raiders",
    "viewers": "416"
  },
  {
    "name": "cerebrocule",
    "game": "Sports",
    "viewers": "414"
  },
  {
    "name": "lolmechs",
    "game": "League of Legends",
    "viewers": "414"
  },
  {
    "name": "kayanetv",
    "game": "TEKKEN 8",
    "viewers": "414"
  },
  {
    "name": "taylien",
    "game": "Just Chatting",
    "viewers": "414"
  },
  {
    "name": "math6tv",
    "game": "Just Chatting",
    "viewers": "414"
  },
  {
    "name": "streamerhouse",
    "game": "Where Winds Meet",
    "viewers": "412"
  },
  {
    "name": "shannonmais",
    "game": "Just Chatting",
    "viewers": "412"
  },
  {
    "name": "andreynoiles",
    "game": "Detroit: Become Human",
    "viewers": "411"
  },
  {
    "name": "rglqq",
    "game": "Battlefield 6",
    "viewers": "411"
  },
  {
    "name": "magiemaz",
    "game": "Slots",
    "viewers": "411"
  },
  {
    "name": "magistorkaga",
    "game": "Mobile Legends: Bang Bang",
    "viewers": "411"
  },
  {
    "name": "kylebosman",
    "game": "Shining Force",
    "viewers": "411"
  },
  {
    "name": "bachelorbby",
    "game": "Just Chatting",
    "viewers": "411"
  },
  {
    "name": "serpent",
    "game": "Balatro",
    "viewers": "410"
  },
  {
    "name": "lgoony",
    "game": "Just Chatting",
    "viewers": "410"
  },
  {
    "name": "qtzynderella",
    "game": "Just Chatting",
    "viewers": "408"
  },
  {
    "name": "talkto_megoose",
    "game": "World of Tanks",
    "viewers": "406"
  },
  {
    "name": "omidlive",
    "game": "Escape from Tarkov",
    "viewers": "406"
  },
  {
    "name": "poly",
    "game": "Moonlighter 2: The Endless Vault",
    "viewers": "406"
  },
  {
    "name": "cooldee__",
    "game": "Escape from Tarkov",
    "viewers": "405"
  },
  {
    "name": "geass81",
    "game": "Mobile Legends: Bang Bang",
    "viewers": "404"
  },
  {
    "name": "sndylan",
    "game": "Call of Duty: Black Ops 7",
    "viewers": "404"
  },
  {
    "name": "ariasaki",
    "game": "Teamfight Tactics",
    "viewers": "403"
  },
  {
    "name": "kurolaos",
    "game": "Once Human",
    "viewers": "402"
  },
  {
    "name": "berritv",
    "game": "ARC Raiders",
    "viewers": "401"
  },
  {
    "name": "salomesomething",
    "game": "Silent Hill 2",
    "viewers": "400"
  },
  {
    "name": "totless",
    "game": "VRChat",
    "viewers": "400"
  },
  {
    "name": "arkanightlive",
    "game": "Just Chatting",
    "viewers": "400"
  },
  {
    "name": "socksbx",
    "game": "Super Mario Sunshine",
    "viewers": "398"
  },
  {
    "name": "zoe_0601",
    "game": "Just Chatting",
    "viewers": "398"
  },
  {
    "name": "avacrown_",
    "game": "DJs",
    "viewers": "397"
  },
  {
    "name": "wanessawolf",
    "game": "Just Chatting",
    "viewers": "397"
  },
  {
    "name": "kurolily",
    "game": "The Alters",
    "viewers": "396"
  },
  {
    "name": "crayon_fps",
    "game": "Deadlock",
    "viewers": "395"
  },
  {
    "name": "nakoo_fn",
    "game": "Fortnite",
    "viewers": "395"
  },
  {
    "name": "gordox",
    "game": "League of Legends",
    "viewers": "394"
  },
  {
    "name": "dannomercy__",
    "game": "Dead by Daylight",
    "viewers": "393"
  },
  {
    "name": "telasconews",
    "game": "Grand Theft Auto V",
    "viewers": "393"
  },
  {
    "name": "vodkaskndr",
    "game": "Enshrouded",
    "viewers": "393"
  },
  {
    "name": "dear_hellgirl",
    "game": "Supermarket Simulator",
    "viewers": "393"
  },
  {
    "name": "vlouue",
    "game": "DJs",
    "viewers": "392"
  },
  {
    "name": "ramez05",
    "game": "Where Winds Meet",
    "viewers": "392"
  },
  {
    "name": "sh4rin",
    "game": "League of Legends",
    "viewers": "391"
  },
  {
    "name": "laderrickjrr",
    "game": "Madden NFL 26",
    "viewers": "389"
  },
  {
    "name": "monagua",
    "game": "Summoners War: Sky Arena",
    "viewers": "388"
  },
  {
    "name": "ellum",
    "game": "VALORANT",
    "viewers": "388"
  },
  {
    "name": "pureexde",
    "game": "Grand Theft Auto V",
    "viewers": "386"
  },
  {
    "name": "arrowli",
    "game": "Guild Wars 2",
    "viewers": "386"
  },
  {
    "name": "mandrake",
    "game": "Virtual Casino",
    "viewers": "386"
  },
  {
    "name": "mdmdaiane",
    "game": "Farm Frenzy 2",
    "viewers": "385"
  },
  {
    "name": "saintvicious",
    "game": "Teamfight Tactics",
    "viewers": "385"
  },
  {
    "name": "hucokagot",
    "game": "",
    "viewers": "385"
  },
  {
    "name": "smurf_tv",
    "game": "ARC Raiders",
    "viewers": "384"
  },
  {
    "name": "sarahkey",
    "game": "The Legend of Heroes: Trails in the Sky SC",
    "viewers": "384"
  },
  {
    "name": "werster",
    "game": "Pokémon HeartGold/SoulSilver",
    "viewers": "384"
  },
  {
    "name": "assodiroma_official",
    "game": "Sports",
    "viewers": "383"
  },
  {
    "name": "megamuoficial",
    "game": "MU Online",
    "viewers": "383"
  },
  {
    "name": "kaos_angel",
    "game": "League of Legends",
    "viewers": "383"
  },
  {
    "name": "djrtx",
    "game": "DJs",
    "viewers": "382"
  },
  {
    "name": "fridge",
    "game": "Fortnite",
    "viewers": "381"
  },
  {
    "name": "niisa",
    "game": "A.I.L.A",
    "viewers": "381"
  },
  {
    "name": "mistressmayhemmm",
    "game": "ASMR",
    "viewers": "380"
  },
  {
    "name": "sefirotks",
    "game": "Dead by Daylight",
    "viewers": "379"
  },
  {
    "name": "captainsparklez",
    "game": "Minecraft",
    "viewers": "376"
  },
  {
    "name": "ambush",
    "game": "Hollow Knight",
    "viewers": "376"
  },
  {
    "name": "thefeloz",
    "game": "Fortnite",
    "viewers": "376"
  },
  {
    "name": "mortalsmurph",
    "game": "RimWorld",
    "viewers": "376"
  },
  {
    "name": "priscillaliaud",
    "game": "Just Chatting",
    "viewers": "376"
  },
  {
    "name": "granny",
    "game": "Bayonetta",
    "viewers": "375"
  },
  {
    "name": "zeegers",
    "game": "Arena Breakout: Infinite",
    "viewers": "375"
  },
  {
    "name": "epictightpants",
    "game": "Phasmophobia",
    "viewers": "374"
  },
  {
    "name": "karasmai",
    "game": "League of Legends",
    "viewers": "373"
  },
  {
    "name": "filfeel",
    "game": "Hearthstone",
    "viewers": "373"
  },
  {
    "name": "freygaret",
    "game": "Vampire: The Masquerade - Bloodlines 2",
    "viewers": "372"
  },
  {
    "name": "brobbenlive",
    "game": "Overwatch 2",
    "viewers": "372"
  },
  {
    "name": "caresapo",
    "game": "League of Legends",
    "viewers": "372"
  },
  {
    "name": "ravenalternative",
    "game": "Just Chatting",
    "viewers": "370"
  },
  {
    "name": "olaczka",
    "game": "Counter-Strike",
    "viewers": "369"
  },
  {
    "name": "lapoblet",
    "game": "Minecraft",
    "viewers": "369"
  },
  {
    "name": "pinkdonutx",
    "game": "Just Chatting",
    "viewers": "368"
  },
  {
    "name": "lulyfpps",
    "game": "Just Chatting",
    "viewers": "367"
  },
  {
    "name": "internetcityarcade",
    "game": "Just Chatting",
    "viewers": "366"
  },
  {
    "name": "duky",
    "game": "MapleStory",
    "viewers": "366"
  },
  {
    "name": "mbytes37",
    "game": "EA Sports FC 26",
    "viewers": "366"
  },
  {
    "name": "littlesiha",
    "game": "Mass Effect Legendary Edition",
    "viewers": "366"
  },
  {
    "name": "chawndo",
    "game": "Genshin Impact",
    "viewers": "365"
  },
  {
    "name": "muzz",
    "game": "Fortnite",
    "viewers": "365"
  },
  {
    "name": "andy",
    "game": "The Legend of Zelda: A Link to the Past",
    "viewers": "365"
  },
  {
    "name": "pulgaboy",
    "game": "Fortnite",
    "viewers": "365"
  },
  {
    "name": "n3vschet",
    "game": "Grand Theft Auto V",
    "viewers": "365"
  },
  {
    "name": "durpee82",
    "game": "Overwatch 2",
    "viewers": "364"
  },
  {
    "name": "batemanl9",
    "game": "League of Legends",
    "viewers": "364"
  },
  {
    "name": "shadowatnoon",
    "game": "Kirby Air Riders",
    "viewers": "363"
  },
  {
    "name": "aceofspades",
    "game": "Overwatch 2",
    "viewers": "363"
  },
  {
    "name": "racoon_hub",
    "game": "Slots",
    "viewers": "362"
  },
  {
    "name": "ikoneec",
    "game": "DayZ",
    "viewers": "361"
  },
  {
    "name": "gp_tv",
    "game": "Dispatch",
    "viewers": "360"
  },
  {
    "name": "aches_gaming",
    "game": "ARC Raiders",
    "viewers": "359"
  },
  {
    "name": "cicciotvv",
    "game": "Just Chatting",
    "viewers": "358"
  },
  {
    "name": "lilmorro_",
    "game": "Just Chatting",
    "viewers": "358"
  },
  {
    "name": "rawdogmoon",
    "game": "VALORANT",
    "viewers": "357"
  },
  {
    "name": "carioklol",
    "game": "League of Legends",
    "viewers": "357"
  },
  {
    "name": "th3beardedbaron",
    "game": "Phasmophobia",
    "viewers": "356"
  },
  {
    "name": "lanje_live",
    "game": "World of Warcraft",
    "viewers": "356"
  },
  {
    "name": "jogabilidade",
    "game": "Talk Shows & Podcasts",
    "viewers": "356"
  },
  {
    "name": "dub_ok_tv",
    "game": " SEKIRO: SHADOWS DIE TWICE",
    "viewers": "354"
  },
  {
    "name": "6cyx",
    "game": "Overwatch 2",
    "viewers": "353"
  },
  {
    "name": "neenoh",
    "game": "ARC Raiders",
    "viewers": "353"
  },
  {
    "name": "jayden",
    "game": "League of Legends",
    "viewers": "352"
  },
  {
    "name": "saselandiadirectos",
    "game": "Just Chatting",
    "viewers": "352"
  },
  {
    "name": "viibiin",
    "game": "Escape from Tarkov",
    "viewers": "352"
  },
  {
    "name": "elgato",
    "game": "Just Chatting",
    "viewers": "351"
  },
  {
    "name": "evil_granny",
    "game": "Mir Tankov",
    "viewers": "351"
  },
  {
    "name": "breebunn",
    "game": "Lies of P",
    "viewers": "351"
  },
  {
    "name": "bardehaus",
    "game": "Battlefield 6",
    "viewers": "351"
  },
  {
    "name": "skullvolver",
    "game": "Cruelty Squad",
    "viewers": "351"
  },
  {
    "name": "oruipinto",
    "game": "Counter-Strike",
    "viewers": "350"
  },
  {
    "name": "encourage45",
    "game": "Call of Duty: Black Ops 7",
    "viewers": "350"
  },
  {
    "name": "wakiwaki612",
    "game": "ARC Raiders",
    "viewers": "349"
  },
  {
    "name": "goatgeezy",
    "game": "Madden NFL 26",
    "viewers": "349"
  },
  {
    "name": "skittlz",
    "game": "Tom Clancy's Rainbow Six Siege X",
    "viewers": "349"
  },
  {
    "name": "suyummy",
    "game": "ASMR",
    "viewers": "349"
  },
  {
    "name": "rengawr",
    "game": "Escape from Tarkov",
    "viewers": "349"
  },
  {
    "name": "kaileymae",
    "game": "Just Chatting",
    "viewers": "349"
  },
  {
    "name": "nawi",
    "game": "League of Legends",
    "viewers": "348"
  },
  {
    "name": "jadealy",
    "game": "Where Winds Meet",
    "viewers": "348"
  },
  {
    "name": "chenchen53",
    "game": "League of Legends",
    "viewers": "347"
  },
  {
    "name": "purrjectyui",
    "game": "Just Chatting",
    "viewers": "347"
  },
  {
    "name": "koreanbjfans",
    "game": "Just Chatting",
    "viewers": "347"
  },
  {
    "name": "lanancy__",
    "game": "ASMR",
    "viewers": "346"
  },
  {
    "name": "d00mwake",
    "game": "Magic: The Gathering",
    "viewers": "345"
  },
  {
    "name": "summyahmarie",
    "game": "Just Chatting",
    "viewers": "345"
  },
  {
    "name": "jalensworld_",
    "game": "Just Chatting",
    "viewers": "345"
  },
  {
    "name": "heboxjonge",
    "game": "Old School RuneScape",
    "viewers": "345"
  },
  {
    "name": "thehydrogen",
    "game": "League of Legends",
    "viewers": "345"
  },
  {
    "name": "rumathrawrr",
    "game": "World of Warcraft",
    "viewers": "344"
  },
  {
    "name": "cocaoo_",
    "game": "Escape from Tarkov",
    "viewers": "344"
  },
  {
    "name": "pgod",
    "game": "Rust",
    "viewers": "344"
  },
  {
    "name": "killoress",
    "game": "Casino Simulator",
    "viewers": "343"
  },
  {
    "name": "vulpixie",
    "game": "Kirby Air Riders",
    "viewers": "343"
  },
  {
    "name": "fahhkies",
    "game": "Just Chatting",
    "viewers": "343"
  },
  {
    "name": "fuxelbau",
    "game": "ARC Raiders",
    "viewers": "342"
  },
  {
    "name": "teuzz",
    "game": "Fortnite",
    "viewers": "342"
  },
  {
    "name": "wbcclub",
    "game": "Crypto",
    "viewers": "341"
  },
  {
    "name": "llegendry",
    "game": "Marvel Rivals",
    "viewers": "341"
  },
  {
    "name": "gerbrowny",
    "game": "My Summer Car",
    "viewers": "341"
  },
  {
    "name": "miamakesmusic",
    "game": "Music",
    "viewers": "341"
  },
  {
    "name": "albatrox18",
    "game": "Path of Exile",
    "viewers": "341"
  },
  {
    "name": "doogile",
    "game": "Minecraft",
    "viewers": "341"
  },
  {
    "name": "murloka",
    "game": "Albion Online",
    "viewers": "340"
  },
  {
    "name": "billycriz",
    "game": "Just Chatting",
    "viewers": "340"
  },
  {
    "name": "jenntacles",
    "game": "Escape from Tarkov",
    "viewers": "340"
  },
  {
    "name": "laserbelch",
    "game": "Fire Emblem: The Blazing Blade",
    "viewers": "340"
  },
  {
    "name": "givinglifetop",
    "game": "World of Warcraft",
    "viewers": "339"
  },
  {
    "name": "anaaja",
    "game": "Minecraft",
    "viewers": "339"
  },
  {
    "name": "kamuslol",
    "game": "The Last of Us Part II",
    "viewers": "338"
  },
  {
    "name": "brederodess",
    "game": "Tibia",
    "viewers": "338"
  },
  {
    "name": "angrypug",
    "game": "Dead by Daylight",
    "viewers": "338"
  },
  {
    "name": "swooty18",
    "game": "Call of Duty: Black Ops 7",
    "viewers": "337"
  },
  {
    "name": "middleditch",
    "game": "Just Chatting",
    "viewers": "337"
  },
  {
    "name": "rosiebellmoo",
    "game": "Just Chatting",
    "viewers": "336"
  },
  {
    "name": "carol",
    "game": "Just Chatting",
    "viewers": "335"
  },
  {
    "name": "sneakylol",
    "game": "Escape from Tarkov",
    "viewers": "335"
  },
  {
    "name": "fgrav_",
    "game": "DARK SOULS III",
    "viewers": "334"
  },
  {
    "name": "immarksman",
    "game": "Call of Duty: Black Ops 7",
    "viewers": "334"
  },
  {
    "name": "kneand69",
    "game": "Madden NFL 26",
    "viewers": "334"
  },
  {
    "name": "bilalkamarieh7",
    "game": "Just Chatting",
    "viewers": "334"
  },
  {
    "name": "compl1cs",
    "game": "Counter-Strike",
    "viewers": "333"
  },
  {
    "name": "gennci",
    "game": "Counter-Strike",
    "viewers": "333"
  },
  {
    "name": "zigueira",
    "game": "Arena Breakout: Infinite",
    "viewers": "333"
  },
  {
    "name": "knebel_de",
    "game": "Star Citizen",
    "viewers": "333"
  },
  {
    "name": "imba__tv",
    "game": "EA Sports FC 26",
    "viewers": "333"
  },
  {
    "name": "capcomfighters",
    "game": "Street Fighter 6",
    "viewers": "333"
  },
  {
    "name": "namvseyasno",
    "game": "Just Chatting",
    "viewers": "332"
  },
  {
    "name": "airwingmarine",
    "game": "Escape from Tarkov",
    "viewers": "332"
  },
  {
    "name": "rz_brozervgds",
    "game": "Garry's Mod",
    "viewers": "332"
  },
  {
    "name": "sharonqueen",
    "game": "ASMR",
    "viewers": "327"
  },
  {
    "name": "rallied",
    "game": "Call of Duty: Warzone",
    "viewers": "327"
  },
  {
    "name": "xeus1tap",
    "game": "VALORANT",
    "viewers": "326"
  },
  {
    "name": "mainfinitytv",
    "game": "Just Chatting",
    "viewers": "324"
  },
  {
    "name": "leffen",
    "game": "2XKO",
    "viewers": "324"
  },
  {
    "name": "calliecalico",
    "game": "Grand Theft Auto IV",
    "viewers": "324"
  },
  {
    "name": "eunamiku",
    "game": "ASMR",
    "viewers": "323"
  },
  {
    "name": "hoppii",
    "game": "Just Chatting",
    "viewers": "322"
  },
  {
    "name": "terlosawyerhx",
    "game": "Mafia: The Old Country",
    "viewers": "322"
  },
  {
    "name": "moumousx",
    "game": "Grand Theft Auto V",
    "viewers": "322"
  },
  {
    "name": "blooprint",
    "game": "ARC Raiders",
    "viewers": "322"
  },
  {
    "name": "lizok_ssk",
    "game": "Dota 2",
    "viewers": "320"
  },
  {
    "name": "vampykinz",
    "game": "Just Chatting",
    "viewers": "319"
  },
  {
    "name": "dj_headschot",
    "game": "Grand Theft Auto V",
    "viewers": "319"
  },
  {
    "name": "mst3k",
    "game": "Always On",
    "viewers": "318"
  },
  {
    "name": "brozime",
    "game": "Duet Night Abyss",
    "viewers": "318"
  },
  {
    "name": "galaxyyk",
    "game": "MARVEL Cosmic Invasion",
    "viewers": "318"
  },
  {
    "name": "smitegame",
    "game": "SMITE 2",
    "viewers": "318"
  },
  {
    "name": "auroralgames",
    "game": "Software and Game Development",
    "viewers": "318"
  },
  {
    "name": "niikoletaa",
    "game": "League of Legends",
    "viewers": "318"
  },
  {
    "name": "reiyuguigui",
    "game": "Homicipher",
    "viewers": "318"
  },
  {
    "name": "narelio",
    "game": "Black Desert",
    "viewers": "317"
  },
  {
    "name": "rouszztrash",
    "game": "Dota 2",
    "viewers": "317"
  },
  {
    "name": "mino56",
    "game": "IRL",
    "viewers": "317"
  },
  {
    "name": "pinzo",
    "game": "Predecessor",
    "viewers": "316"
  },
  {
    "name": "furkcs",
    "game": "Virtual Casino",
    "viewers": "316"
  },
  {
    "name": "sebo",
    "game": "World of Warcraft",
    "viewers": "316"
  },
  {
    "name": "drdynastic",
    "game": "Out of the Park Baseball 26",
    "viewers": "316"
  },
  {
    "name": "shiishak",
    "game": "Dota 2",
    "viewers": "316"
  },
  {
    "name": "bogush",
    "game": "Dota 2",
    "viewers": "315"
  },
  {
    "name": "blue_kao",
    "game": "FINAL FANTASY XIV ONLINE",
    "viewers": "315"
  },
  {
    "name": "parlayp_sports",
    "game": "Sports",
    "viewers": "314"
  },
  {
    "name": "xdavemon",
    "game": "League of Legends",
    "viewers": "313"
  },
  {
    "name": "norgannonhh",
    "game": "ARC Raiders",
    "viewers": "312"
  },
  {
    "name": "loalalunadj",
    "game": "DJs",
    "viewers": "312"
  },
  {
    "name": "languagehacker",
    "game": "Hearthstone",
    "viewers": "311"
  },
  {
    "name": "vertiigogaming",
    "game": "ARC Raiders",
    "viewers": "310"
  },
  {
    "name": "mpx_player",
    "game": "Call of Duty: Warzone",
    "viewers": "310"
  },
  {
    "name": "stolenbr",
    "game": "Battlefield REDSEC",
    "viewers": "310"
  },
  {
    "name": "mills",
    "game": "EA Sports College Football 26",
    "viewers": "309"
  },
  {
    "name": "marvincalifornia",
    "game": "Just Chatting",
    "viewers": "309"
  },
  {
    "name": "s3kox",
    "game": "Rust",
    "viewers": "309"
  },
  {
    "name": "longlivequebec",
    "game": "Kingdom Come: Deliverance II",
    "viewers": "308"
  },
  {
    "name": "freckleston1",
    "game": "Call of Duty: Black Ops 7",
    "viewers": "308"
  },
  {
    "name": "tonytheduff",
    "game": "Dead by Daylight",
    "viewers": "308"
  },
  {
    "name": "client",
    "game": "Grand Theft Auto V",
    "viewers": "307"
  },
  {
    "name": "simonizeshow",
    "game": "World of Warcraft",
    "viewers": "306"
  },
  {
    "name": "yunalescka",
    "game": "Trails in the Sky 1st Chapter",
    "viewers": "306"
  },
  {
    "name": "repullze",
    "game": "Call of Duty: Warzone",
    "viewers": "306"
  },
  {
    "name": "khadim",
    "game": "Grand Theft Auto V",
    "viewers": "306"
  },
  {
    "name": "retrolongplay",
    "game": "Retro",
    "viewers": "306"
  },
  {
    "name": "opesanec",
    "game": "Teamfight Tactics",
    "viewers": "306"
  },
  {
    "name": "joepags",
    "game": "Talk Shows & Podcasts",
    "viewers": "305"
  },
  {
    "name": "yeatle",
    "game": "Overwatch 2",
    "viewers": "305"
  },
  {
    "name": "siormax",
    "game": "The Hobbit",
    "viewers": "305"
  },
  {
    "name": "phalanks666",
    "game": "Knight Online",
    "viewers": "304"
  },
  {
    "name": "burtsbeat",
    "game": "Just Chatting",
    "viewers": "303"
  },
  {
    "name": "charlitoss",
    "game": "Just Chatting",
    "viewers": "303"
  },
  {
    "name": "puppiestummies",
    "game": "Minecraft",
    "viewers": "303"
  },
  {
    "name": "douglassola",
    "game": "Dispatch",
    "viewers": "302"
  },
  {
    "name": "goorilaa",
    "game": "Call of Duty: Black Ops 7",
    "viewers": "302"
  },
  {
    "name": "ariesakana",
    "game": "Minecraft",
    "viewers": "302"
  },
  {
    "name": "drunge_",
    "game": "Aion 2",
    "viewers": "302"
  },
  {
    "name": "marcuskron",
    "game": "Minecraft",
    "viewers": "301"
  },
  {
    "name": "d1straite",
    "game": "Counter-Strike",
    "viewers": "301"
  },
  {
    "name": "thersguy",
    "game": "RuneScape",
    "viewers": "300"
  },
  {
    "name": "chorifletes",
    "game": "Just Chatting",
    "viewers": "300"
  },
  {
    "name": "deusotbr",
    "game": "Tibia",
    "viewers": "299"
  },
  {
    "name": "maddynf",
    "game": "Fortnite",
    "viewers": "299"
  },
  {
    "name": "andre_moraph",
    "game": "Art",
    "viewers": "299"
  },
  {
    "name": "nexxossgaming",
    "game": "Mount & Blade II: Bannerlord",
    "viewers": "299"
  },
  {
    "name": "alldaynyc",
    "game": "Just Chatting",
    "viewers": "299"
  },
  {
    "name": "juakynen",
    "game": "Sports",
    "viewers": "298"
  },
  {
    "name": "jmarianne",
    "game": "Co-working & Studying",
    "viewers": "298"
  },
  {
    "name": "chiches",
    "game": "Cowboy Life Simulator",
    "viewers": "297"
  },
  {
    "name": "veohz",
    "game": "Call of Duty: Black Ops 7",
    "viewers": "297"
  },
  {
    "name": "floowzinfps",
    "game": "Virtual Casino",
    "viewers": "297"
  },
  {
    "name": "hugo_one",
    "game": "Grand Theft Auto: San Andreas",
    "viewers": "296"
  },
  {
    "name": "blueberrygabi",
    "game": "Escape from Tarkov",
    "viewers": "296"
  },
  {
    "name": "deemonrider",
    "game": "Pokémon Community Game",
    "viewers": "296"
  },
  {
    "name": "basilwoof",
    "game": "Art",
    "viewers": "295"
  },
  {
    "name": "oisakura",
    "game": "Just Chatting",
    "viewers": "295"
  },
  {
    "name": "dante_will",
    "game": "Just Chatting",
    "viewers": "295"
  },
  {
    "name": "johnmendesfun",
    "game": "Grand Theft Auto V",
    "viewers": "295"
  },
  {
    "name": "waayz1n",
    "game": "Virtual Casino",
    "viewers": "294"
  },
  {
    "name": "v1nchenso7",
    "game": "Counter-Strike",
    "viewers": "294"
  },
  {
    "name": "starsmitten",
    "game": "Teamfight Tactics",
    "viewers": "294"
  },
  {
    "name": "punchy",
    "game": "Resident Evil: Revelations 2",
    "viewers": "294"
  },
  {
    "name": "superbutterbuns",
    "game": "Just Chatting",
    "viewers": "293"
  },
  {
    "name": "kelre0n",
    "game": "Red Dead Redemption II",
    "viewers": "293"
  },
  {
    "name": "megga",
    "game": "Crypto",
    "viewers": "293"
  },
  {
    "name": "hyperi1cs2",
    "game": "Counter-Strike",
    "viewers": "292"
  },
  {
    "name": "maddogsleague",
    "game": "Dota 2",
    "viewers": "292"
  },
  {
    "name": "oskar1up",
    "game": "Star Citizen",
    "viewers": "291"
  },
  {
    "name": "helloitsmouse",
    "game": "Kingdom Hearts HD 1.5 + 2.5 ReMIX",
    "viewers": "290"
  },
  {
    "name": "ablkz",
    "game": "Deadlock",
    "viewers": "290"
  },
  {
    "name": "e11ysa",
    "game": "Just Chatting",
    "viewers": "290"
  },
  {
    "name": "linny",
    "game": "Just Chatting",
    "viewers": "289"
  },
  {
    "name": "liviomateusrp",
    "game": "Grand Theft Auto V",
    "viewers": "289"
  },
  {
    "name": "nyunkoro",
    "game": "PowerWash Simulator 2",
    "viewers": "288"
  },
  {
    "name": "cuppcaake",
    "game": "Palia",
    "viewers": "288"
  },
  {
    "name": "streamorris",
    "game": "Just Chatting",
    "viewers": "287"
  },
  {
    "name": "puioff",
    "game": "Just Chatting",
    "viewers": "286"
  },
  {
    "name": "alcemarrp",
    "game": "Grand Theft Auto V",
    "viewers": "286"
  },
  {
    "name": "jupieverse",
    "game": "Palia",
    "viewers": "285"
  },
  {
    "name": "newtypebtw",
    "game": "Warhammer 40,000: Darktide",
    "viewers": "285"
  },
  {
    "name": "zarbex_tv",
    "game": "Just Chatting",
    "viewers": "285"
  },
  {
    "name": "myaustinwhite",
    "game": "Just Chatting",
    "viewers": "285"
  },
  {
    "name": "tayoh_",
    "game": "Garry's Mod",
    "viewers": "285"
  },
  {
    "name": "pumacddrj",
    "game": "Grand Theft Auto V",
    "viewers": "284"
  },
  {
    "name": "quesadacid",
    "game": "Just Chatting",
    "viewers": "283"
  },
  {
    "name": "madnezzzzzzzz",
    "game": "PLAYERUNKNOWN'S BATTLEGROUNDS Mobile",
    "viewers": "283"
  },
  {
    "name": "streamdatabase",
    "game": "Tom Clancy's Rainbow Six Siege X",
    "viewers": "283"
  },
  {
    "name": "milquetoast_claire",
    "game": "Project Zomboid",
    "viewers": "281"
  },
  {
    "name": "f639olya",
    "game": "Just Chatting",
    "viewers": "280"
  },
  {
    "name": "cotonete",
    "game": "Grand Theft Auto V",
    "viewers": "280"
  },
  {
    "name": "popsbarngrill",
    "game": "World of Warcraft",
    "viewers": "280"
  },
  {
    "name": "hiimsky",
    "game": "Overwatch 2",
    "viewers": "279"
  },
  {
    "name": "splashy",
    "game": "NBA 2K26",
    "viewers": "279"
  },
  {
    "name": "justfunkyy",
    "game": "Outlast",
    "viewers": "279"
  },
  {
    "name": "thisispnr",
    "game": "NBA 2K26",
    "viewers": "279"
  },
  {
    "name": "s_chilla",
    "game": "Counter-Strike",
    "viewers": "278"
  }
]